Workbook

Sheet Data Pegawai
A1: No | B1: NAMA | C1: Status Aktif | D1: Jenis | E1: JAD | F1: PRODI/BAGIAN | G1: NIP YPT | H1: NIDN | I1: NUPTK | J1: STATUS | K1: GELAR DEPAN | L1: GELAR BELAKANG | M1: PENDIDIKAN | N1: TMT MASUK | O1: TMT Keluar | P1: MASA KERJA DOSEN | Q1: Email | R1: No HP | S1: ALAMAT
A2: 1 | B2: Bambang Agus Sumantri | C2: Aktif | D2: Dosen | E2: =IF(D2="DOSEN",VLOOKUP(B2,Dosen!B:Z,11,FALSE),VLOOKUP(B2,TPA!B:Z,7,FALSE)) -> L | F2: Digital Bisnis | G2: 24800005 | H2: 730088001 | I2: 9162758659130123 | J2: =IF(D2="DOSEN",VLOOKUP(B2,Dosen!B:Z,7,FALSE),VLOOKUP(B2,TPA!B:Z,5,FALSE)) -> PROFESIONAL | K2: Dr.M. | L2: S.IP., M.M. | M2: =IF(D2="DOSEN",VLOOKUP(B2,Dosen!B:ZZ,33,FALSE),VLOOKUP(B2,TPA!B:ZZ,44,FALSE)) -> S3 | N2: 45544 | P2: =IF(O2="",DATEDIF(N2,TODAY(),"y")&" tahun "&DATEDIF(N2,TODAY(),"ym")&" bulan ",DATEDIF(N2,O2,"y")&" tahun "&DATEDIF(N2,O2,"ym")&" bulan ") -> 1 tahun 4 bulan | Q2: bambang.sumantri@mhs.unsoed.ac.id | R2: 85235684085 | S2: Dusun Wonorejo RT/RW 004/002 Desa Semanding Kec. PaguKab. Kediri | T2: =VLOOKUP(B3,Dosen!B:Z,11,FALSE) -> AA
A3: 2 | B3: Darlin Aulia | C3: Aktif | D3: Dosen | E3: =IF(D3="DOSEN",VLOOKUP(B3,Dosen!B:Z,11,FALSE),VLOOKUP(B3,TPA!B:Z,7,FALSE)) -> AA | F3: Digital Bisnis | G3: 22920004 | H3: 309069201 | I3: 2941770671230372 | J3: =IF(D3="DOSEN",VLOOKUP(B3,Dosen!B:Z,7,FALSE),VLOOKUP(B3,TPA!B:Z,5,FALSE)) -> PROFESIONAL | L3: S. E., M.S.Ak. | M3: =IF(D3="DOSEN",VLOOKUP(B3,Dosen!B:ZZ,33,FALSE),VLOOKUP(B3,TPA!B:ZZ,44,FALSE)) -> S2 | N3: 44627 | P3: =IF(O3="",DATEDIF(N3,TODAY(),"y")&" tahun "&DATEDIF(N3,TODAY(),"ym")&" bulan ",DATEDIF(N3,O3,"y")&" tahun "&DATEDIF(N3,O3,"ym")&" bulan ") -> 3 tahun 10 bulan | Q3: darlin.aulia@ittelkom-sby.ac.id | R3: 82122074533 | S3: Jl. Sentot Prawirodhirjo XIV/70, Jember Kidul, Kaliwates, Jember
A4: 3 | B4: Dominggo Bayu Baskara | C4: Aktif | D4: Dosen | E4: =IF(D4="DOSEN",VLOOKUP(B4,Dosen!B:Z,11,FALSE),VLOOKUP(B4,TPA!B:Z,7,FALSE)) -> AA | F4: Digital Bisnis | G4: 19900005 | H4: 722069004 | I4: 6954768669130292 | J4: =IF(D4="DOSEN",VLOOKUP(B4,Dosen!B:Z,7,FALSE),VLOOKUP(B4,TPA!B:Z,5,FALSE)) -> TETAP | K4: Ir. | L4: S.T., M.MT. | M4: =IF(D4="DOSEN",VLOOKUP(B4,Dosen!B:ZZ,33,FALSE),VLOOKUP(B4,TPA!B:ZZ,44,FALSE)) -> S2 | N4: 43101 | P4: =IF(O4="",DATEDIF(N4,TODAY(),"y")&" tahun "&DATEDIF(N4,TODAY(),"ym")&" bulan ",DATEDIF(N4,O4,"y")&" tahun "&DATEDIF(N4,O4,"ym")&" bulan ") -> 8 tahun 0 bulan | Q4: domi@ittelkom-sby.ac.id | R4: 85230001444 | S4: Jl. Palem Selatan II MC/163, Waru, Sidoarjo, Jawa Timur 61256
A5: 4 | B5: Sekar Widyasari Putri | C5: Aktif | D5: Dosen | E5: =IF(D5="DOSEN",VLOOKUP(B5,Dosen!B:Z,11,FALSE),VLOOKUP(B5,TPA!B:Z,7,FALSE)) -> AA | F5: Digital Bisnis | G5: 24930005 | H5: 704029302 | I5: 0536771672230252 | J5: =IF(D5="DOSEN",VLOOKUP(B5,Dosen!B:Z,7,FALSE),VLOOKUP(B5,TPA!B:Z,5,FALSE)) -> TETAP | L5: S.A.B., M.Si. | M5: =IF(D5="DOSEN",VLOOKUP(B5,Dosen!B:ZZ,33,FALSE),VLOOKUP(B5,TPA!B:ZZ,44,FALSE)) -> S2 | N5: 44166 | P5: =IF(O5="",DATEDIF(N5,TODAY(),"y")&" tahun "&DATEDIF(N5,TODAY(),"ym")&" bulan ",DATEDIF(N5,O5,"y")&" tahun "&DATEDIF(N5,O5,"ym")&" bulan ") -> 5 tahun 1 bulan | Q5: sekar@ittelkom-sby.ac.id | R5: 81334448548 | S5: Jl. Plamongan Indah Blok G3 No. 24, Batusari, Mranggen, Demak
A6: 5 | B6: Riza Akhsani Setyo Prayoga | C6: Non-Aktif | D6: Dosen | E6: =IF(D6="DOSEN",VLOOKUP(B6,Dosen!B:Z,11,FALSE),VLOOKUP(B6,TPA!B:Z,7,FALSE)) -> AA | F6: Digital Bisnis | G6: 20940041 | H6: 730049402 | J6: =IF(D6="DOSEN",VLOOKUP(B6,Dosen!B:Z,7,FALSE),VLOOKUP(B6,TPA!B:Z,5,FALSE)) -> PROFESIONAL | L6: S.Kom., M.MT. | M6: =IF(D6="DOSEN",VLOOKUP(B6,Dosen!B:ZZ,33,FALSE),VLOOKUP(B6,TPA!B:ZZ,44,FALSE)) -> S2 | N6: 44166 | O6: 45473 | P6: =IF(O6="",DATEDIF(N6,TODAY(),"y")&" tahun "&DATEDIF(N6,TODAY(),"ym")&" bulan ",DATEDIF(N6,O6,"y")&" tahun "&DATEDIF(N6,O6,"ym")&" bulan ") -> 3 tahun 6 bulan | Q6: rizayoga30@ittelkom-sby.ac.id | R6: 81286153175 | S6: Jl. Ukel GG 1 No. 26, Kertosari, Babadan, Ponorogo
A7: 6 | B7: Caesareano Lafado Yesa | C7: Aktif | D7: Dosen | E7: =IF(D7="DOSEN",VLOOKUP(B7,Dosen!B:Z,11,FALSE),VLOOKUP(B7,TPA!B:Z,7,FALSE)) -> AA | F7: Digital Bisnis | G7: 15890076 | H7: 708128901 | I7: 7540767668130283 | J7: =IF(D7="DOSEN",VLOOKUP(B7,Dosen!B:Z,7,FALSE),VLOOKUP(B7,TPA!B:Z,5,FALSE)) -> TETAP | L7: S.M.B., M.M. | M7: =IF(D7="DOSEN",VLOOKUP(B7,Dosen!B:ZZ,33,FALSE),VLOOKUP(B7,TPA!B:ZZ,44,FALSE)) -> S2 | N7: 44652 | P7: =IF(O7="",DATEDIF(N7,TODAY(),"y")&" tahun "&DATEDIF(N7,TODAY(),"ym")&" bulan ",DATEDIF(N7,O7,"y")&" tahun "&DATEDIF(N7,O7,"ym")&" bulan ") -> 3 tahun 9 bulan | Q7: anofado@ittelkom-sby.ac.id | R7: 81214806006 | S7: Jl. Eka Surya Gg. Eka Dewi No. 2A, Gedung Johor, Medan Johor, Medan
A8: 7 | B8: Titus Kristanto | C8: Aktif | D8: Dosen | E8: =IF(D8="DOSEN",VLOOKUP(B8,Dosen!B:Z,11,FALSE),VLOOKUP(B8,TPA!B:Z,7,FALSE)) -> L | F8: Digital Bisnis | G8: 20860014 | H8: 710028604 | I8: 7542764665137062 | J8: =IF(D8="DOSEN",VLOOKUP(B8,Dosen!B:Z,7,FALSE),VLOOKUP(B8,TPA!B:Z,5,FALSE)) -> TETAP | L8: S.Kom., M.Kom. | M8: =IF(D8="DOSEN",VLOOKUP(B8,Dosen!B:ZZ,33,FALSE),VLOOKUP(B8,TPA!B:ZZ,44,FALSE)) -> S2 | N8: 43282 | P8: =IF(O8="",DATEDIF(N8,TODAY(),"y")&" tahun "&DATEDIF(N8,TODAY(),"ym")&" bulan ",DATEDIF(N8,O8,"y")&" tahun "&DATEDIF(N8,O8,"ym")&" bulan ") -> 7 tahun 6 bulan | Q8: titus.kristanto@ittelkom-sby.ac.id | R8: 81325019978 | S8: Jl. Darmo Indah Selatan 3 Blok GG-25 Surabaya
A9: 8 | B9: Agoes Windarto | C9: Aktif | D9: Dosen | E9: =IF(D9="DOSEN",VLOOKUP(B9,Dosen!B:Z,11,FALSE),VLOOKUP(B9,TPA!B:Z,7,FALSE)) -> AA | F9: Digital Bisnis | G9: 15720039 | H9: 8961580023 | I9: 1138750652130163 | J9: =IF(D9="DOSEN",VLOOKUP(B9,Dosen!B:Z,7,FALSE),VLOOKUP(B9,TPA!B:Z,5,FALSE)) -> PERBANTUAN | L9: S.T., M.M. | M9: =IF(D9="DOSEN",VLOOKUP(B9,Dosen!B:ZZ,33,FALSE),VLOOKUP(B9,TPA!B:ZZ,44,FALSE)) -> S2 | N9: 44562 | P9: =IF(O9="",DATEDIF(N9,TODAY(),"y")&" tahun "&DATEDIF(N9,TODAY(),"ym")&" bulan ",DATEDIF(N9,O9,"y")&" tahun "&DATEDIF(N9,O9,"ym")&" bulan ") -> 4 tahun 0 bulan | Q9: agoeswindarto@ittelkom-sby.ac.id | R9: 81334395366 | S9: Graha Asri Sukodono, Pekarungan, Sidoarjo
A10: 9 | B10: Wachda Yuniar Rochmah | C10: Aktif | D10: Dosen | E10: =IF(D10="DOSEN",VLOOKUP(B10,Dosen!B:Z,11,FALSE),VLOOKUP(B10,TPA!B:Z,7,FALSE)) -> AA | F10: Digital Bisnis | G10: 22970043 | H10: 701069701 | I10: 6933775676230162 | J10: =IF(D10="DOSEN",VLOOKUP(B10,Dosen!B:Z,7,FALSE),VLOOKUP(B10,TPA!B:Z,5,FALSE)) -> PROFESIONAL | L10: S.M., M.M. | M10: =IF(D10="DOSEN",VLOOKUP(B10,Dosen!B:ZZ,33,FALSE),VLOOKUP(B10,TPA!B:ZZ,44,FALSE)) -> S2 | N10: 44832 | P10: =IF(O10="",DATEDIF(N10,TODAY(),"y")&" tahun "&DATEDIF(N10,TODAY(),"ym")&" bulan ",DATEDIF(N10,O10,"y")&" tahun "&DATEDIF(N10,O10,"ym")&" bulan ") -> 3 tahun 3 bulan | Q10: wachdayuniar@ittelkom-sby.ac.id | R10: 82234320272 | S10: Mojoranu, Dander, Bojonegoro
A11: 10 | B11: Adisya Resti Rahmadanti | C11: Non-Aktif | D11: Dosen | E11: =IF(D11="DOSEN",VLOOKUP(B11,Dosen!B:Z,11,FALSE),VLOOKUP(B11,TPA!B:Z,7,FALSE)) -> NJAD | F11: Digital Bisnis | G11: 23990018 | H11: 727019901 | I11: 0459777678230052 | J11: =IF(D11="DOSEN",VLOOKUP(B11,Dosen!B:Z,7,FALSE),VLOOKUP(B11,TPA!B:Z,5,FALSE)) -> PROFESIONAL | L11: S.M., M.A.B. | M11: =IF(D11="DOSEN",VLOOKUP(B11,Dosen!B:ZZ,33,FALSE),VLOOKUP(B11,TPA!B:ZZ,44,FALSE)) -> S2 | N11: 45170 | P11: =IF(O11="",DATEDIF(N11,TODAY(),"y")&" tahun "&DATEDIF(N11,TODAY(),"ym")&" bulan ",DATEDIF(N11,O11,"y")&" tahun "&DATEDIF(N11,O11,"ym")&" bulan ") -> 2 tahun 4 bulan | Q11: adisya@ittelkom-sby.ac.id | R11: 81529137179 | S11: Jl. Gedong Kuning 40A, Jogjakarta, 5517
A12: 11 | B12: Krisnayanti Aditasari | C12: Aktif | D12: Dosen | E12: =IF(D12="DOSEN",VLOOKUP(B12,Dosen!B:Z,11,FALSE),VLOOKUP(B12,TPA!B:Z,7,FALSE)) -> AA | F12: Digital Bisnis | G12: 23990019 | H12: 704069901 | I12: 5936777678230072 | J12: =IF(D12="DOSEN",VLOOKUP(B12,Dosen!B:Z,7,FALSE),VLOOKUP(B12,TPA!B:Z,5,FALSE)) -> PROFESIONAL | L12: S.M., M.MT. | M12: =IF(D12="DOSEN",VLOOKUP(B12,Dosen!B:ZZ,33,FALSE),VLOOKUP(B12,TPA!B:ZZ,44,FALSE)) -> S2 | N12: 45170 | P12: =IF(O12="",DATEDIF(N12,TODAY(),"y")&" tahun "&DATEDIF(N12,TODAY(),"ym")&" bulan ",DATEDIF(N12,O12,"y")&" tahun "&DATEDIF(N12,O12,"ym")&" bulan ") -> 2 tahun 4 bulan | Q12: krisna@ittelkom-sby.ac.id | R12: 81223566959 | S12: Tambak Medokan Ayu XVI / 4, Surabaya, 60295
A13: 12 | B13: Rudi Harianto | C13: Non-Aktif | D13: Dosen | E13: =IF(D13="DOSEN",VLOOKUP(B13,Dosen!B:Z,11,FALSE),VLOOKUP(B13,TPA!B:Z,7,FALSE)) -> AA | F13: Digital Bisnis | G13: 24870001 | H13: 701108702 | J13: =IF(D13="DOSEN",VLOOKUP(B13,Dosen!B:Z,7,FALSE),VLOOKUP(B13,TPA!B:Z,5,FALSE)) -> PROFESIONAL | L13: S.E., M.A. | M13: =IF(D13="DOSEN",VLOOKUP(B13,Dosen!B:ZZ,33,FALSE),VLOOKUP(B13,TPA!B:ZZ,44,FALSE)) -> S2 | N13: 45505 | O13: 45688 | P13: =IF(O13="",DATEDIF(N13,TODAY(),"y")&" tahun "&DATEDIF(N13,TODAY(),"ym")&" bulan ",DATEDIF(N13,O13,"y")&" tahun "&DATEDIF(N13,O13,"ym")&" bulan ") -> 0 tahun 5 bulan | R13: 82123556785 | S13: Sidokapasan 1/54 SBY RT 001 RW 001, Kel. Sidodadi, Kec. Simokerto, Kota Surabaya, Jawa Timur
A14: 13 | B14: N. Azizia Gia Mutiarasari | C14: Aktif | D14: Dosen | E14: =IF(D14="DOSEN",VLOOKUP(B14,Dosen!B:Z,11,FALSE),VLOOKUP(B14,TPA!B:Z,7,FALSE)) -> NJAD | F14: Digital Bisnis | G14: 24970010 | H14: 5149775676230303 | I14: 5149775676230303 | J14: =IF(D14="DOSEN",VLOOKUP(B14,Dosen!B:Z,7,FALSE),VLOOKUP(B14,TPA!B:Z,5,FALSE)) -> PROFESIONAL | L14: S.M., MBA | M14: =IF(D14="DOSEN",VLOOKUP(B14,Dosen!B:ZZ,33,FALSE),VLOOKUP(B14,TPA!B:ZZ,44,FALSE)) -> S3 | N14: 45536 | P14: =IF(O14="",DATEDIF(N14,TODAY(),"y")&" tahun "&DATEDIF(N14,TODAY(),"ym")&" bulan ",DATEDIF(N14,O14,"y")&" tahun "&DATEDIF(N14,O14,"ym")&" bulan ") -> 1 tahun 4 bulan | Q14: giamsari17@gmail.com | R14: 82134623762 | S14: Rejosari RT 003 RT 008, Kel. Sabrang, Kec. Delanggu, Kab. Klaten
A15: 14 | B15: Annisa Ramadhan | C15: Aktif | D15: Dosen | E15: =IF(D15="DOSEN",VLOOKUP(B15,Dosen!B:Z,11,FALSE),VLOOKUP(B15,TPA!B:Z,7,FALSE)) -> NJAD | F15: Digital Bisnis | G15: 25950003 | I15: 7545773674230262 | J15: =IF(D15="DOSEN",VLOOKUP(B15,Dosen!B:Z,7,FALSE),VLOOKUP(B15,TPA!B:Z,5,FALSE)) -> PROFESIONAL | L15: S.Stat. M.Stat. | M15: =IF(D15="DOSEN",VLOOKUP(B15,Dosen!B:ZZ,33,FALSE),VLOOKUP(B15,TPA!B:ZZ,44,FALSE)) -> S2 | N15: 45689 | P15: =IF(O15="",DATEDIF(N15,TODAY(),"y")&" tahun "&DATEDIF(N15,TODAY(),"ym")&" bulan ",DATEDIF(N15,O15,"y")&" tahun "&DATEDIF(N15,O15,"ym")&" bulan ") -> 0 tahun 11 bulan | Q15: annisaramadhan807@gmail.com | R15: 81233838309 | S15: JAMBANGAN KEBON AGUNG KEL JAMBANGAN KEC JAMBANGAN SURABAYA
A16: 15 | B16: Egi Gumala Sari | C16: Non-Aktif | D16: Dosen | E16: =IF(D16="DOSEN",VLOOKUP(B16,Dosen!B:Z,11,FALSE),VLOOKUP(B16,TPA!B:Z,7,FALSE)) -> NJAD | F16: Digital Bisnis | G16: 25980005 | J16: =IF(D16="DOSEN",VLOOKUP(B16,Dosen!B:Z,7,FALSE),VLOOKUP(B16,TPA!B:Z,5,FALSE)) -> PROFESIONAL | L16: S.E., M.Ak. | M16: =IF(D16="DOSEN",VLOOKUP(B16,Dosen!B:ZZ,33,FALSE),VLOOKUP(B16,TPA!B:ZZ,44,FALSE)) -> S2 | N16: 45689 | O16: 45869 | P16: =IF(O16="",DATEDIF(N16,TODAY(),"y")&" tahun "&DATEDIF(N16,TODAY(),"ym")&" bulan ",DATEDIF(N16,O16,"y")&" tahun "&DATEDIF(N16,O16,"ym")&" bulan ") -> 0 tahun 5 bulan | Q16: riset.egigumalasari@gmail.com | R16: 82123510747 | S16: jl perintis kemardekaan no 154 kel padang matinggi
A17: 16 | B17: Wahyu Eka Kiswardani | C17: Aktif | D17: Dosen | E17: =IF(D17="DOSEN",VLOOKUP(B17,Dosen!B:Z,11,FALSE),VLOOKUP(B17,TPA!B:Z,7,FALSE)) -> NJAD | F17: Digital Bisnis | G17: 25010008 | H17: 0452779680230052 | I17: 0452779680230052 | J17: =IF(D17="DOSEN",VLOOKUP(B17,Dosen!B:Z,7,FALSE),VLOOKUP(B17,TPA!B:Z,5,FALSE)) -> PROFESIONAL | L17: S.M., M.M. | M17: =IF(D17="DOSEN",VLOOKUP(B17,Dosen!B:ZZ,33,FALSE),VLOOKUP(B17,TPA!B:ZZ,44,FALSE)) -> S2 | N17: 45689 | P17: =IF(O17="",DATEDIF(N17,TODAY(),"y")&" tahun "&DATEDIF(N17,TODAY(),"ym")&" bulan ",DATEDIF(N17,O17,"y")&" tahun "&DATEDIF(N17,O17,"ym")&" bulan ") -> 0 tahun 11 bulan | Q17: wahyuuekafb658@gmail.com | R17: 81222871863 | S17: DESA NGETOS RT 002 RW 002 KEL NGETOS KEC NGETOS NGANJUK
A18: 17 | B18: Hussein Gibreel Musa Salih | C18: Aktif | D18: Dosen | E18: =IF(D18="DOSEN",VLOOKUP(B18,Dosen!B:Z,11,FALSE),VLOOKUP(B18,TPA!B:Z,7,FALSE)) -> NJAD | F18: Digital Bisnis | G18: 25900003 | J18: =IF(D18="DOSEN",VLOOKUP(B18,Dosen!B:Z,7,FALSE),VLOOKUP(B18,TPA!B:Z,5,FALSE)) -> PROFESIONAL | L18: B.Art., M.I.kom., Ph.D. | M18: =IF(D18="DOSEN",VLOOKUP(B18,Dosen!B:ZZ,33,FALSE),VLOOKUP(B18,TPA!B:ZZ,44,FALSE)) -> S3 | N18: 45658 | P18: =IF(O18="",DATEDIF(N18,TODAY(),"y")&" tahun "&DATEDIF(N18,TODAY(),"ym")&" bulan ",DATEDIF(N18,O18,"y")&" tahun "&DATEDIF(N18,O18,"ym")&" bulan ") -> 1 tahun 0 bulan | Q18: husseingibreelmusa@gmail.com | S18: Anugrah Batako RT 006 RW 000, Kel. Argorejo, Kec. Sedayu, Kab. Bantul
A19: 18 | B19: Ardian Yusuf Wicaksono | C19: Aktif | D19: Dosen | E19: =IF(D19="DOSEN",VLOOKUP(B19,Dosen!B:Z,11,FALSE),VLOOKUP(B19,TPA!B:Z,7,FALSE)) -> AA | F19: Informatika | G19: 18920109 | H19: 727099201 | I19: 5259770671130293 | J19: =IF(D19="DOSEN",VLOOKUP(B19,Dosen!B:Z,7,FALSE),VLOOKUP(B19,TPA!B:Z,5,FALSE)) -> TETAP | L19: S.Kom., M.Kom. | M19: =IF(D19="DOSEN",VLOOKUP(B19,Dosen!B:ZZ,33,FALSE),VLOOKUP(B19,TPA!B:ZZ,44,FALSE)) -> S2 | N19: 43282 | P19: =IF(O19="",DATEDIF(N19,TODAY(),"y")&" tahun "&DATEDIF(N19,TODAY(),"ym")&" bulan ",DATEDIF(N19,O19,"y")&" tahun "&DATEDIF(N19,O19,"ym")&" bulan ") -> 7 tahun 6 bulan | Q19: ardian@ittelkom-sby.ac.id | R19: 82245510526 | S19: Jalan Mayor Bismo No. 26A RT/RW 02/02, Templek, Gadungan, Puncu, Kediri
A20: 19 | B20: Ahmad Wali Satria Bahari Johan | C20: Aktif | D20: Dosen | E20: =IF(D20="DOSEN",VLOOKUP(B20,Dosen!B:Z,11,FALSE),VLOOKUP(B20,TPA!B:Z,7,FALSE)) -> L | F20: Informatika | G20: 20950043 | H20: 713059501 | I20: 7845773674130212 | J20: =IF(D20="DOSEN",VLOOKUP(B20,Dosen!B:Z,7,FALSE),VLOOKUP(B20,TPA!B:Z,5,FALSE)) -> TETAP | L20: S.ST., M.Kom. | M20: =IF(D20="DOSEN",VLOOKUP(B20,Dosen!B:ZZ,33,FALSE),VLOOKUP(B20,TPA!B:ZZ,44,FALSE)) -> S2 | N20: 44166 | P20: =IF(O20="",DATEDIF(N20,TODAY(),"y")&" tahun "&DATEDIF(N20,TODAY(),"ym")&" bulan ",DATEDIF(N20,O20,"y")&" tahun "&DATEDIF(N20,O20,"ym")&" bulan ") -> 5 tahun 1 bulan | Q20: ahmadsatria13@ittelkom-sby.ac.id | R20: 82132194465 | S20: Dsn. Bujel, Suwaloh, Balen, Bojonegoro
A21: 20 | B21: Muhammad Dzulfikar Fauzi | C21: Aktif | D21: Dosen | E21: =IF(D21="DOSEN",VLOOKUP(B21,Dosen!B:Z,11,FALSE),VLOOKUP(B21,TPA!B:Z,7,FALSE)) -> L | F21: Informatika | G21: 20940043 | H21: 711039403 | I21: 2643772673130292 | J21: =IF(D21="DOSEN",VLOOKUP(B21,Dosen!B:Z,7,FALSE),VLOOKUP(B21,TPA!B:Z,5,FALSE)) -> TETAP | L21: S.Kom., M.Cs. | M21: =IF(D21="DOSEN",VLOOKUP(B21,Dosen!B:ZZ,33,FALSE),VLOOKUP(B21,TPA!B:ZZ,44,FALSE)) -> S2 | N21: 44166 | P21: =IF(O21="",DATEDIF(N21,TODAY(),"y")&" tahun "&DATEDIF(N21,TODAY(),"ym")&" bulan ",DATEDIF(N21,O21,"y")&" tahun "&DATEDIF(N21,O21,"ym")&" bulan ") -> 5 tahun 1 bulan | Q21: muhammad.dzulfikar.f@ittelkom-sby.ac.id | R21: 85323076783 | S21: Dsn. Kayen, Morosunggingan, Peterongan, Jombang
A22: 21 | B22: Kharisma Monika Dian Pertiwi | C22: Aktif | D22: Dosen | E22: =IF(D22="DOSEN",VLOOKUP(B22,Dosen!B:Z,11,FALSE),VLOOKUP(B22,TPA!B:Z,7,FALSE)) -> AA | F22: Informatika | G22: 23950024 | H22: 706089501 | I22: 4138773674230223 | J22: =IF(D22="DOSEN",VLOOKUP(B22,Dosen!B:Z,7,FALSE),VLOOKUP(B22,TPA!B:Z,5,FALSE)) -> TETAP | L22: S.Kom., M.Kom. | M22: =IF(D22="DOSEN",VLOOKUP(B22,Dosen!B:ZZ,33,FALSE),VLOOKUP(B22,TPA!B:ZZ,44,FALSE)) -> S2 | N22: 44166 | P22: =IF(O22="",DATEDIF(N22,TODAY(),"y")&" tahun "&DATEDIF(N22,TODAY(),"ym")&" bulan ",DATEDIF(N22,O22,"y")&" tahun "&DATEDIF(N22,O22,"ym")&" bulan ") -> 5 tahun 1 bulan | Q22: kharismamonika@ittelkom-sby.ac.id | R22: 81233777404 | S22: Jl. YKP Pandugo 2F-4, Penjaringan Sari, Rungkut, Surabaya
A23: 22 | B23: Rizky Fenaldo Maulana | C23: Aktif | D23: Dosen | E23: =IF(D23="DOSEN",VLOOKUP(B23,Dosen!B:Z,11,FALSE),VLOOKUP(B23,TPA!B:Z,7,FALSE)) -> AA | F23: Informatika | G23: 20970031 | H23: 714079701 | I23: 2046775676130173 | J23: =IF(D23="DOSEN",VLOOKUP(B23,Dosen!B:Z,7,FALSE),VLOOKUP(B23,TPA!B:Z,5,FALSE)) -> TETAP | L23: S.Kom., M.Kom. | M23: =IF(D23="DOSEN",VLOOKUP(B23,Dosen!B:ZZ,33,FALSE),VLOOKUP(B23,TPA!B:ZZ,44,FALSE)) -> S2 | N23: 44166 | P23: =IF(O23="",DATEDIF(N23,TODAY(),"y")&" tahun "&DATEDIF(N23,TODAY(),"ym")&" bulan ",DATEDIF(N23,O23,"y")&" tahun "&DATEDIF(N23,O23,"ym")&" bulan ") -> 5 tahun 1 bulan | Q23: aldo@ittelkom-sby.ac.id | R23: 81230777099 | S23: Jl. Gajayana No. 796, Dinoyo, Lowokwaru, Malang
A24: 23 | B24: Vessa Rizky Oktavia | C24: Aktif | D24: Dosen | E24: =IF(D24="DOSEN",VLOOKUP(B24,Dosen!B:Z,11,FALSE),VLOOKUP(B24,TPA!B:Z,7,FALSE)) -> AA | F24: Informatika | G24: 22950051 | H24: 705109501 | I24: 7337773674230273 | J24: =IF(D24="DOSEN",VLOOKUP(B24,Dosen!B:Z,7,FALSE),VLOOKUP(B24,TPA!B:Z,5,FALSE)) -> PROFESIONAL | L24: S.Kom., M.Kom. | M24: =IF(D24="DOSEN",VLOOKUP(B24,Dosen!B:ZZ,33,FALSE),VLOOKUP(B24,TPA!B:ZZ,44,FALSE)) -> S2 | N24: 44832 | P24: =IF(O24="",DATEDIF(N24,TODAY(),"y")&" tahun "&DATEDIF(N24,TODAY(),"ym")&" bulan ",DATEDIF(N24,O24,"y")&" tahun "&DATEDIF(N24,O24,"ym")&" bulan ") -> 3 tahun 3 bulan | Q24: vessa@ittelkom-sby.ac.id | R24: 82139322002 | S24: Alun Alun Rangkah NO 17-II, Tambaksari, Surabaya
A25: 24 | B25: Alqis Rausanfita | C25: Aktif | D25: Dosen | E25: =IF(D25="DOSEN",VLOOKUP(B25,Dosen!B:Z,11,FALSE),VLOOKUP(B25,TPA!B:Z,7,FALSE)) -> AA | F25: Informatika | G25: 22960060 | H25: 710029601 | I25: 7542774675230212 | J25: =IF(D25="DOSEN",VLOOKUP(B25,Dosen!B:Z,7,FALSE),VLOOKUP(B25,TPA!B:Z,5,FALSE)) -> PROFESIONAL | L25: S.Kom., M.Kom. | M25: =IF(D25="DOSEN",VLOOKUP(B25,Dosen!B:ZZ,33,FALSE),VLOOKUP(B25,TPA!B:ZZ,44,FALSE)) -> S2 | N25: 44832 | P25: =IF(O25="",DATEDIF(N25,TODAY(),"y")&" tahun "&DATEDIF(N25,TODAY(),"ym")&" bulan ",DATEDIF(N25,O25,"y")&" tahun "&DATEDIF(N25,O25,"ym")&" bulan ") -> 3 tahun 3 bulan | Q25: alqisrausanfita@ittelkom-sby.ac.id | R25: 82143463645 | S25: Ngagel Mulya 8/42, Wonokromo, Surabaya
A26: 25 | B26: Daud Muhajir | C26: Aktif | D26: Dosen | E26: =IF(D26="DOSEN",VLOOKUP(B26,Dosen!B:Z,11,FALSE),VLOOKUP(B26,TPA!B:Z,7,FALSE)) -> AA | F26: Informatika | G26: 23970024 | H26: 711079701 | I26: 5043775676130143 | J26: =IF(D26="DOSEN",VLOOKUP(B26,Dosen!B:Z,7,FALSE),VLOOKUP(B26,TPA!B:Z,5,FALSE)) -> PROFESIONAL | L26: S.Kom., M.Kom. | M26: =IF(D26="DOSEN",VLOOKUP(B26,Dosen!B:ZZ,33,FALSE),VLOOKUP(B26,TPA!B:ZZ,44,FALSE)) -> S2 | N26: 45170 | P26: =IF(O26="",DATEDIF(N26,TODAY(),"y")&" tahun "&DATEDIF(N26,TODAY(),"ym")&" bulan ",DATEDIF(N26,O26,"y")&" tahun "&DATEDIF(N26,O26,"ym")&" bulan ") -> 2 tahun 4 bulan | Q26: daud@ittelkom-sby.ac.id | R26: 81227926332 | S26: Klakahrejo Lor Gg. Arwana 34, Surabaya
A27: 26 | B27: Dyah Putri Rahmawati | C27: Aktif | D27: Dosen | E27: =IF(D27="DOSEN",VLOOKUP(B27,Dosen!B:Z,11,FALSE),VLOOKUP(B27,TPA!B:Z,7,FALSE)) -> L | F27: Informatika | G27: 23960023 | H27: 719039601 | I27: 3651774675230192 | J27: =IF(D27="DOSEN",VLOOKUP(B27,Dosen!B:Z,7,FALSE),VLOOKUP(B27,TPA!B:Z,5,FALSE)) -> PROFESIONAL | K27: Dr. | L27: S.Stat. | M27: =IF(D27="DOSEN",VLOOKUP(B27,Dosen!B:ZZ,33,FALSE),VLOOKUP(B27,TPA!B:ZZ,44,FALSE)) -> S3 | N27: 45170 | P27: =IF(O27="",DATEDIF(N27,TODAY(),"y")&" tahun "&DATEDIF(N27,TODAY(),"ym")&" bulan ",DATEDIF(N27,O27,"y")&" tahun "&DATEDIF(N27,O27,"ym")&" bulan ") -> 2 tahun 4 bulan | Q27: dyahputri@ittelkom-sby.ac.id | R27: 82131803152 | S27: Jl. Turkis V-15, Sooko, Mojokerto, 61361
A28: 27 | B28: Pima Hani Safitri | C28: Aktif | D28: Dosen | E28: =IF(D28="DOSEN",VLOOKUP(B28,Dosen!B:Z,11,FALSE),VLOOKUP(B28,TPA!B:Z,7,FALSE)) -> NJAD | F28: Informatika | G28: 23950016 | H28: 703039502 | I28: 2635773674230322 | J28: =IF(D28="DOSEN",VLOOKUP(B28,Dosen!B:Z,7,FALSE),VLOOKUP(B28,TPA!B:Z,5,FALSE)) -> PROFESIONAL | L28: S.Kom., M.Kom. | M28: =IF(D28="DOSEN",VLOOKUP(B28,Dosen!B:ZZ,33,FALSE),VLOOKUP(B28,TPA!B:ZZ,44,FALSE)) -> S2 | N28: 45170 | P28: =IF(O28="",DATEDIF(N28,TODAY(),"y")&" tahun "&DATEDIF(N28,TODAY(),"ym")&" bulan ",DATEDIF(N28,O28,"y")&" tahun "&DATEDIF(N28,O28,"ym")&" bulan ") -> 2 tahun 4 bulan | Q28: pimahanisafitri@ittelkom-sby.ac.id | R28: 85236699663 | S28: Jl. Jagalan II, Kedok, Turen, Malang, 65175
A29: 28 | B29: Tanzilal Mustaqim | C29: Aktif | D29: Dosen | E29: =IF(D29="DOSEN",VLOOKUP(B29,Dosen!B:Z,11,FALSE),VLOOKUP(B29,TPA!B:Z,7,FALSE)) -> NJAD | F29: Informatika | G29: 23980024 | H29: 714089801 | I29: 3146776677130103 | J29: =IF(D29="DOSEN",VLOOKUP(B29,Dosen!B:Z,7,FALSE),VLOOKUP(B29,TPA!B:Z,5,FALSE)) -> PROFESIONAL | L29: S.Kom., M.Kom. | M29: =IF(D29="DOSEN",VLOOKUP(B29,Dosen!B:ZZ,33,FALSE),VLOOKUP(B29,TPA!B:ZZ,44,FALSE)) -> S3 | N29: 45170 | P29: =IF(O29="",DATEDIF(N29,TODAY(),"y")&" tahun "&DATEDIF(N29,TODAY(),"ym")&" bulan ",DATEDIF(N29,O29,"y")&" tahun "&DATEDIF(N29,O29,"ym")&" bulan ") -> 2 tahun 4 bulan | Q29: tanzilal@ittelkom-sby.ac.id | R29: 85171711408 | S29: Tlogojati, Plosorejo, Gondang, Sragen, 57254
A30: 29 | B30: Fandisya Rahman | C30: Aktif | D30: Dosen | E30: =IF(D30="DOSEN",VLOOKUP(B30,Dosen!B:Z,11,FALSE),VLOOKUP(B30,TPA!B:Z,7,FALSE)) -> NJAD | F30: Informatika | G30: 23900006 | H30: 0711059005 | I30: 2843768669130322 | J30: =IF(D30="DOSEN",VLOOKUP(B30,Dosen!B:Z,7,FALSE),VLOOKUP(B30,TPA!B:Z,5,FALSE)) -> PROFESIONAL | L30: S.Kom., M.Kom. | M30: =IF(D30="DOSEN",VLOOKUP(B30,Dosen!B:ZZ,33,FALSE),VLOOKUP(B30,TPA!B:ZZ,44,FALSE)) -> S2 | N30: 45170 | P30: =IF(O30="",DATEDIF(N30,TODAY(),"y")&" tahun "&DATEDIF(N30,TODAY(),"ym")&" bulan ",DATEDIF(N30,O30,"y")&" tahun "&DATEDIF(N30,O30,"ym")&" bulan ") -> 2 tahun 4 bulan | Q30: rahman@ittelkom-sby.ac.id | R30: 85175442445 | S30: Jl. MT. Haryono XVII / 211, Malang, 65145
A31: 30 | B31: Dimas Chaerul Ekty Saputra | C31: Aktif | D31: Dosen | E31: =IF(D31="DOSEN",VLOOKUP(B31,Dosen!B:Z,11,FALSE),VLOOKUP(B31,TPA!B:Z,7,FALSE)) -> NJAD | F31: Informatika | G31: 24980018 | H31: 6961776677130132 | I31: 6961776677130132 | J31: =IF(D31="DOSEN",VLOOKUP(B31,Dosen!B:Z,7,FALSE),VLOOKUP(B31,TPA!B:Z,5,FALSE)) -> PROFESIONAL | L31: S.Kom., M.Sc. | M31: =IF(D31="DOSEN",VLOOKUP(B31,Dosen!B:ZZ,33,FALSE),VLOOKUP(B31,TPA!B:ZZ,44,FALSE)) -> S3 | N31: 45536 | P31: =IF(O31="",DATEDIF(N31,TODAY(),"y")&" tahun "&DATEDIF(N31,TODAY(),"ym")&" bulan ",DATEDIF(N31,O31,"y")&" tahun "&DATEDIF(N31,O31,"ym")&" bulan ") -> 1 tahun 4 bulan | Q31: dimaschaerul3@gmail.com | R31: 81225763073 | S31: Asrama Polri Pathuk Ng I/598 Rt 030 Rw 006, Kel. Ngampilan, Kec. Ngampilan, Yogyakarta
A32: 31 | B32: Yasinta Romadhona | C32: Aktif | D32: Dosen | E32: =IF(D32="DOSEN",VLOOKUP(B32,Dosen!B:Z,11,FALSE),VLOOKUP(B32,TPA!B:Z,7,FALSE)) -> NJAD | F32: Informatika | G32: 25989002 | I32: 1438776677230172 | J32: =IF(D32="DOSEN",VLOOKUP(B32,Dosen!B:Z,7,FALSE),VLOOKUP(B32,TPA!B:Z,5,FALSE)) -> PROFESIONAL | L32: S.Kom., M.Kom. | M32: =IF(D32="DOSEN",VLOOKUP(B32,Dosen!B:ZZ,33,FALSE),VLOOKUP(B32,TPA!B:ZZ,44,FALSE)) -> S2 | N32: 45717 | P32: =IF(O32="",DATEDIF(N32,TODAY(),"y")&" tahun "&DATEDIF(N32,TODAY(),"ym")&" bulan ",DATEDIF(N32,O32,"y")&" tahun "&DATEDIF(N32,O32,"ym")&" bulan ") -> 0 tahun 10 bulan | Q32: yasinta.rmd@gmail.com | R32: 82225333154 | S32: Dusun Sukobanteng RT 016 RW 004 Desa Karangsoko, Kecamatan Trenggalek, Kabupaten Trenggalek, Jawa Timur
A33: 32 | B33: Billy Montolalu | C33: Aktif | D33: Dosen | E33: =IF(D33="DOSEN",VLOOKUP(B33,Dosen!B:Z,11,FALSE),VLOOKUP(B33,TPA!B:Z,7,FALSE)) -> AA | F33: Rekayasa Perangkat Lunak | G33: 20870004 | H33: 729088704 | I33: 9160765666137003 | J33: =IF(D33="DOSEN",VLOOKUP(B33,Dosen!B:Z,7,FALSE),VLOOKUP(B33,TPA!B:Z,5,FALSE)) -> TETAP | L33: S.Kom., M.Kom. | M33: =IF(D33="DOSEN",VLOOKUP(B33,Dosen!B:ZZ,33,FALSE),VLOOKUP(B33,TPA!B:ZZ,44,FALSE)) -> S2 | N33: 43282 | P33: =IF(O33="",DATEDIF(N33,TODAY(),"y")&" tahun "&DATEDIF(N33,TODAY(),"ym")&" bulan ",DATEDIF(N33,O33,"y")&" tahun "&DATEDIF(N33,O33,"ym")&" bulan ") -> 7 tahun 6 bulan | Q33: billy@ittelkom-sby.ac.id | R33: 85233310837 | S33: DSN. KRAJAN RT 19 RW 5, YOSOWILANGUN LOR, LUMAJANG
A34: 33 | B34: Dahliar Ananda | C34: Aktif | D34: Dosen | E34: =IF(D34="DOSEN",VLOOKUP(B34,Dosen!B:Z,11,FALSE),VLOOKUP(B34,TPA!B:Z,7,FALSE)) -> L | F34: Rekayasa Perangkat Lunak | G34: 9820030 | H34: 402058203 | I34: 9834760661131142 | J34: =IF(D34="DOSEN",VLOOKUP(B34,Dosen!B:Z,7,FALSE),VLOOKUP(B34,TPA!B:Z,5,FALSE)) -> TETAP | L34: S.T., M.T. | M34: =IF(D34="DOSEN",VLOOKUP(B34,Dosen!B:ZZ,33,FALSE),VLOOKUP(B34,TPA!B:ZZ,44,FALSE)) -> S2 | N34: 39845 | P34: =IF(O34="",DATEDIF(N34,TODAY(),"y")&" tahun "&DATEDIF(N34,TODAY(),"ym")&" bulan ",DATEDIF(N34,O34,"y")&" tahun "&DATEDIF(N34,O34,"ym")&" bulan ") -> 16 tahun 11 bulan | Q34: dahliar@ittelkom-sby.ac.id | R34: 8121446627 | S34: Perum Batu Indah Regency Blok C7 no 1, Cilame, Ngamprah, Bandung Barat
A35: 34 | B35: Fidi Wincoko Putro | C35: Aktif | D35: Dosen | E35: =IF(D35="DOSEN",VLOOKUP(B35,Dosen!B:Z,11,FALSE),VLOOKUP(B35,TPA!B:Z,7,FALSE)) -> L | F35: Rekayasa Perangkat Lunak | G35: 19870004 | H35: 730058702 | I35: 1862765666130262 | J35: =IF(D35="DOSEN",VLOOKUP(B35,Dosen!B:Z,7,FALSE),VLOOKUP(B35,TPA!B:Z,5,FALSE)) -> TETAP | L35: S.ST., M.Kom. | M35: =IF(D35="DOSEN",VLOOKUP(B35,Dosen!B:ZZ,33,FALSE),VLOOKUP(B35,TPA!B:ZZ,44,FALSE)) -> S2 | N35: 43101 | P35: =IF(O35="",DATEDIF(N35,TODAY(),"y")&" tahun "&DATEDIF(N35,TODAY(),"ym")&" bulan ",DATEDIF(N35,O35,"y")&" tahun "&DATEDIF(N35,O35,"ym")&" bulan ") -> 8 tahun 0 bulan | Q35: fidiwputro@ittelkom-sby.ac.id | R35: 82143161793 | S35: Jl. Cempaka 42, Kel Bangunsari, Kec Mejayan, Kab Madiun, Jawa Timur
A36: 35 | B36: Mohammad Sholik | C36: Aktif | D36: Dosen | E36: =IF(D36="DOSEN",VLOOKUP(B36,Dosen!B:Z,11,FALSE),VLOOKUP(B36,TPA!B:Z,7,FALSE)) -> AA | F36: Rekayasa Perangkat Lunak | G36: 19810001 | H36: 709128101 | I36: 0541759660130163 | J36: =IF(D36="DOSEN",VLOOKUP(B36,Dosen!B:Z,7,FALSE),VLOOKUP(B36,TPA!B:Z,5,FALSE)) -> TETAP | L36: S.Kom., M.Kom. | M36: =IF(D36="DOSEN",VLOOKUP(B36,Dosen!B:ZZ,33,FALSE),VLOOKUP(B36,TPA!B:ZZ,44,FALSE)) -> S2 | N36: 43101 | P36: =IF(O36="",DATEDIF(N36,TODAY(),"y")&" tahun "&DATEDIF(N36,TODAY(),"ym")&" bulan ",DATEDIF(N36,O36,"y")&" tahun "&DATEDIF(N36,O36,"ym")&" bulan ") -> 8 tahun 0 bulan | Q36: mohammad.sholik@ittelkom-sby.ac.id | R36: 811324984 | S36: LOWAYU, RT. 029 RW. 008, DUKUN, GRESIK 61155
A37: 36 | B37: Dewi Rahmawati | C37: Aktif | D37: Dosen | E37: =IF(D37="DOSEN",VLOOKUP(B37,Dosen!B:Z,11,FALSE),VLOOKUP(B37,TPA!B:Z,7,FALSE)) -> L | F37: Rekayasa Perangkat Lunak | G37: 20940001 | H37: 709039401 | I37: 5641772673230262 | J37: =IF(D37="DOSEN",VLOOKUP(B37,Dosen!B:Z,7,FALSE),VLOOKUP(B37,TPA!B:Z,5,FALSE)) -> TETAP | K37: Dr. | L37: S.Kom., M.Kom. | M37: =IF(D37="DOSEN",VLOOKUP(B37,Dosen!B:ZZ,33,FALSE),VLOOKUP(B37,TPA!B:ZZ,44,FALSE)) -> S3 | N37: 43282 | P37: =IF(O37="",DATEDIF(N37,TODAY(),"y")&" tahun "&DATEDIF(N37,TODAY(),"ym")&" bulan ",DATEDIF(N37,O37,"y")&" tahun "&DATEDIF(N37,O37,"ym")&" bulan ") -> 7 tahun 6 bulan | Q37: dewirahmawati@ittelkom-sby.ac.id | R37: 81359057346 | S37: Perumahan Gempol Citra Asri O-24 Pasuruan
A38: 37 | B38: Achmad Muzakki | C38: Aktif | D38: Dosen | E38: =IF(D38="DOSEN",VLOOKUP(B38,Dosen!B:Z,11,FALSE),VLOOKUP(B38,TPA!B:Z,7,FALSE)) -> L | F38: Rekayasa Perangkat Lunak | G38: 23850011 | H38: 728058503 | I38: 7860763664130242 | J38: =IF(D38="DOSEN",VLOOKUP(B38,Dosen!B:Z,7,FALSE),VLOOKUP(B38,TPA!B:Z,5,FALSE)) -> TETAP | L38: S.Kom., M.Kom. | M38: =IF(D38="DOSEN",VLOOKUP(B38,Dosen!B:ZZ,33,FALSE),VLOOKUP(B38,TPA!B:ZZ,44,FALSE)) -> S2 | N38: 44627 | P38: =IF(O38="",DATEDIF(N38,TODAY(),"y")&" tahun "&DATEDIF(N38,TODAY(),"ym")&" bulan ",DATEDIF(N38,O38,"y")&" tahun "&DATEDIF(N38,O38,"ym")&" bulan ") -> 3 tahun 10 bulan | Q38: achmad.muzakki@ittelkom-sby.ac.id | R38: 81216473232 | S38: Gebang Wetan 1/9, Gebang Putih, Sukolilo, Surabaya
A39: 38 | B39: Arni Muarifah Amri | C39: Aktif | D39: Dosen | E39: =IF(D39="DOSEN",VLOOKUP(B39,Dosen!B:Z,11,FALSE),VLOOKUP(B39,TPA!B:Z,7,FALSE)) -> AA | F39: Rekayasa Perangkat Lunak | G39: 23900007 | H39: 718069004 | I39: 6950768669230322 | J39: =IF(D39="DOSEN",VLOOKUP(B39,Dosen!B:Z,7,FALSE),VLOOKUP(B39,TPA!B:Z,5,FALSE)) -> PROFESIONAL | L39: S.T., M.T. | M39: =IF(D39="DOSEN",VLOOKUP(B39,Dosen!B:ZZ,33,FALSE),VLOOKUP(B39,TPA!B:ZZ,44,FALSE)) -> S2 | N39: 45170 | P39: =IF(O39="",DATEDIF(N39,TODAY(),"y")&" tahun "&DATEDIF(N39,TODAY(),"ym")&" bulan ",DATEDIF(N39,O39,"y")&" tahun "&DATEDIF(N39,O39,"ym")&" bulan ") -> 2 tahun 4 bulan | Q39: arnimuarifah@ittelkom-sby.ac.id | R39: 85292632388 | S39: Mutiara Garden Blok A5, Sidoarjo, 61252
A40: 39 | B40: Amalia Nur Alifah | C40: Aktif | D40: Dosen | E40: =IF(D40="DOSEN",VLOOKUP(B40,Dosen!B:Z,11,FALSE),VLOOKUP(B40,TPA!B:Z,7,FALSE)) -> L | F40: Sains Data | G40: 20940044 | H40: 729129403 | I40: 1561772673230263 | J40: =IF(D40="DOSEN",VLOOKUP(B40,Dosen!B:Z,7,FALSE),VLOOKUP(B40,TPA!B:Z,5,FALSE)) -> TETAP | L40: S.Si., M.Si. | M40: =IF(D40="DOSEN",VLOOKUP(B40,Dosen!B:ZZ,33,FALSE),VLOOKUP(B40,TPA!B:ZZ,44,FALSE)) -> S2 | N40: 44166 | P40: =IF(O40="",DATEDIF(N40,TODAY(),"y")&" tahun "&DATEDIF(N40,TODAY(),"ym")&" bulan ",DATEDIF(N40,O40,"y")&" tahun "&DATEDIF(N40,O40,"ym")&" bulan ") -> 5 tahun 1 bulan | Q40: amalialifah@ittelkom-sby.ac.id | R40: 82229313437 | S40: Jl. Gondangmanis, Gondangmanis, BAE, Kudus
A41: 40 | B41: Helisyah Nur Fadhilah | C41: Non-Aktif | D41: Dosen | E41: =IF(D41="DOSEN",VLOOKUP(B41,Dosen!B:Z,11,FALSE),VLOOKUP(B41,TPA!B:Z,7,FALSE)) -> AA | F41: Sains Data | G41: 23950026 | H41: 707019501 | I41: 9439773674230232 | J41: =IF(D41="DOSEN",VLOOKUP(B41,Dosen!B:Z,7,FALSE),VLOOKUP(B41,TPA!B:Z,5,FALSE)) -> TETAP | K41: Dr. | L41: S.Si., M.Mat. | M41: =IF(D41="DOSEN",VLOOKUP(B41,Dosen!B:ZZ,33,FALSE),VLOOKUP(B41,TPA!B:ZZ,44,FALSE)) -> S3 | N41: 44166 | O41: 45747 | P41: =IF(O41="",DATEDIF(N41,TODAY(),"y")&" tahun "&DATEDIF(N41,TODAY(),"ym")&" bulan ",DATEDIF(N41,O41,"y")&" tahun "&DATEDIF(N41,O41,"ym")&" bulan ") -> 4 tahun 3 bulan | Q41: helisyah07@ittelkom-sby.ac.id | R41: 82131281868 | S41: Jl. R.A. Kartini 1-A/21, Gresik
A42: 41 | B42: Moh. Hamim Zajuli Al Faroby | C42: Aktif | D42: Dosen | E42: =IF(D42="DOSEN",VLOOKUP(B42,Dosen!B:Z,11,FALSE),VLOOKUP(B42,TPA!B:Z,7,FALSE)) -> L | F42: Sains Data | G42: 23950023 | H42: 724079501 | I42: 3056773674130233 | J42: =IF(D42="DOSEN",VLOOKUP(B42,Dosen!B:Z,7,FALSE),VLOOKUP(B42,TPA!B:Z,5,FALSE)) -> TETAP | L42: S.Si., M.Mat. | M42: =IF(D42="DOSEN",VLOOKUP(B42,Dosen!B:ZZ,33,FALSE),VLOOKUP(B42,TPA!B:ZZ,44,FALSE)) -> S2 | N42: 44166 | P42: =IF(O42="",DATEDIF(N42,TODAY(),"y")&" tahun "&DATEDIF(N42,TODAY(),"ym")&" bulan ",DATEDIF(N42,O42,"y")&" tahun "&DATEDIF(N42,O42,"ym")&" bulan ") -> 5 tahun 1 bulan | Q42: alfaroby@ittelkom-sby.ac.id | R42: 81331653603 | S42: Dsn. Krajan, Gladag, Rogojampi, Banyuwangi
A43: 42 | B43: Regita Putri Permata | C43: Aktif | D43: Dosen | E43: =IF(D43="DOSEN",VLOOKUP(B43,Dosen!B:Z,11,FALSE),VLOOKUP(B43,TPA!B:Z,7,FALSE)) -> AA | F43: Sains Data | G43: 22960008 | H43: 730099601 | I43: 0262774675230173 | J43: =IF(D43="DOSEN",VLOOKUP(B43,Dosen!B:Z,7,FALSE),VLOOKUP(B43,TPA!B:Z,5,FALSE)) -> PROFESIONAL | L43: S.Stat., M.Stat. | M43: =IF(D43="DOSEN",VLOOKUP(B43,Dosen!B:ZZ,33,FALSE),VLOOKUP(B43,TPA!B:ZZ,44,FALSE)) -> S2 | N43: 44627 | P43: =IF(O43="",DATEDIF(N43,TODAY(),"y")&" tahun "&DATEDIF(N43,TODAY(),"ym")&" bulan ",DATEDIF(N43,O43,"y")&" tahun "&DATEDIF(N43,O43,"ym")&" bulan ") -> 3 tahun 10 bulan | Q43: regitapermata@ittelkom-sby.ac.id | R43: 81232988938 | S43: GG. Sumur Kendal, Ronggomulyo, Tuban
A44: 43 | B44: Rifdatun Ni'mah | C44: Aktif | D44: Dosen | E44: =IF(D44="DOSEN",VLOOKUP(B44,Dosen!B:Z,11,FALSE),VLOOKUP(B44,TPA!B:Z,7,FALSE)) -> AA | F44: Sains Data | G44: 22900008 | H44: 714069008 | I44: 1946768669230292 | J44: =IF(D44="DOSEN",VLOOKUP(B44,Dosen!B:Z,7,FALSE),VLOOKUP(B44,TPA!B:Z,5,FALSE)) -> PROFESIONAL | L44: S.Si., M.Si. | M44: =IF(D44="DOSEN",VLOOKUP(B44,Dosen!B:ZZ,33,FALSE),VLOOKUP(B44,TPA!B:ZZ,44,FALSE)) -> S2 | N44: 44627 | P44: =IF(O44="",DATEDIF(N44,TODAY(),"y")&" tahun "&DATEDIF(N44,TODAY(),"ym")&" bulan ",DATEDIF(N44,O44,"y")&" tahun "&DATEDIF(N44,O44,"ym")&" bulan ") -> 3 tahun 10 bulan | Q44: rifdatun@ittelkom-sby.ac.id | R44: 82143858460 | S44: Meria, Pangkah Kulon, Ujungpangkah, Gresik
A45: 44 | B45: Sri Hidayati | C45: Aktif | D45: Dosen | E45: =IF(D45="DOSEN",VLOOKUP(B45,Dosen!B:Z,11,FALSE),VLOOKUP(B45,TPA!B:Z,7,FALSE)) -> AA | F45: Sains Data | G45: 22930003 | H45: 723119302 | I45: 6455771672230313 | J45: =IF(D45="DOSEN",VLOOKUP(B45,Dosen!B:Z,7,FALSE),VLOOKUP(B45,TPA!B:Z,5,FALSE)) -> PROFESIONAL | L45: ` | M45: =IF(D45="DOSEN",VLOOKUP(B45,Dosen!B:ZZ,33,FALSE),VLOOKUP(B45,TPA!B:ZZ,44,FALSE)) -> S2 | N45: 44627 | P45: =IF(O45="",DATEDIF(N45,TODAY(),"y")&" tahun "&DATEDIF(N45,TODAY(),"ym")&" bulan ",DATEDIF(N45,O45,"y")&" tahun "&DATEDIF(N45,O45,"ym")&" bulan ") -> 3 tahun 10 bulan | Q45: srihidayati@ittelkom-sby.ac.id | R45: 81217497767 | S45: Dsn. Kedaleman, Kemiren, Glagah, Banyuwangi
A46: 45 | B46: Sulthan Rafif | C46: Aktif | D46: Dosen | E46: =IF(D46="DOSEN",VLOOKUP(B46,Dosen!B:Z,11,FALSE),VLOOKUP(B46,TPA!B:Z,7,FALSE)) -> NJAD | F46: Sains Data | G46: 25990003 | I46: 3237777678130113 | J46: =IF(D46="DOSEN",VLOOKUP(B46,Dosen!B:Z,7,FALSE),VLOOKUP(B46,TPA!B:Z,5,FALSE)) -> PROFESIONAL | L46: S.Tr.Kom., M.Kom. | M46: =IF(D46="DOSEN",VLOOKUP(B46,Dosen!B:ZZ,33,FALSE),VLOOKUP(B46,TPA!B:ZZ,44,FALSE)) -> S2 | N46: 45658 | P46: =IF(O46="",DATEDIF(N46,TODAY(),"y")&" tahun "&DATEDIF(N46,TODAY(),"ym")&" bulan ",DATEDIF(N46,O46,"y")&" tahun "&DATEDIF(N46,O46,"ym")&" bulan ") -> 1 tahun 0 bulan | Q46: rsulthan5@gmail.com | R46: 82146235254 | S46: JL. GONDOSULI NO 2 RT FL)4 RW OO9, XEL. LOWOKWARU, KEC. LOWOKWARU, MALANG
A47: 46 | B47: Anfazul Faridatul Azizah | C47: Aktif | D47: Dosen | E47: =IF(D47="DOSEN",VLOOKUP(B47,Dosen!B:Z,11,FALSE),VLOOKUP(B47,TPA!B:Z,7,FALSE)) -> AA | F47: Sistem Informasi | G47: 19900002 | H47: 715039004 | I47: 8647768669230332 | J47: =IF(D47="DOSEN",VLOOKUP(B47,Dosen!B:Z,7,FALSE),VLOOKUP(B47,TPA!B:Z,5,FALSE)) -> TETAP | L47: S.Kom., M.Kom. | M47: =IF(D47="DOSEN",VLOOKUP(B47,Dosen!B:ZZ,33,FALSE),VLOOKUP(B47,TPA!B:ZZ,44,FALSE)) -> S2 | N47: 43101 | P47: =IF(O47="",DATEDIF(N47,TODAY(),"y")&" tahun "&DATEDIF(N47,TODAY(),"ym")&" bulan ",DATEDIF(N47,O47,"y")&" tahun "&DATEDIF(N47,O47,"ym")&" bulan ") -> 8 tahun 0 bulan | Q47: anfazul.azizah@ittelkom-sby.ac.id | R47: 82232504468 | S47: Jalan Ketintang 3 / 7, Surabaya
A48: 47 | B48: Hawwin Mardhiana | C48: Aktif | D48: Dosen | E48: =IF(D48="DOSEN",VLOOKUP(B48,Dosen!B:Z,11,FALSE),VLOOKUP(B48,TPA!B:Z,7,FALSE)) -> AA | F48: Sistem Informasi | G48: 20920039 | H48: 724089201 | I48: 6156770671230303 | J48: =IF(D48="DOSEN",VLOOKUP(B48,Dosen!B:Z,7,FALSE),VLOOKUP(B48,TPA!B:Z,5,FALSE)) -> TETAP | L48: S.Kom., M.Kom. | M48: =IF(D48="DOSEN",VLOOKUP(B48,Dosen!B:ZZ,33,FALSE),VLOOKUP(B48,TPA!B:ZZ,44,FALSE)) -> S2 | N48: 43282 | P48: =IF(O48="",DATEDIF(N48,TODAY(),"y")&" tahun "&DATEDIF(N48,TODAY(),"ym")&" bulan ",DATEDIF(N48,O48,"y")&" tahun "&DATEDIF(N48,O48,"ym")&" bulan ") -> 7 tahun 6 bulan | Q48: hawwin@ittelkom-sby.ac.id | R48: 81259106836 | S48: Jl.Mandala No.414, Semambung, RT.16 RW.04, Gedangan, Sidoarjo
A49: 48 | B49: Yupit Sudianto | C49: Aktif | D49: Dosen | E49: =IF(D49="DOSEN",VLOOKUP(B49,Dosen!B:Z,11,FALSE),VLOOKUP(B49,TPA!B:Z,7,FALSE)) -> AA | F49: Sistem Informasi | G49: 20860017 | H49: 721088602 | I49: 9153764665130213 | J49: =IF(D49="DOSEN",VLOOKUP(B49,Dosen!B:Z,7,FALSE),VLOOKUP(B49,TPA!B:Z,5,FALSE)) -> TETAP | L49: S.Kom., M.Kom. | M49: =IF(D49="DOSEN",VLOOKUP(B49,Dosen!B:ZZ,33,FALSE),VLOOKUP(B49,TPA!B:ZZ,44,FALSE)) -> S2 | N49: 43282 | P49: =IF(O49="",DATEDIF(N49,TODAY(),"y")&" tahun "&DATEDIF(N49,TODAY(),"ym")&" bulan ",DATEDIF(N49,O49,"y")&" tahun "&DATEDIF(N49,O49,"ym")&" bulan ") -> 7 tahun 6 bulan | Q49: yupit@ittelkom-sby.ac.id | R49: 81359558005 | S49: Klampis Aji 2/4 Surabaya
A50: 49 | B50: Noerma Pudji Istyanto | C50: Aktif | D50: Dosen | E50: =IF(D50="DOSEN",VLOOKUP(B50,Dosen!B:Z,11,FALSE),VLOOKUP(B50,TPA!B:Z,7,FALSE)) -> L | F50: Sistem Informasi | G50: 19900003 | H50: 725059004 | I50: 8857768669130442 | J50: =IF(D50="DOSEN",VLOOKUP(B50,Dosen!B:Z,7,FALSE),VLOOKUP(B50,TPA!B:Z,5,FALSE)) -> TETAP | L50: S.Kom., M.Kom. | M50: =IF(D50="DOSEN",VLOOKUP(B50,Dosen!B:ZZ,33,FALSE),VLOOKUP(B50,TPA!B:ZZ,44,FALSE)) -> S2 | N50: 43101 | P50: =IF(O50="",DATEDIF(N50,TODAY(),"y")&" tahun "&DATEDIF(N50,TODAY(),"ym")&" bulan ",DATEDIF(N50,O50,"y")&" tahun "&DATEDIF(N50,O50,"ym")&" bulan ") -> 8 tahun 0 bulan | Q50: noermapudjiistyanto@ittelkom-sby.ac.id | R50: 85326721456 | S50: Jalan Pintu Gerbang, Pamekasan
A51: 50 | B51: Rokhmatul Insani | C51: Aktif | D51: Dosen | E51: =IF(D51="DOSEN",VLOOKUP(B51,Dosen!B:Z,11,FALSE),VLOOKUP(B51,TPA!B:Z,7,FALSE)) -> AA | F51: Sistem Informasi | G51: 23890011 | H51: 704068902 | I51: 5936767668230352 | J51: =IF(D51="DOSEN",VLOOKUP(B51,Dosen!B:Z,7,FALSE),VLOOKUP(B51,TPA!B:Z,5,FALSE)) -> TETAP | L51: S.T., M.T. | M51: =IF(D51="DOSEN",VLOOKUP(B51,Dosen!B:ZZ,33,FALSE),VLOOKUP(B51,TPA!B:ZZ,44,FALSE)) -> S2 | N51: 43831 | P51: =IF(O51="",DATEDIF(N51,TODAY(),"y")&" tahun "&DATEDIF(N51,TODAY(),"ym")&" bulan ",DATEDIF(N51,O51,"y")&" tahun "&DATEDIF(N51,O51,"ym")&" bulan ") -> 6 tahun 0 bulan | Q51: insani@ittelkom-sby.ac.id | R51: 85232959894 | S51: Jl. Pandan 16, Mojokerto
A52: 51 | B52: Agus Sulistya | C52: Aktif | D52: Dosen | E52: =IF(D52="DOSEN",VLOOKUP(B52,Dosen!B:Z,11,FALSE),VLOOKUP(B52,TPA!B:Z,7,FALSE)) -> L | F52: Sistem Informasi | G52: 19750005 | H52: 8920230021 | I52: 4150753654130133 | J52: =IF(D52="DOSEN",VLOOKUP(B52,Dosen!B:Z,7,FALSE),VLOOKUP(B52,TPA!B:Z,5,FALSE)) -> PERBANTUAN | L52: S.T., M.Sc., Ph.D | M52: =IF(D52="DOSEN",VLOOKUP(B52,Dosen!B:ZZ,33,FALSE),VLOOKUP(B52,TPA!B:ZZ,44,FALSE)) -> S3 | N52: 43770 | P52: =IF(O52="",DATEDIF(N52,TODAY(),"y")&" tahun "&DATEDIF(N52,TODAY(),"ym")&" bulan ",DATEDIF(N52,O52,"y")&" tahun "&DATEDIF(N52,O52,"ym")&" bulan ") -> 6 tahun 2 bulan | Q52: sulistya@ittelkom-sby.ac.id | R52: 8127041015 | S52: Jl. Rungkut Barata III/6, Rungkut Menanggal, Gunung Anyar, Surabaya
A53: 52 | B53: Muhamad Nasrullah | C53: Aktif | D53: Dosen | E53: =IF(D53="DOSEN",VLOOKUP(B53,Dosen!B:Z,11,FALSE),VLOOKUP(B53,TPA!B:Z,7,FALSE)) -> AA | F53: Sistem Informasi | G53: 23900009 | H53: 709059004 | I53: 3841768669130332 | J53: =IF(D53="DOSEN",VLOOKUP(B53,Dosen!B:Z,7,FALSE),VLOOKUP(B53,TPA!B:Z,5,FALSE)) -> TETAP | L53: S.Kom., M.Kom. | M53: =IF(D53="DOSEN",VLOOKUP(B53,Dosen!B:ZZ,33,FALSE),VLOOKUP(B53,TPA!B:ZZ,44,FALSE)) -> S2 | N53: 44075 | P53: =IF(O53="",DATEDIF(N53,TODAY(),"y")&" tahun "&DATEDIF(N53,TODAY(),"ym")&" bulan ",DATEDIF(N53,O53,"y")&" tahun "&DATEDIF(N53,O53,"ym")&" bulan ") -> 5 tahun 4 bulan | Q53: emnasrul@ittelkom-sby.ac.id | R53: 85259501314 | S53: Dusun Kemuning RT. 03 RW. 05 Desa Menunggal Kecamatan Kedamean Kabupaten Gresik
A54: 53 | B54: Aris Kusumawati | C54: Aktif | D54: Dosen | E54: =IF(D54="DOSEN",VLOOKUP(B54,Dosen!B:Z,11,FALSE),VLOOKUP(B54,TPA!B:Z,7,FALSE)) -> AA | F54: Sistem Informasi | G54: 21890010 | H54: 720088905 | I54: 6152767668230373 | J54: =IF(D54="DOSEN",VLOOKUP(B54,Dosen!B:Z,7,FALSE),VLOOKUP(B54,TPA!B:Z,5,FALSE)) -> PROFESIONAL | L54: S.Kom., M.Kom. | M54: =IF(D54="DOSEN",VLOOKUP(B54,Dosen!B:ZZ,33,FALSE),VLOOKUP(B54,TPA!B:ZZ,44,FALSE)) -> S2 | N54: 44470 | P54: =IF(O54="",DATEDIF(N54,TODAY(),"y")&" tahun "&DATEDIF(N54,TODAY(),"ym")&" bulan ",DATEDIF(N54,O54,"y")&" tahun "&DATEDIF(N54,O54,"ym")&" bulan ") -> 4 tahun 3 bulan | Q54: arisk@ittelkom-sby.ac.id | R54: 81330823998 | S54: Jl. Sunan Giri Gg. Beringin Jaya No 11, Lamongan
A55: 54 | B55: Mochamad Nizar Palefi Ma'ady | C55: Aktif | D55: Dosen | E55: =IF(D55="DOSEN",VLOOKUP(B55,Dosen!B:Z,11,FALSE),VLOOKUP(B55,TPA!B:Z,7,FALSE)) -> AA | F55: Sistem Informasi | G55: 21910012 | H55: 708119103 | I55: 7440769670130263 | J55: =IF(D55="DOSEN",VLOOKUP(B55,Dosen!B:Z,7,FALSE),VLOOKUP(B55,TPA!B:Z,5,FALSE)) -> PROFESIONAL | L55: S.Kom., M.Kom., M.IM. | M55: =IF(D55="DOSEN",VLOOKUP(B55,Dosen!B:ZZ,33,FALSE),VLOOKUP(B55,TPA!B:ZZ,44,FALSE)) -> S2 | N55: 44562 | P55: =IF(O55="",DATEDIF(N55,TODAY(),"y")&" tahun "&DATEDIF(N55,TODAY(),"ym")&" bulan ",DATEDIF(N55,O55,"y")&" tahun "&DATEDIF(N55,O55,"ym")&" bulan ") -> 4 tahun 0 bulan | Q55: nizar@ittelkom-sby.ac.id | R55: 8123122708 | S55: Jl. Taman Mulyosari Utara No. 21, Surabaya
A56: 55 | B56: Purnama Anaking | C56: Aktif | D56: Dosen | E56: =IF(D56="DOSEN",VLOOKUP(B56,Dosen!B:Z,11,FALSE),VLOOKUP(B56,TPA!B:Z,7,FALSE)) -> NJAD | F56: Sistem Informasi | G56: 21870007 | H56: 724098701 | I56: 0256765666130223 | J56: =IF(D56="DOSEN",VLOOKUP(B56,Dosen!B:Z,7,FALSE),VLOOKUP(B56,TPA!B:Z,5,FALSE)) -> PROFESIONAL | L56: S.Kom., M.Kom. | M56: =IF(D56="DOSEN",VLOOKUP(B56,Dosen!B:ZZ,33,FALSE),VLOOKUP(B56,TPA!B:ZZ,44,FALSE)) -> S2 | N56: 44562 | P56: =IF(O56="",DATEDIF(N56,TODAY(),"y")&" tahun "&DATEDIF(N56,TODAY(),"ym")&" bulan ",DATEDIF(N56,O56,"y")&" tahun "&DATEDIF(N56,O56,"ym")&" bulan ") -> 4 tahun 0 bulan | Q56: purnama.anaking@ittelkom-sby.ac.id | R56: 81239428683 | S56: Jl. Semampir Tengah 9 / 5D Surabaya
A57: 56 | B57: Raulia Riski | C57: Aktif | D57: Dosen | E57: =IF(D57="DOSEN",VLOOKUP(B57,Dosen!B:Z,11,FALSE),VLOOKUP(B57,TPA!B:Z,7,FALSE)) -> AA | F57: Sistem Informasi | G57: 22940003 | H57: 719109401 | I57: 1351772673230253 | J57: =IF(D57="DOSEN",VLOOKUP(B57,Dosen!B:Z,7,FALSE),VLOOKUP(B57,TPA!B:Z,5,FALSE)) -> PROFESIONAL | L57: S.Kom., M.Kom., M.M.S. | M57: =IF(D57="DOSEN",VLOOKUP(B57,Dosen!B:ZZ,33,FALSE),VLOOKUP(B57,TPA!B:ZZ,44,FALSE)) -> S2 | N57: 44627 | P57: =IF(O57="",DATEDIF(N57,TODAY(),"y")&" tahun "&DATEDIF(N57,TODAY(),"ym")&" bulan ",DATEDIF(N57,O57,"y")&" tahun "&DATEDIF(N57,O57,"ym")&" bulan ") -> 3 tahun 10 bulan | Q57: rauliariski@ittelkom-sby.ac.id | R57: 81357644374 | S57: Jl. Gatot Subroto, Mautapaga, Ende Timur, Ende
A58: 57 | B58: Adzanil Rachmadhi Putra | C58: Aktif | D58: Dosen | E58: =IF(D58="DOSEN",VLOOKUP(B58,Dosen!B:Z,11,FALSE),VLOOKUP(B58,TPA!B:Z,7,FALSE)) -> AA | F58: Sistem Informasi | G58: 22940040 | H58: 710089403 | I58: 5142772673130293 | J58: =IF(D58="DOSEN",VLOOKUP(B58,Dosen!B:Z,7,FALSE),VLOOKUP(B58,TPA!B:Z,5,FALSE)) -> PROFESIONAL | L58: S.Kom., M.Kom. | M58: =IF(D58="DOSEN",VLOOKUP(B58,Dosen!B:ZZ,33,FALSE),VLOOKUP(B58,TPA!B:ZZ,44,FALSE)) -> S2 | N58: 44832 | P58: =IF(O58="",DATEDIF(N58,TODAY(),"y")&" tahun "&DATEDIF(N58,TODAY(),"ym")&" bulan ",DATEDIF(N58,O58,"y")&" tahun "&DATEDIF(N58,O58,"ym")&" bulan ") -> 3 tahun 3 bulan | Q58: adzanilrachmadhip@ittelkom-sby.ac.id | R58: 82229846221 | S58: Jl Candi Mendut Selatan 20, Lowokwaru, Malang
A59: 58 | B59: Affifiana Prisyanti | C59: Non-Aktif | D59: Dosen | E59: =IF(D59="DOSEN",VLOOKUP(B59,Dosen!B:Z,11,FALSE),VLOOKUP(B59,TPA!B:Z,7,FALSE)) -> NJAD | F59: Sistem Informasi | G59: 22930047 | H59: 707089302 | I59: 1139771672230283 | J59: =IF(D59="DOSEN",VLOOKUP(B59,Dosen!B:Z,7,FALSE),VLOOKUP(B59,TPA!B:Z,5,FALSE)) -> PROFESIONAL | L59: S.Kom., M.Kom. | M59: =IF(D59="DOSEN",VLOOKUP(B59,Dosen!B:ZZ,33,FALSE),VLOOKUP(B59,TPA!B:ZZ,44,FALSE)) -> S2 | N59: 44832 | O59: 45838 | P59: =IF(O59="",DATEDIF(N59,TODAY(),"y")&" tahun "&DATEDIF(N59,TODAY(),"ym")&" bulan ",DATEDIF(N59,O59,"y")&" tahun "&DATEDIF(N59,O59,"ym")&" bulan ") -> 2 tahun 9 bulan | Q59: prisyantiaffifiana@ittelkom-sby.ac.id | R59: 81321003564 | S59: Jl. MT Haryono No 123 B, Ponorogo
A60: 59 | B60: Alifiansyah Arrizqy Hidayat | C60: Aktif | D60: Dosen | E60: =IF(D60="DOSEN",VLOOKUP(B60,Dosen!B:Z,11,FALSE),VLOOKUP(B60,TPA!B:Z,7,FALSE)) -> AA | F60: Sistem Informasi | G60: 22960061 | H60: 729059601 | I60: 4861774675130202 | J60: =IF(D60="DOSEN",VLOOKUP(B60,Dosen!B:Z,7,FALSE),VLOOKUP(B60,TPA!B:Z,5,FALSE)) -> PROFESIONAL | L60: S.Kom., M.Kom. | M60: =IF(D60="DOSEN",VLOOKUP(B60,Dosen!B:ZZ,33,FALSE),VLOOKUP(B60,TPA!B:ZZ,44,FALSE)) -> S2 | N60: 44832 | P60: =IF(O60="",DATEDIF(N60,TODAY(),"y")&" tahun "&DATEDIF(N60,TODAY(),"ym")&" bulan ",DATEDIF(N60,O60,"y")&" tahun "&DATEDIF(N60,O60,"ym")&" bulan ") -> 3 tahun 3 bulan | Q60: hidayatalifiansyah@ittelkom-sby.ac.id | R60: 82140046812 | S60: Jemur Andayani XIII no. 3, Kel. Wonocolo, Kec. Jemur Wonosari, Kota Surabaya
A61: 60 | B61: Anisa Dzulkarnain | C61: Aktif | D61: Dosen | E61: =IF(D61="DOSEN",VLOOKUP(B61,Dosen!B:Z,11,FALSE),VLOOKUP(B61,TPA!B:Z,7,FALSE)) -> AA | F61: Sistem Informasi | G61: 22950050 | H61: 724099501 | I61: 8256773674230223 | J61: =IF(D61="DOSEN",VLOOKUP(B61,Dosen!B:Z,7,FALSE),VLOOKUP(B61,TPA!B:Z,5,FALSE)) -> PROFESIONAL | L61: S.Kom., M.Kom. | M61: =IF(D61="DOSEN",VLOOKUP(B61,Dosen!B:ZZ,33,FALSE),VLOOKUP(B61,TPA!B:ZZ,44,FALSE)) -> S2 | N61: 44832 | P61: =IF(O61="",DATEDIF(N61,TODAY(),"y")&" tahun "&DATEDIF(N61,TODAY(),"ym")&" bulan ",DATEDIF(N61,O61,"y")&" tahun "&DATEDIF(N61,O61,"ym")&" bulan ") -> 3 tahun 3 bulan | Q61: anisadz@ittelkom-sby.ac.id | R61: 81359720852 | S61: Dusun Gilin, Tlanakan, Pamekasan
A62: 61 | B62: Anita Hakim Nasution | C62: Aktif | D62: Dosen | E62: =IF(D62="DOSEN",VLOOKUP(B62,Dosen!B:Z,11,FALSE),VLOOKUP(B62,TPA!B:Z,7,FALSE)) -> AA | F62: Sistem Informasi | G62: 22900033 | H62: 714019002 | I62: 8446768669230222 | J62: =IF(D62="DOSEN",VLOOKUP(B62,Dosen!B:Z,7,FALSE),VLOOKUP(B62,TPA!B:Z,5,FALSE)) -> PROFESIONAL | L62: S.T., M.T. | M62: =IF(D62="DOSEN",VLOOKUP(B62,Dosen!B:ZZ,33,FALSE),VLOOKUP(B62,TPA!B:ZZ,44,FALSE)) -> S2 | N62: 44832 | P62: =IF(O62="",DATEDIF(N62,TODAY(),"y")&" tahun "&DATEDIF(N62,TODAY(),"ym")&" bulan ",DATEDIF(N62,O62,"y")&" tahun "&DATEDIF(N62,O62,"ym")&" bulan ") -> 3 tahun 3 bulan | Q62: anitahakimnst@ittelkom-sby.ac.id | R62: 81231358055 | S62: Baratajaya 11/3, Gubeng, Surabaya
A63: 62 | B63: Arip Ramadan | C63: Aktif | D63: Dosen | E63: =IF(D63="DOSEN",VLOOKUP(B63,Dosen!B:Z,11,FALSE),VLOOKUP(B63,TPA!B:Z,7,FALSE)) -> AA | F63: Sistem Informasi | G63: 22930045 | H63: 712039301 | I63: 9644771672130302 | J63: =IF(D63="DOSEN",VLOOKUP(B63,Dosen!B:Z,7,FALSE),VLOOKUP(B63,TPA!B:Z,5,FALSE)) -> PROFESIONAL | L63: S.Si., M.Stat. | M63: =IF(D63="DOSEN",VLOOKUP(B63,Dosen!B:ZZ,33,FALSE),VLOOKUP(B63,TPA!B:ZZ,44,FALSE)) -> S3 | N63: 44832 | P63: =IF(O63="",DATEDIF(N63,TODAY(),"y")&" tahun "&DATEDIF(N63,TODAY(),"ym")&" bulan ",DATEDIF(N63,O63,"y")&" tahun "&DATEDIF(N63,O63,"ym")&" bulan ") -> 3 tahun 3 bulan | Q63: aripramadan@ittelkom-sby.ac.id | R63: 85288421363 | S63: Dusun Pangrumasan, Rancah, Ciamis
A64: 63 | B64: Rosyid Abdillah | C64: Aktif | D64: Dosen | E64: =IF(D64="DOSEN",VLOOKUP(B64,Dosen!B:Z,11,FALSE),VLOOKUP(B64,TPA!B:Z,7,FALSE)) -> AA | F64: Sistem Informasi | G64: 22920034 | H64: 715019202 | I64: 6447770671130292 | J64: =IF(D64="DOSEN",VLOOKUP(B64,Dosen!B:Z,7,FALSE),VLOOKUP(B64,TPA!B:Z,5,FALSE)) -> PROFESIONAL | L64: S.Si., M.Kom. | M64: =IF(D64="DOSEN",VLOOKUP(B64,Dosen!B:ZZ,33,FALSE),VLOOKUP(B64,TPA!B:ZZ,44,FALSE)) -> S2 | N64: 44832 | P64: =IF(O64="",DATEDIF(N64,TODAY(),"y")&" tahun "&DATEDIF(N64,TODAY(),"ym")&" bulan ",DATEDIF(N64,O64,"y")&" tahun "&DATEDIF(N64,O64,"ym")&" bulan ") -> 3 tahun 3 bulan | Q64: rosyidabdillah@ittelkom-sby.ac.id | R64: 82244983606 | S64: Babatan, Wiyung, Surabaya
A65: 64 | B65: Tita Ayu Rospricilia | C65: Aktif | D65: Dosen | E65: =IF(D65="DOSEN",VLOOKUP(B65,Dosen!B:Z,11,FALSE),VLOOKUP(B65,TPA!B:Z,7,FALSE)) -> AA | F65: Sistem Informasi | G65: 22980046 | H65: 702049801 | I65: 5734776677230092 | J65: =IF(D65="DOSEN",VLOOKUP(B65,Dosen!B:Z,7,FALSE),VLOOKUP(B65,TPA!B:Z,5,FALSE)) -> PROFESIONAL | L65: S.Kom., M.Kom. | M65: =IF(D65="DOSEN",VLOOKUP(B65,Dosen!B:ZZ,33,FALSE),VLOOKUP(B65,TPA!B:ZZ,44,FALSE)) -> S2 | N65: 44832 | P65: =IF(O65="",DATEDIF(N65,TODAY(),"y")&" tahun "&DATEDIF(N65,TODAY(),"ym")&" bulan ",DATEDIF(N65,O65,"y")&" tahun "&DATEDIF(N65,O65,"ym")&" bulan ") -> 3 tahun 3 bulan | Q65: titaayu@ittelkom-sby.ac.id | R65: 81336546637 | S65: Jl. Kenanga, Plosoklaten, Kediri
A66: 65 | B66: Berlian Rahmy Lidiawaty | C66: Aktif | D66: Dosen | E66: =IF(D66="DOSEN",VLOOKUP(B66,Dosen!B:Z,11,FALSE),VLOOKUP(B66,TPA!B:Z,7,FALSE)) -> AA | F66: Sistem Informasi | G66: 22940041 | H66: 10109403 | I66: 1342772673230433 | J66: =IF(D66="DOSEN",VLOOKUP(B66,Dosen!B:Z,7,FALSE),VLOOKUP(B66,TPA!B:Z,5,FALSE)) -> PROFESIONAL | L66: S.ST., M.MT. | M66: =IF(D66="DOSEN",VLOOKUP(B66,Dosen!B:ZZ,33,FALSE),VLOOKUP(B66,TPA!B:ZZ,44,FALSE)) -> S3 | N66: 44832 | P66: =IF(O66="",DATEDIF(N66,TODAY(),"y")&" tahun "&DATEDIF(N66,TODAY(),"ym")&" bulan ",DATEDIF(N66,O66,"y")&" tahun "&DATEDIF(N66,O66,"ym")&" bulan ") -> 3 tahun 3 bulan | Q66: berlianerel@ittelkom-sby.ac.id | R66: 81333283721 | S66: Apartemen Puncak Kertajaya Tower A0715 Jl. Kertajaya Indah, Surabaya
A67: 66 | B67: Ully Asfari | C67: Aktif | D67: Dosen | E67: =IF(D67="DOSEN",VLOOKUP(B67,Dosen!B:Z,11,FALSE),VLOOKUP(B67,TPA!B:Z,7,FALSE)) -> AA | F67: Sistem Informasi | G67: 19900008 | H67: 703129001 | I67: 5535768669230273 | J67: =IF(D67="DOSEN",VLOOKUP(B67,Dosen!B:Z,7,FALSE),VLOOKUP(B67,TPA!B:Z,5,FALSE)) -> TETAP | L67: S.Kom., M.Kom. | M67: =IF(D67="DOSEN",VLOOKUP(B67,Dosen!B:ZZ,33,FALSE),VLOOKUP(B67,TPA!B:ZZ,44,FALSE)) -> S2 | N67: 43101 | P67: =IF(O67="",DATEDIF(N67,TODAY(),"y")&" tahun "&DATEDIF(N67,TODAY(),"ym")&" bulan ",DATEDIF(N67,O67,"y")&" tahun "&DATEDIF(N67,O67,"ym")&" bulan ") -> 8 tahun 0 bulan | Q67: ully.asfari@ittelkom-sby.ac.id | R67: 82229243603 | S67: Jl. Babatan Pilang XI/1, Surabaya
A68: 67 | B68: Muhammad Ilham Alhari | C68: Aktif | D68: Dosen | E68: =IF(D68="DOSEN",VLOOKUP(B68,Dosen!B:Z,11,FALSE),VLOOKUP(B68,TPA!B:Z,7,FALSE)) -> NJAD | F68: Sistem Informasi | G68: 23990020 | H68: 722079901 | I68: 5054777678130063 | J68: =IF(D68="DOSEN",VLOOKUP(B68,Dosen!B:Z,7,FALSE),VLOOKUP(B68,TPA!B:Z,5,FALSE)) -> PROFESIONAL | L68: S.Kom., M.Kom. | M68: =IF(D68="DOSEN",VLOOKUP(B68,Dosen!B:ZZ,33,FALSE),VLOOKUP(B68,TPA!B:ZZ,44,FALSE)) -> S2 | N68: 45170 | P68: =IF(O68="",DATEDIF(N68,TODAY(),"y")&" tahun "&DATEDIF(N68,TODAY(),"ym")&" bulan ",DATEDIF(N68,O68,"y")&" tahun "&DATEDIF(N68,O68,"ym")&" bulan ") -> 2 tahun 4 bulan | Q68: milhamalhari@ittelkom-sby.ac.id | R68: 85200022100 | S68: Sumberagung, Mondokan, Sragen, 57271
A69: 68 | B69: Anifatul Faricha | C69: Aktif | D69: Dosen | E69: =IF(D69="DOSEN",VLOOKUP(B69,Dosen!B:Z,11,FALSE),VLOOKUP(B69,TPA!B:Z,7,FALSE)) -> AA | F69: Teknik Elektro | G69: 19920003 | H69: 704069202 | I69: 0936770671230312 | J69: =IF(D69="DOSEN",VLOOKUP(B69,Dosen!B:Z,7,FALSE),VLOOKUP(B69,TPA!B:Z,5,FALSE)) -> TETAP | L69: S.T., M.Sc., Ph.D | M69: =IF(D69="DOSEN",VLOOKUP(B69,Dosen!B:ZZ,33,FALSE),VLOOKUP(B69,TPA!B:ZZ,44,FALSE)) -> S3 | N69: 43101 | P69: =IF(O69="",DATEDIF(N69,TODAY(),"y")&" tahun "&DATEDIF(N69,TODAY(),"ym")&" bulan ",DATEDIF(N69,O69,"y")&" tahun "&DATEDIF(N69,O69,"ym")&" bulan ") -> 8 tahun 0 bulan | Q69: faricha@ittelkom-sby.ac.id | R69: 81360805290 | S69: Sekaran RT/RW:005/001, Kec. Sekaran, Lamongan
A70: 69 | B70: Dimas Adiputra | C70: Aktif | D70: Dosen | E70: =IF(D70="DOSEN",VLOOKUP(B70,Dosen!B:Z,11,FALSE),VLOOKUP(B70,TPA!B:Z,7,FALSE)) -> L | F70: Teknik Elektro | G70: 19930001 | H70: 725059301 | I70: 2857771672130342 | J70: =IF(D70="DOSEN",VLOOKUP(B70,Dosen!B:Z,7,FALSE),VLOOKUP(B70,TPA!B:Z,5,FALSE)) -> TETAP | L70: B.Sc., M.Phil., Ph.D. | M70: =IF(D70="DOSEN",VLOOKUP(B70,Dosen!B:ZZ,33,FALSE),VLOOKUP(B70,TPA!B:ZZ,44,FALSE)) -> S3 | N70: 43101 | P70: =IF(O70="",DATEDIF(N70,TODAY(),"y")&" tahun "&DATEDIF(N70,TODAY(),"ym")&" bulan ",DATEDIF(N70,O70,"y")&" tahun "&DATEDIF(N70,O70,"ym")&" bulan ") -> 8 tahun 0 bulan | Q70: adimas@ittelkom-sby.ac.id | R70: 81335397727 | S70: Jl. KH. Hasyim No. 35 RT009/RW002 Siwalanpanji Buduran Sidoarjo
A71: 70 | B71: Dwi Edi Setyawan | C71: Aktif | D71: Dosen | E71: =IF(D71="DOSEN",VLOOKUP(B71,Dosen!B:Z,11,FALSE),VLOOKUP(B71,TPA!B:Z,7,FALSE)) -> AA | F71: Teknik Elektro | G71: 19870005 | H71: 713068702 | I71: 7945765666130292 | J71: =IF(D71="DOSEN",VLOOKUP(B71,Dosen!B:Z,7,FALSE),VLOOKUP(B71,TPA!B:Z,5,FALSE)) -> TETAP | L71: S.T., M.T. | M71: =IF(D71="DOSEN",VLOOKUP(B71,Dosen!B:ZZ,33,FALSE),VLOOKUP(B71,TPA!B:ZZ,44,FALSE)) -> S2 | N71: 43101 | P71: =IF(O71="",DATEDIF(N71,TODAY(),"y")&" tahun "&DATEDIF(N71,TODAY(),"ym")&" bulan ",DATEDIF(N71,O71,"y")&" tahun "&DATEDIF(N71,O71,"ym")&" bulan ") -> 8 tahun 0 bulan | Q71: ediset@ittelkom-sby.ac.id | R71: 82134340781 | S71: Jl Raya Sedati Gede No 5, Sidoarjo
A72: 71 | B72: Isa Hafidz | C72: Aktif | D72: Dosen | E72: =IF(D72="DOSEN",VLOOKUP(B72,Dosen!B:Z,11,FALSE),VLOOKUP(B72,TPA!B:Z,7,FALSE)) -> L | F72: Teknik Elektro | G72: 19920002 | H72: 728059203 | I72: 5860770671130292 | J72: =IF(D72="DOSEN",VLOOKUP(B72,Dosen!B:Z,7,FALSE),VLOOKUP(B72,TPA!B:Z,5,FALSE)) -> TETAP | K72: Dr. | L72: S.T., M.T. | M72: =IF(D72="DOSEN",VLOOKUP(B72,Dosen!B:ZZ,33,FALSE),VLOOKUP(B72,TPA!B:ZZ,44,FALSE)) -> S3 | N72: 43101 | P72: =IF(O72="",DATEDIF(N72,TODAY(),"y")&" tahun "&DATEDIF(N72,TODAY(),"ym")&" bulan ",DATEDIF(N72,O72,"y")&" tahun "&DATEDIF(N72,O72,"ym")&" bulan ") -> 8 tahun 0 bulan | Q72: isa@ittelkom-sby.ac.id | R72: 85234852155 | S72: Jl. Tambak Deres 6/2, Surabaya
A73: 72 | B73: Lora Khaula Amifia | C73: Aktif | D73: Dosen | E73: =IF(D73="DOSEN",VLOOKUP(B73,Dosen!B:Z,11,FALSE),VLOOKUP(B73,TPA!B:Z,7,FALSE)) -> L | F73: Teknik Elektro | G73: 19920004 | H73: 706069201 | I73: 4938770671230412 | J73: =IF(D73="DOSEN",VLOOKUP(B73,Dosen!B:Z,7,FALSE),VLOOKUP(B73,TPA!B:Z,5,FALSE)) -> TETAP | L73: S.Pd., M.Eng. | M73: =IF(D73="DOSEN",VLOOKUP(B73,Dosen!B:ZZ,33,FALSE),VLOOKUP(B73,TPA!B:ZZ,44,FALSE)) -> S2 | N73: 43101 | P73: =IF(O73="",DATEDIF(N73,TODAY(),"y")&" tahun "&DATEDIF(N73,TODAY(),"ym")&" bulan ",DATEDIF(N73,O73,"y")&" tahun "&DATEDIF(N73,O73,"ym")&" bulan ") -> 8 tahun 0 bulan | Q73: loraamifia@ittelkom-sby.ac.id | R73: 82143903133 | S73: Jl. Tunggul Sari No.09 Daleman, Japan, Sooko, Mojokerto
A74: 73 | B74: Moch. Iskandar Riansyah | C74: Aktif | D74: Dosen | E74: =IF(D74="DOSEN",VLOOKUP(B74,Dosen!B:Z,11,FALSE),VLOOKUP(B74,TPA!B:Z,7,FALSE)) -> AA | F74: Teknik Elektro | G74: 19880005 | H74: 721068802 | I74: 2953766667130262 | J74: =IF(D74="DOSEN",VLOOKUP(B74,Dosen!B:Z,7,FALSE),VLOOKUP(B74,TPA!B:Z,5,FALSE)) -> TETAP | L74: S.ST., M.T. | M74: =IF(D74="DOSEN",VLOOKUP(B74,Dosen!B:ZZ,33,FALSE),VLOOKUP(B74,TPA!B:ZZ,44,FALSE)) -> S2 | N74: 43101 | P74: =IF(O74="",DATEDIF(N74,TODAY(),"y")&" tahun "&DATEDIF(N74,TODAY(),"ym")&" bulan ",DATEDIF(N74,O74,"y")&" tahun "&DATEDIF(N74,O74,"ym")&" bulan ") -> 8 tahun 0 bulan | Q74: iskandar@ittelkom-sby.ac.id | R74: 81232573646 | S74: Jl. Manggar Gg. Jambu 17 Lingk. Gebang Poreng, Jember
A75: 74 | B75: Rifki Dwi Putranto | C75: Aktif | D75: Dosen | E75: =IF(D75="DOSEN",VLOOKUP(B75,Dosen!B:Z,11,FALSE),VLOOKUP(B75,TPA!B:Z,7,FALSE)) -> NJAD | F75: Teknik Elektro | G75: 21950014 | H75: 727069503 | I75: 0959773674130252 | J75: =IF(D75="DOSEN",VLOOKUP(B75,Dosen!B:Z,7,FALSE),VLOOKUP(B75,TPA!B:Z,5,FALSE)) -> PROFESIONAL | L75: S.T., M.T. | M75: =IF(D75="DOSEN",VLOOKUP(B75,Dosen!B:ZZ,33,FALSE),VLOOKUP(B75,TPA!B:ZZ,44,FALSE)) -> S2 | N75: 44832 | P75: =IF(O75="",DATEDIF(N75,TODAY(),"y")&" tahun "&DATEDIF(N75,TODAY(),"ym")&" bulan ",DATEDIF(N75,O75,"y")&" tahun "&DATEDIF(N75,O75,"ym")&" bulan ") -> 3 tahun 3 bulan | Q75: rifkidwip@ittelkom-sby.ac.id | R75: 81234464242 | S75: Jl. Tehnologi No. 150 Perum. UNS, Jati, Jaten, Karanganyar
A76: 75 | B76: Chaironi Latif | C76: Aktif | D76: Dosen | E76: =IF(D76="DOSEN",VLOOKUP(B76,Dosen!B:Z,11,FALSE),VLOOKUP(B76,TPA!B:Z,7,FALSE)) -> L | F76: Teknik Elektro | G76: 20900019 | H76: 705109006 | I76: 8337768669130383 | J76: =IF(D76="DOSEN",VLOOKUP(B76,Dosen!B:Z,7,FALSE),VLOOKUP(B76,TPA!B:Z,5,FALSE)) -> PROFESIONAL | K76: Dr. | L76: S.Si. | M76: =IF(D76="DOSEN",VLOOKUP(B76,Dosen!B:ZZ,33,FALSE),VLOOKUP(B76,TPA!B:ZZ,44,FALSE)) -> S3 | N76: 43885 | P76: =IF(O76="",DATEDIF(N76,TODAY(),"y")&" tahun "&DATEDIF(N76,TODAY(),"ym")&" bulan ",DATEDIF(N76,O76,"y")&" tahun "&DATEDIF(N76,O76,"ym")&" bulan ") -> 5 tahun 10 bulan | Q76: chaironi@ittelkom-sby.ac.id | R76: 82140058468 | S76: Jl. Cendrawasih Bunderan 97, Waru, Sidoarjo
A77: 76 | B77: Tri Arief Sardjono | C77: Non-Aktif | D77: Dosen | E77: =IF(D77="DOSEN",VLOOKUP(B77,Dosen!B:Z,11,FALSE),VLOOKUP(B77,TPA!B:Z,7,FALSE)) -> GB | F77: Teknik Elektro | G77: 19700004 | H77: 12027005 | J77: =IF(D77="DOSEN",VLOOKUP(B77,Dosen!B:Z,7,FALSE),VLOOKUP(B77,TPA!B:Z,5,FALSE)) -> PERBANTUAN | K77: Prof. Dr. | L77: S.T., M.T. | M77: =IF(D77="DOSEN",VLOOKUP(B77,Dosen!B:ZZ,33,FALSE),VLOOKUP(B77,TPA!B:ZZ,44,FALSE)) -> S3 | N77: 43770 | O77: 45761 | P77: =IF(O77="",DATEDIF(N77,TODAY(),"y")&" tahun "&DATEDIF(N77,TODAY(),"ym")&" bulan ",DATEDIF(N77,O77,"y")&" tahun "&DATEDIF(N77,O77,"ym")&" bulan ") -> 5 tahun 5 bulan | Q77: triarief@ittelkom-sby.ac.id
A78: 77 | B78: Ayu Endah Wahyuni | C78: Aktif | D78: Dosen | E78: =IF(D78="DOSEN",VLOOKUP(B78,Dosen!B:Z,11,FALSE),VLOOKUP(B78,TPA!B:Z,7,FALSE)) -> L | F78: Teknik Industri | G78: 23880010 | H78: 401078801 | I78: 9033766667230323 | J78: =IF(D78="DOSEN",VLOOKUP(B78,Dosen!B:Z,7,FALSE),VLOOKUP(B78,TPA!B:Z,5,FALSE)) -> TETAP | L78: S.T., M.T. | M78: =IF(D78="DOSEN",VLOOKUP(B78,Dosen!B:ZZ,33,FALSE),VLOOKUP(B78,TPA!B:ZZ,44,FALSE)) -> S2 | N78: 44013 | P78: =IF(O78="",DATEDIF(N78,TODAY(),"y")&" tahun "&DATEDIF(N78,TODAY(),"ym")&" bulan ",DATEDIF(N78,O78,"y")&" tahun "&DATEDIF(N78,O78,"ym")&" bulan ") -> 5 tahun 6 bulan | Q78: ayu.endah@ittelkom-sby.ac.id | R78: 81395224118 | S78: Jl. Guru Mughni, Kuningan Timur, Jakarta Selatan
A79: 78 | B79: Benazir Imam Arif Muttaqin | C79: Aktif | D79: Dosen | E79: =IF(D79="DOSEN",VLOOKUP(B79,Dosen!B:Z,11,FALSE),VLOOKUP(B79,TPA!B:Z,7,FALSE)) -> L | F79: Teknik Industri | G79: 20930043 | H79: 703119301 | I79: 4435771672130323 | J79: =IF(D79="DOSEN",VLOOKUP(B79,Dosen!B:Z,7,FALSE),VLOOKUP(B79,TPA!B:Z,5,FALSE)) -> TETAP | L79: S.T., M.T. | M79: =IF(D79="DOSEN",VLOOKUP(B79,Dosen!B:ZZ,33,FALSE),VLOOKUP(B79,TPA!B:ZZ,44,FALSE)) -> S3 | N79: 43282 | P79: =IF(O79="",DATEDIF(N79,TODAY(),"y")&" tahun "&DATEDIF(N79,TODAY(),"ym")&" bulan ",DATEDIF(N79,O79,"y")&" tahun "&DATEDIF(N79,O79,"ym")&" bulan ") -> 7 tahun 6 bulan | Q79: benazir.imam.a.m@ittelkom-sby.ac.id | R79: 81329464686 | S79: Karanglo 01/02, Wironanggan, Gatak, Sukoharjo, 57557, Jawa Tengah
A80: 79 | B80: Rahaditya Dimas Prihadianto | C80: Aktif | D80: Dosen | E80: =IF(D80="DOSEN",VLOOKUP(B80,Dosen!B:Z,11,FALSE),VLOOKUP(B80,TPA!B:Z,7,FALSE)) -> AA | F80: Teknik Industri | G80: 20920036 | H80: 725059202 | I80: 4857770671130462 | J80: =IF(D80="DOSEN",VLOOKUP(B80,Dosen!B:Z,7,FALSE),VLOOKUP(B80,TPA!B:Z,5,FALSE)) -> TETAP | L80: S.T., M.T. | M80: =IF(D80="DOSEN",VLOOKUP(B80,Dosen!B:ZZ,33,FALSE),VLOOKUP(B80,TPA!B:ZZ,44,FALSE)) -> S2 | N80: 43101 | P80: =IF(O80="",DATEDIF(N80,TODAY(),"y")&" tahun "&DATEDIF(N80,TODAY(),"ym")&" bulan ",DATEDIF(N80,O80,"y")&" tahun "&DATEDIF(N80,O80,"ym")&" bulan ") -> 8 tahun 0 bulan | Q80: dimas.prihadianto@ittelkom-sby.ac.id | R80: 82231018193 | S80: Jl. Langsep Raya blok B1, Jember
A81: 80 | B81: Rizqa Amelia Zunaidi | C81: Aktif | D81: Dosen | E81: =IF(D81="DOSEN",VLOOKUP(B81,Dosen!B:Z,11,FALSE),VLOOKUP(B81,TPA!B:Z,7,FALSE)) -> L | F81: Teknik Industri | G81: 20930036 | H81: 711069301 | I81: 5943771672230272 | J81: =IF(D81="DOSEN",VLOOKUP(B81,Dosen!B:Z,7,FALSE),VLOOKUP(B81,TPA!B:Z,5,FALSE)) -> TETAP | L81: S.T., M.T. | M81: =IF(D81="DOSEN",VLOOKUP(B81,Dosen!B:ZZ,33,FALSE),VLOOKUP(B81,TPA!B:ZZ,44,FALSE)) -> S2 | N81: 43282 | P81: =IF(O81="",DATEDIF(N81,TODAY(),"y")&" tahun "&DATEDIF(N81,TODAY(),"ym")&" bulan ",DATEDIF(N81,O81,"y")&" tahun "&DATEDIF(N81,O81,"ym")&" bulan ") -> 7 tahun 6 bulan | Q81: rizqazunaidi@ittelkom-sby.ac.id | R81: 81221804899 | S81: Perumahan Magersari Permai BK-29 RT 31 RW 07 Sidoarjo, Jawa Timur
A82: 81 | B82: Silvi Istiqomah | C82: Aktif | D82: Dosen | E82: =IF(D82="DOSEN",VLOOKUP(B82,Dosen!B:Z,11,FALSE),VLOOKUP(B82,TPA!B:Z,7,FALSE)) -> AA | F82: Teknik Industri | G82: 22960010 | H82: 523119601 | I82: 8455774675230163 | J82: =IF(D82="DOSEN",VLOOKUP(B82,Dosen!B:Z,7,FALSE),VLOOKUP(B82,TPA!B:Z,5,FALSE)) -> PROFESIONAL | L82: S.T., M.T. | M82: =IF(D82="DOSEN",VLOOKUP(B82,Dosen!B:ZZ,33,FALSE),VLOOKUP(B82,TPA!B:ZZ,44,FALSE)) -> S2 | N82: 44627 | P82: =IF(O82="",DATEDIF(N82,TODAY(),"y")&" tahun "&DATEDIF(N82,TODAY(),"ym")&" bulan ",DATEDIF(N82,O82,"y")&" tahun "&DATEDIF(N82,O82,"ym")&" bulan ") -> 3 tahun 10 bulan | Q82: silviistiqomah@ittelkom-sby.ac.id | R82: 82213601320 | S82: Jl. Lempongsari Gg. Bawal No. 15, Jongkang, Sariharjo, Ngaglik, Sleman
A83: 82 | B83: Perdana Suteja Putra | C83: Non-Aktif | D83: Dosen | E83: =IF(D83="DOSEN",VLOOKUP(B83,Dosen!B:Z,11,FALSE),VLOOKUP(B83,TPA!B:Z,7,FALSE)) -> NJAD | F83: Teknik Industri | G83: 22950052 | H83: 704129501 | J83: =IF(D83="DOSEN",VLOOKUP(B83,Dosen!B:Z,7,FALSE),VLOOKUP(B83,TPA!B:Z,5,FALSE)) -> PROFESIONAL | L83: S.T., M.T. | M83: =IF(D83="DOSEN",VLOOKUP(B83,Dosen!B:ZZ,33,FALSE),VLOOKUP(B83,TPA!B:ZZ,44,FALSE)) -> S2 | N83: 44832 | O83: 45535 | P83: =IF(O83="",DATEDIF(N83,TODAY(),"y")&" tahun "&DATEDIF(N83,TODAY(),"ym")&" bulan ",DATEDIF(N83,O83,"y")&" tahun "&DATEDIF(N83,O83,"ym")&" bulan ") -> 1 tahun 11 bulan | Q83: perdanasuteja@ittelkom-sby.ac.id | R83: 81287562288 | S83: Dk. Ngemplak, Sukorejo, Wedi, Klaten
A84: 83 | B84: Huki Chandra | C84: Aktif | D84: Dosen | E84: =IF(D84="DOSEN",VLOOKUP(B84,Dosen!B:Z,11,FALSE),VLOOKUP(B84,TPA!B:Z,7,FALSE)) -> AA | F84: Teknik Industri | G84: 22970044 | H84: 719079702 | I84: 4051775676130153 | J84: =IF(D84="DOSEN",VLOOKUP(B84,Dosen!B:Z,7,FALSE),VLOOKUP(B84,TPA!B:Z,5,FALSE)) -> PROFESIONAL | L84: S.T., M.Sc. | M84: =IF(D84="DOSEN",VLOOKUP(B84,Dosen!B:ZZ,33,FALSE),VLOOKUP(B84,TPA!B:ZZ,44,FALSE)) -> S2 | N84: 44832 | P84: =IF(O84="",DATEDIF(N84,TODAY(),"y")&" tahun "&DATEDIF(N84,TODAY(),"ym")&" bulan ",DATEDIF(N84,O84,"y")&" tahun "&DATEDIF(N84,O84,"ym")&" bulan ") -> 3 tahun 3 bulan | Q84: hukichandra@ittelkom-sby.ac.id | R84: 81333596409 | S84: Jl. Riau Ujung GG Karya Makmur No 01, Payung Sekaki, Pekanbaru
A85: 84 | B85: Aufar Fikri Dimyati | C85: Aktif | D85: Dosen | E85: =IF(D85="DOSEN",VLOOKUP(B85,Dosen!B:Z,11,FALSE),VLOOKUP(B85,TPA!B:Z,7,FALSE)) -> AA | F85: Teknik Industri | G85: 23970026 | H85: 718099702 | I85: 0250775676130133 | J85: =IF(D85="DOSEN",VLOOKUP(B85,Dosen!B:Z,7,FALSE),VLOOKUP(B85,TPA!B:Z,5,FALSE)) -> PROFESIONAL | L85: S.T., M.T. | M85: =IF(D85="DOSEN",VLOOKUP(B85,Dosen!B:ZZ,33,FALSE),VLOOKUP(B85,TPA!B:ZZ,44,FALSE)) -> S2 | N85: 45170 | P85: =IF(O85="",DATEDIF(N85,TODAY(),"y")&" tahun "&DATEDIF(N85,TODAY(),"ym")&" bulan ",DATEDIF(N85,O85,"y")&" tahun "&DATEDIF(N85,O85,"ym")&" bulan ") -> 2 tahun 4 bulan | Q85: aufar.dimyati@ittelkom-sby.ac.id | R85: 82228377835 | S85: Jl. Jawa II Gg. 7, Sumbersari, Jember, 68121
A86: 85 | B86: Paramaditya Arismawati | C86: Aktif | D86: Dosen | E86: =IF(D86="DOSEN",VLOOKUP(B86,Dosen!B:Z,11,FALSE),VLOOKUP(B86,TPA!B:Z,7,FALSE)) -> NJAD | F86: Teknik Industri | G86: 22950019 | H86: 706019502 | I86: 6438773674230212 | J86: =IF(D86="DOSEN",VLOOKUP(B86,Dosen!B:Z,7,FALSE),VLOOKUP(B86,TPA!B:Z,5,FALSE)) -> TETAP | L86: S.T., M.T. | M86: =IF(D86="DOSEN",VLOOKUP(B86,Dosen!B:ZZ,33,FALSE),VLOOKUP(B86,TPA!B:ZZ,44,FALSE)) -> S2 | N86: 45170 | P86: =IF(O86="",DATEDIF(N86,TODAY(),"y")&" tahun "&DATEDIF(N86,TODAY(),"ym")&" bulan ",DATEDIF(N86,O86,"y")&" tahun "&DATEDIF(N86,O86,"ym")&" bulan ") -> 2 tahun 4 bulan | Q86: dityaars@ittelkom-sby.ac.id | R86: 81295227089 | S86: Jl. Legenda Wisata Zona Vasco da Gama P1/12
A87: 86 | B87: Bambang Lelono Widjiantoro | C87: Non-Aktif | D87: Dosen | E87: =IF(D87="DOSEN",VLOOKUP(B87,Dosen!B:Z,11,FALSE),VLOOKUP(B87,TPA!B:Z,7,FALSE)) -> LK | F87: Teknik Industri | G87: 20690002 | H87: 7056901 | J87: =IF(D87="DOSEN",VLOOKUP(B87,Dosen!B:Z,7,FALSE),VLOOKUP(B87,TPA!B:Z,5,FALSE)) -> PERBANTUAN | K87: Dr. | L87: S.T., M.T. | M87: =IF(D87="DOSEN",VLOOKUP(B87,Dosen!B:ZZ,33,FALSE),VLOOKUP(B87,TPA!B:ZZ,44,FALSE)) -> S3 | N87: 43882 | O87: 45761 | P87: =IF(O87="",DATEDIF(N87,TODAY(),"y")&" tahun "&DATEDIF(N87,TODAY(),"ym")&" bulan ",DATEDIF(N87,O87,"y")&" tahun "&DATEDIF(N87,O87,"ym")&" bulan ") -> 5 tahun 1 bulan | Q87: bambang@ittelkom-sby.ac.id
A88: 87 | B88: Wahyu Andy Prastyabudi | C88: Aktif | D88: Dosen | E88: =IF(D88="DOSEN",VLOOKUP(B88,Dosen!B:Z,11,FALSE),VLOOKUP(B88,TPA!B:Z,7,FALSE)) -> L | F88: Teknik Industri | G88: 19870002 | H88: 702048705 | I88: 6536765666130262 | J88: =IF(D88="DOSEN",VLOOKUP(B88,Dosen!B:Z,7,FALSE),VLOOKUP(B88,TPA!B:Z,5,FALSE)) -> TETAP | L88: S.Kom., M.Sc. | M88: =IF(D88="DOSEN",VLOOKUP(B88,Dosen!B:ZZ,33,FALSE),VLOOKUP(B88,TPA!B:ZZ,44,FALSE)) -> S2 | N88: 43101 | P88: =IF(O88="",DATEDIF(N88,TODAY(),"y")&" tahun "&DATEDIF(N88,TODAY(),"ym")&" bulan ",DATEDIF(N88,O88,"y")&" tahun "&DATEDIF(N88,O88,"ym")&" bulan ") -> 8 tahun 0 bulan | Q88: wahyu.andy@ittelkom-sby.ac.id | R88: 81217225716 | S88: Mulyorejo Utara 203-B, Surabaya
A89: 88 | B89: Ardiansyah Al Farouq | C89: Aktif | D89: Dosen | E89: =IF(D89="DOSEN",VLOOKUP(B89,Dosen!B:Z,11,FALSE),VLOOKUP(B89,TPA!B:Z,7,FALSE)) -> L | F89: Teknik Komputer | G89: 20930033 | H89: 714029301 | I89: 0546771672130272 | J89: =IF(D89="DOSEN",VLOOKUP(B89,Dosen!B:Z,7,FALSE),VLOOKUP(B89,TPA!B:Z,5,FALSE)) -> TETAP | L89: S.ST., M.T. | M89: =IF(D89="DOSEN",VLOOKUP(B89,Dosen!B:ZZ,33,FALSE),VLOOKUP(B89,TPA!B:ZZ,44,FALSE)) -> S2 | N89: 43282 | P89: =IF(O89="",DATEDIF(N89,TODAY(),"y")&" tahun "&DATEDIF(N89,TODAY(),"ym")&" bulan ",DATEDIF(N89,O89,"y")&" tahun "&DATEDIF(N89,O89,"ym")&" bulan ") -> 7 tahun 6 bulan | Q89: alfarouq@ittelkom-sby.ac.id | R89: 81241833022 | S89: teluk nibung barat 4/12 perak utara surabaya
A90: 89 | B90: Mohamad Yani | C90: Aktif | D90: Dosen | E90: =IF(D90="DOSEN",VLOOKUP(B90,Dosen!B:Z,11,FALSE),VLOOKUP(B90,TPA!B:Z,7,FALSE)) -> NJAD | F90: Teknik Komputer | G90: 17910092 | H90: 701129102 | I90: 0444769670130282 | J90: =IF(D90="DOSEN",VLOOKUP(B90,Dosen!B:Z,7,FALSE),VLOOKUP(B90,TPA!B:Z,5,FALSE)) -> PROFESIONAL | L90: S.ST., M.Phil., Ph.D. | M90: =IF(D90="DOSEN",VLOOKUP(B90,Dosen!B:ZZ,33,FALSE),VLOOKUP(B90,TPA!B:ZZ,44,FALSE)) -> S3 | N90: 43101 | P90: =IF(O90="",DATEDIF(N90,TODAY(),"y")&" tahun "&DATEDIF(N90,TODAY(),"ym")&" bulan ",DATEDIF(N90,O90,"y")&" tahun "&DATEDIF(N90,O90,"ym")&" bulan ") -> 8 tahun 0 bulan | Q90: mai@ittelkom-sby.ac.id | R90: 81226595253 | S90: MEDOKAN AYU MA-I/J-35, SURABAYA
A91: 90 | B91: Pangestu Widodo | C91: Aktif | D91: Dosen | E91: =IF(D91="DOSEN",VLOOKUP(B91,Dosen!B:Z,11,FALSE),VLOOKUP(B91,TPA!B:Z,7,FALSE)) -> AA | F91: Teknik Komputer | G91: 20830012 | H91: 721058310 | I91: 6853761662130212 | J91: =IF(D91="DOSEN",VLOOKUP(B91,Dosen!B:Z,7,FALSE),VLOOKUP(B91,TPA!B:Z,5,FALSE)) -> TETAP | L91: S.T., M.Kom. | M91: =IF(D91="DOSEN",VLOOKUP(B91,Dosen!B:ZZ,33,FALSE),VLOOKUP(B91,TPA!B:ZZ,44,FALSE)) -> S2 | N91: 43282 | P91: =IF(O91="",DATEDIF(N91,TODAY(),"y")&" tahun "&DATEDIF(N91,TODAY(),"ym")&" bulan ",DATEDIF(N91,O91,"y")&" tahun "&DATEDIF(N91,O91,"ym")&" bulan ") -> 7 tahun 6 bulan | Q91: pangestu@ittelkom-sby.ac.id | R91: 85258754375 | S91: Jl. Tumapel 1 RT/RW 007/009 Kel. Kauman Kec. Klojen Kota Malang
A92: 91 | B92: Susijanto Tri Rasmana | C92: Aktif | D92: Dosen | E92: =IF(D92="DOSEN",VLOOKUP(B92,Dosen!B:Z,11,FALSE),VLOOKUP(B92,TPA!B:Z,7,FALSE)) -> L | F92: Teknik Komputer | G92: 22730002 | H92: 727097302 | I92: 4259751652130093 | J92: =IF(D92="DOSEN",VLOOKUP(B92,Dosen!B:Z,7,FALSE),VLOOKUP(B92,TPA!B:Z,5,FALSE)) -> TETAP | K92: Dr. | L92: S.Kom., M.T. | M92: =IF(D92="DOSEN",VLOOKUP(B92,Dosen!B:ZZ,33,FALSE),VLOOKUP(B92,TPA!B:ZZ,44,FALSE)) -> S3 | N92: 44075 | P92: =IF(O92="",DATEDIF(N92,TODAY(),"y")&" tahun "&DATEDIF(N92,TODAY(),"ym")&" bulan ",DATEDIF(N92,O92,"y")&" tahun "&DATEDIF(N92,O92,"ym")&" bulan ") -> 5 tahun 4 bulan | Q92: susijanto@ittelkom-sby.ac.id | R92: 81216170645 | S92: Jl. Merak III A/Q45, Sidoarjo
A93: 92 | B93: Aulia Rahma Annisa | C93: Non-Aktif | D93: Dosen | E93: =IF(D93="DOSEN",VLOOKUP(B93,Dosen!B:Z,11,FALSE),VLOOKUP(B93,TPA!B:Z,7,FALSE)) -> AA | F93: Teknik Komputer | G93: 23910011 | H93: 303069102 | J93: =IF(D93="DOSEN",VLOOKUP(B93,Dosen!B:Z,7,FALSE),VLOOKUP(B93,TPA!B:Z,5,FALSE)) -> PROFESIONAL | L93: S.ST., M.T. | M93: =IF(D93="DOSEN",VLOOKUP(B93,Dosen!B:ZZ,33,FALSE),VLOOKUP(B93,TPA!B:ZZ,44,FALSE)) -> S2 | N93: 44562 | O93: 45473 | P93: =IF(O93="",DATEDIF(N93,TODAY(),"y")&" tahun "&DATEDIF(N93,TODAY(),"ym")&" bulan ",DATEDIF(N93,O93,"y")&" tahun "&DATEDIF(N93,O93,"ym")&" bulan ") -> 2 tahun 5 bulan | Q93: aulia.ra@ittelkom-sby.ac.id | R93: 82143778029 | S93: Dsn. Gareman, Babadan, Patianrowo, Nganjuk
A94: 93 | B94: Nanda Iryani | C94: Non-Aktif | D94: Dosen | E94: =IF(D94="DOSEN",VLOOKUP(B94,Dosen!B:Z,11,FALSE),VLOOKUP(B94,TPA!B:Z,7,FALSE)) -> AA | F94: Teknik Komputer | G94: 22930046 | H94: 604059302 | J94: =IF(D94="DOSEN",VLOOKUP(B94,Dosen!B:Z,7,FALSE),VLOOKUP(B94,TPA!B:Z,5,FALSE)) -> PROFESIONAL | L94: S.T., M.T. | M94: =IF(D94="DOSEN",VLOOKUP(B94,Dosen!B:ZZ,33,FALSE),VLOOKUP(B94,TPA!B:ZZ,44,FALSE)) -> S2 | N94: 44832 | O94: 45169 | P94: =IF(O94="",DATEDIF(N94,TODAY(),"y")&" tahun "&DATEDIF(N94,TODAY(),"ym")&" bulan ",DATEDIF(N94,O94,"y")&" tahun "&DATEDIF(N94,O94,"ym")&" bulan ") -> 0 tahun 11 bulan | Q94: nandandi@ittelkom-sby.ac.id | R94: 82137220958 | S94: Peum Sumber Taman Indah Blok OO-8, Wonoasih, Probolinggo
A95: 94 | B95: Ubaidillah Umar | C95: Aktif | D95: Dosen | E95: =IF(D95="DOSEN",VLOOKUP(B95,Dosen!B:Z,11,FALSE),VLOOKUP(B95,TPA!B:Z,7,FALSE)) -> L | F95: Teknik Komputer | G95: 19880003 | H95: 727048809 | I95: 6759766667131102 | J95: =IF(D95="DOSEN",VLOOKUP(B95,Dosen!B:Z,7,FALSE),VLOOKUP(B95,TPA!B:Z,5,FALSE)) -> TETAP | L95: S.ST., M.T. | M95: =IF(D95="DOSEN",VLOOKUP(B95,Dosen!B:ZZ,33,FALSE),VLOOKUP(B95,TPA!B:ZZ,44,FALSE)) -> S2 | N95: 43101 | P95: =IF(O95="",DATEDIF(N95,TODAY(),"y")&" tahun "&DATEDIF(N95,TODAY(),"ym")&" bulan ",DATEDIF(N95,O95,"y")&" tahun "&DATEDIF(N95,O95,"ym")&" bulan ") -> 8 tahun 0 bulan | Q95: ubaidillahumar@ittelkom-sby.ac.id | R95: 82336823404 | S95: Tambak Bening 5/6, Tambak Rejo, Simokerto, Surabaya
A96: 95 | B96: Eka Sari Oktarina | C96: Aktif | D96: Dosen | E96: =IF(D96="DOSEN",VLOOKUP(B96,Dosen!B:Z,11,FALSE),VLOOKUP(B96,TPA!B:Z,7,FALSE)) -> AA | F96: Teknik Komputer | G96: 23910008 | H96: 404109105 | I96: 1336769670230333 | J96: =IF(D96="DOSEN",VLOOKUP(B96,Dosen!B:Z,7,FALSE),VLOOKUP(B96,TPA!B:Z,5,FALSE)) -> PROFESIONAL | L96: S.Kom., M.Eng. | M96: =IF(D96="DOSEN",VLOOKUP(B96,Dosen!B:ZZ,33,FALSE),VLOOKUP(B96,TPA!B:ZZ,44,FALSE)) -> S2 | N96: 45170 | P96: =IF(O96="",DATEDIF(N96,TODAY(),"y")&" tahun "&DATEDIF(N96,TODAY(),"ym")&" bulan ",DATEDIF(N96,O96,"y")&" tahun "&DATEDIF(N96,O96,"ym")&" bulan ") -> 2 tahun 4 bulan | Q96: ekasari@ittelkom-sby.ac.id | R96: 81945944686 | S96: Perum Purimas Regency B2/16, Surabaya
A97: 96 | B97: Abduh Sayid Albana | C97: Aktif | D97: Dosen | E97: =IF(D97="DOSEN",VLOOKUP(B97,Dosen!B:Z,11,FALSE),VLOOKUP(B97,TPA!B:Z,7,FALSE)) -> L | F97: Teknik Logistik | G97: 19900001 | H97: 702039003 | I97: 9634768669130272 | J97: =IF(D97="DOSEN",VLOOKUP(B97,Dosen!B:Z,7,FALSE),VLOOKUP(B97,TPA!B:Z,5,FALSE)) -> TETAP | L97: S.T., M.T., M.Sc., Ph.D. | M97: =IF(D97="DOSEN",VLOOKUP(B97,Dosen!B:ZZ,33,FALSE),VLOOKUP(B97,TPA!B:ZZ,44,FALSE)) -> S3 | N97: 43282 | P97: =IF(O97="",DATEDIF(N97,TODAY(),"y")&" tahun "&DATEDIF(N97,TODAY(),"ym")&" bulan ",DATEDIF(N97,O97,"y")&" tahun "&DATEDIF(N97,O97,"ym")&" bulan ") -> 7 tahun 6 bulan | Q97: abduh.albana@ittelkom-sby.ac.id | R97: 82142628195 | S97: Perum. Kwayangan Jl. Amarta IV, Rt.04 Rw.03, Ds. Kwayangan, Kec. Kedungwuni, Kab. Pekalongan, Jawa Tengah - 51173
A98: 97 | B98: Erly Ekayanti Rosyida | C98: Aktif | D98: Dosen | E98: =IF(D98="DOSEN",VLOOKUP(B98,Dosen!B:Z,11,FALSE),VLOOKUP(B98,TPA!B:Z,7,FALSE)) -> L | F98: Teknik Logistik | G98: 25820001 | H98: 702038201 | I98: 4634760661230252 | J98: =IF(D98="DOSEN",VLOOKUP(B98,Dosen!B:Z,7,FALSE),VLOOKUP(B98,TPA!B:Z,5,FALSE)) -> PROFESIONAL | K98: Dr. | L98: S.T., M.T. | M98: =IF(D98="DOSEN",VLOOKUP(B98,Dosen!B:ZZ,33,FALSE),VLOOKUP(B98,TPA!B:ZZ,44,FALSE)) -> S3 | N98: 45689 | P98: =IF(O98="",DATEDIF(N98,TODAY(),"y")&" tahun "&DATEDIF(N98,TODAY(),"ym")&" bulan ",DATEDIF(N98,O98,"y")&" tahun "&DATEDIF(N98,O98,"ym")&" bulan ") -> 0 tahun 11 bulan | Q98: erlyekayantir@gmail.com | R98: 82245916300 | S98: WONOKAYUN RT 009 RW 005, KEL. WONOKARANG, KEC. BALONGBENDO, KAB. SIDOARJO
A99: 98 | B99: Ahmad Faisal Dahlan | C99: Non-Aktif | D99: Dosen | E99: =IF(D99="DOSEN",VLOOKUP(B99,Dosen!B:Z,11,FALSE),VLOOKUP(B99,TPA!B:Z,7,FALSE)) -> NJAD | F99: Teknik Logistik | G99: 20940045 | H99: 724019401 | J99: =IF(D99="DOSEN",VLOOKUP(B99,Dosen!B:Z,7,FALSE),VLOOKUP(B99,TPA!B:Z,5,FALSE)) -> PROFESIONAL | L99: hlia | M99: =IF(D99="DOSEN",VLOOKUP(B99,Dosen!B:ZZ,33,FALSE),VLOOKUP(B99,TPA!B:ZZ,44,FALSE)) -> S2 | N99: 44166 | O99: 45291 | P99: =IF(O99="",DATEDIF(N99,TODAY(),"y")&" tahun "&DATEDIF(N99,TODAY(),"ym")&" bulan ",DATEDIF(N99,O99,"y")&" tahun "&DATEDIF(N99,O99,"ym")&" bulan ") -> 3 tahun 0 bulan | Q99: faisal@ittelkom-sby.ac.id | R99: 81325336037 | S99: Jl. Bendungan Sutami No. 7, Sumbersari, Lowokwaru, Malang
A100: 99 | B100: Desita Nur Rachmaniar | C100: Aktif | D100: Dosen | E100: =IF(D100="DOSEN",VLOOKUP(B100,Dosen!B:Z,11,FALSE),VLOOKUP(B100,TPA!B:Z,7,FALSE)) -> AA | F100: Teknik Logistik | G100: 20930071 | H100: 707029303 | I100: 5539771672230282 | J100: =IF(D100="DOSEN",VLOOKUP(B100,Dosen!B:Z,7,FALSE),VLOOKUP(B100,TPA!B:Z,5,FALSE)) -> TETAP | L100: S.T., M.Sc. | M100: =IF(D100="DOSEN",VLOOKUP(B100,Dosen!B:ZZ,33,FALSE),VLOOKUP(B100,TPA!B:ZZ,44,FALSE)) -> S2 | N100: 44166 | P100: =IF(O100="",DATEDIF(N100,TODAY(),"y")&" tahun "&DATEDIF(N100,TODAY(),"ym")&" bulan ",DATEDIF(N100,O100,"y")&" tahun "&DATEDIF(N100,O100,"ym")&" bulan ") -> 5 tahun 1 bulan | Q100: desitanurr@ittelkom-sby.ac.id | R100: 8113770702 | S100: Jl. Jomegatan, Ngestiharjo, Kasihan, Bantul
...

Sheet Sheet4
A3: Nama | B3: Program Studi | C3: Pendidikan | D3: Bidang Ilmu
A4: Dr. Mohammad Yanuar Hariyawan, S.T., M.T. | B4: S1 Teknik Telekomunikasi | C4: S1 Teknik Elektro - Telekomunikasi Multimedia S2 Teknik Elektro - Telekomunikasi Multimedia S3 Ilmu Teknik Elektro | D4: Electromagnetic Compatibility
A5: Dr. Helmy Widyantara, S.Kom, M.Eng. | B5: S1 Teknologi Informasi | C5: S1 Teknik Komputer S2 Teknik Elektro S3 Teknik Elektro | D5: Otomasi Sistem

Sheet Proyeksi LK GB
A1: No | B1: NAMA | C1: PRODI | D1: JAFA LLDIKTI | E1: TMT JAFA | F1: MASA JAFA | G1: Target
A2: =A1+1 -> #VALUE! | B2: Titus Kristanto | C2: Digital Bisnis | D2: L | E2: 44428 | F2: =DATEDIF(E2,TODAY(), "Y") & " Tahun " & DATEDIF(E2, TODAY(), "YM") & " Bulan" -> 4 Tahun 4 Bulan | G2: 2029
A3: =A2+1 -> #VALUE! | B3: Bambang Agus Sumantri | C3: Digital Bisnis | D3: L | E3: 44090 | F3: =DATEDIF(E3,TODAY(), "Y") & " Tahun " & DATEDIF(E3, TODAY(), "YM") & " Bulan" -> 5 Tahun 4 Bulan | G3: 2026
A4: =A3+1 -> #VALUE! | B4: Ahmad Wali Satria Bahari Johan | C4: Informatika | D4: L | E4: 45901 | F4: =DATEDIF(E4,TODAY(), "Y") & " Tahun " & DATEDIF(E4, TODAY(), "YM") & " Bulan" -> 0 Tahun 4 Bulan | G4: 2033
A5: =A4+1 -> #VALUE! | B5: Dyah Putri Rahmawati | C5: Informatika | D5: L | E5: 45870 | F5: =DATEDIF(E5,TODAY(), "Y") & " Tahun " & DATEDIF(E5, TODAY(), "YM") & " Bulan" -> 0 Tahun 5 Bulan | G5: =YEAR(E5)+5 -> 2030
A6: =A5+1 -> #VALUE! | B6: Fidi Wincoko Putro | C6: Rekayasa Perangkat Lunak | D6: L | E6: 45901 | F6: =DATEDIF(E6,TODAY(), "Y") & " Tahun " & DATEDIF(E6, TODAY(), "YM") & " Bulan" -> 0 Tahun 4 Bulan | G6: 2033
A7: =A6+1 -> #VALUE! | B7: Dewi Rahmawati | C7: Rekayasa Perangkat Lunak | D7: L | E7: 45108 | F7: =DATEDIF(E7,TODAY(), "Y") & " Tahun " & DATEDIF(E7, TODAY(), "YM") & " Bulan" -> 2 Tahun 6 Bulan | G7: =YEAR(E7)+5 -> 2028
A8: =A7+1 -> #VALUE! | B8: Achmad Muzakki | C8: Rekayasa Perangkat Lunak | D8: L | E8: 45901 | F8: =DATEDIF(E8,TODAY(), "Y") & " Tahun " & DATEDIF(E8, TODAY(), "YM") & " Bulan" -> 0 Tahun 4 Bulan | G8: 2033
A9: =A8+1 -> #VALUE! | B9: Dahliar Ananda | C9: Rekayasa Perangkat Lunak | D9: L | E9: 45627 | F9: =DATEDIF(E9,TODAY(), "Y") & " Tahun " & DATEDIF(E9, TODAY(), "YM") & " Bulan" -> 1 Tahun 1 Bulan | G9: 2033
A10: =A9+1 -> #VALUE! | B10: Alon Jala Tirta Segara | C10: Rekayasa Perangkat Lunak | D10: L | E10: 45261 | F10: =DATEDIF(E10,TODAY(), "Y") & " Tahun " & DATEDIF(E10, TODAY(), "YM") & " Bulan" -> 2 Tahun 1 Bulan | G10: =YEAR(E10)+5 -> 2028
A11: =A10+1 -> #VALUE! | B11: Moh. Hamim Zajuli Al Faroby | C11: Sains Data | D11: L | E11: 45931 | F11: =DATEDIF(E11,TODAY(), "Y") & " Tahun " & DATEDIF(E11, TODAY(), "YM") & " Bulan" -> 0 Tahun 3 Bulan | G11: 2033
A12: =A11+1 -> #VALUE! | B12: Noerma Pudji Istyanto | C12: Sistem Informasi | D12: L | E12: 45108 | F12: =DATEDIF(E12,TODAY(), "Y") & " Tahun " & DATEDIF(E12, TODAY(), "YM") & " Bulan" -> 2 Tahun 6 Bulan | G12: 2033
A13: =A12+1 -> #VALUE! | B13: Agus Sulistya | C13: Sistem Informasi | D13: L | E13: 45444 | F13: =DATEDIF(E13,TODAY(), "Y") & " Tahun " & DATEDIF(E13, TODAY(), "YM") & " Bulan" -> 1 Tahun 7 Bulan | G13: 2033
A14: =A13+1 -> #VALUE! | B14: Dimas Adiputra | C14: Teknik Elektro | D14: L | E14: 45108 | F14: =DATEDIF(E14,TODAY(), "Y") & " Tahun " & DATEDIF(E14, TODAY(), "YM") & " Bulan" -> 2 Tahun 6 Bulan | G14: 2027
A15: =A14+1 -> #VALUE! | B15: Isa Hafidz | C15: Teknik Elektro | D15: L | E15: 45108 | F15: =DATEDIF(E15,TODAY(), "Y") & " Tahun " & DATEDIF(E15, TODAY(), "YM") & " Bulan" -> 2 Tahun 6 Bulan | G15: =YEAR(E15)+5 -> 2028
A16: =A15+1 -> #VALUE! | B16: Lora Khaula Amifia | C16: Teknik Elektro | D16: L | E16: 44805 | F16: =DATEDIF(E16,TODAY(), "Y") & " Tahun " & DATEDIF(E16, TODAY(), "YM") & " Bulan" -> 3 Tahun 4 Bulan | G16: 2033
A17: =A16+1 -> #VALUE! | B17: Chaironi Latif | C17: Teknik Elektro | D17: L | E17: 45962 | F17: =DATEDIF(E17,TODAY(), "Y") & " Tahun " & DATEDIF(E17, TODAY(), "YM") & " Bulan" -> 0 Tahun 2 Bulan | G17: 2033
A18: =A17+1 -> #VALUE! | B18: Wahyu Andy Prastyabudi | C18: Teknik Industri | D18: L | E18: 45108 | F18: =DATEDIF(E18,TODAY(), "Y") & " Tahun " & DATEDIF(E18, TODAY(), "YM") & " Bulan" -> 2 Tahun 6 Bulan | G18: 2030
A19: =A18+1 -> #VALUE! | B19: Rizqa Amelia Zunaidi | C19: Teknik Industri | D19: L | E19: 44927 | F19: =DATEDIF(E19,TODAY(), "Y") & " Tahun " & DATEDIF(E19, TODAY(), "YM") & " Bulan" -> 3 Tahun 0 Bulan | G19: 2033
A20: =A19+1 -> #VALUE! | B20: Benazir Imam Arif Muttaqin | C20: Teknik Industri | D20: L | E20: 44866 | F20: =DATEDIF(E20,TODAY(), "Y") & " Tahun " & DATEDIF(E20, TODAY(), "YM") & " Bulan" -> 3 Tahun 2 Bulan | G20: =YEAR(E20)+5 -> 2027
A21: =A20+1 -> #VALUE! | B21: Ayu Endah Wahyuni | C21: Teknik Industri | D21: L | E21: 45108 | F21: =DATEDIF(E21,TODAY(), "Y") & " Tahun " & DATEDIF(E21, TODAY(), "YM") & " Bulan" -> 2 Tahun 6 Bulan | G21: 2033
A22: =A21+1 -> #VALUE! | B22: Ubaidillah Umar | C22: Teknik Komputer | D22: L | E22: 45413 | F22: =DATEDIF(E22,TODAY(), "Y") & " Tahun " & DATEDIF(E22, TODAY(), "YM") & " Bulan" -> 1 Tahun 8 Bulan | G22: 2030
A23: =A22+1 -> #VALUE! | B23: Ardiansyah Al Farouq | C23: Teknik Komputer | D23: L | E23: 44805 | F23: =DATEDIF(E23,TODAY(), "Y") & " Tahun " & DATEDIF(E23, TODAY(), "YM") & " Bulan" -> 3 Tahun 4 Bulan | G23: 2031
A24: =A23+1 -> #VALUE! | B24: Susijanto Tri Rasmana | C24: Teknik Komputer | D24: L | E24: 45108 | F24: =DATEDIF(E24,TODAY(), "Y") & " Tahun " & DATEDIF(E24, TODAY(), "YM") & " Bulan" -> 2 Tahun 6 Bulan | G24: =YEAR(E24)+5 -> 2028
A25: =A24+1 -> #VALUE! | B25: Abduh Sayid Albana | C25: Teknik Logistik | D25: L | E25: 44032 | F25: =DATEDIF(E25,TODAY(), "Y") & " Tahun " & DATEDIF(E25, TODAY(), "YM") & " Bulan" -> 5 Tahun 5 Bulan | G25: 2027
A26: =A25+1 -> #VALUE! | B26: Erly Ekayanti Rosyida | C26: Teknik Logistik | D26: L | E26: 41365 | F26: =DATEDIF(E26,TODAY(), "Y") & " Tahun " & DATEDIF(E26, TODAY(), "YM") & " Bulan" -> 12 Tahun 9 Bulan | G26: 2027
A27: =A26+1 -> #VALUE! | B27: Muhsin | C27: Teknik Telekomunikasi | D27: L | E27: 45108 | F27: =DATEDIF(E27,TODAY(), "Y") & " Tahun " & DATEDIF(E27, TODAY(), "YM") & " Bulan" -> 2 Tahun 6 Bulan | G27: =YEAR(E27)+5 -> 2028
A28: =A27+1 -> #VALUE! | B28: Fannush Shofi Akbar | C28: Teknik Telekomunikasi | D28: L | E28: 45108 | F28: =DATEDIF(E28,TODAY(), "Y") & " Tahun " & DATEDIF(E28, TODAY(), "YM") & " Bulan" -> 2 Tahun 6 Bulan | G28: =YEAR(E28)+5 -> 2028
A29: =A28+1 -> #VALUE! | B29: Hendy Briantoro | C29: Teknik Telekomunikasi | D29: L | E29: 45597 | F29: =DATEDIF(E29,TODAY(), "Y") & " Tahun " & DATEDIF(E29, TODAY(), "YM") & " Bulan" -> 1 Tahun 2 Bulan | G29: 2033
A30: 1 | B30: Mohammad Yanuar Hariyawan | C30: Teknik Telekomunikasi | D30: LK | E30: 41852 | F30: =DATEDIF(E30,TODAY(), "Y") & " Tahun " & DATEDIF(E30, TODAY(), "YM") & " Bulan" -> 11 Tahun 5 Bulan | G30: 2027
A31: =A30+1 -> 2 | B31: Khodijah Amiroh | C31: Teknologi Informasi | D31: L | E31: 44958 | F31: =DATEDIF(E31,TODAY(), "Y") & " Tahun " & DATEDIF(E31, TODAY(), "YM") & " Bulan" -> 2 Tahun 11 Bulan | G31: 2029
A32: =A31+1 -> 3 | B32: Farah Zakiyah Rahmanti | C32: Teknologi Informasi | D32: L | E32: 43984 | F32: =DATEDIF(E32,TODAY(), "Y") & " Tahun " & DATEDIF(E32, TODAY(), "YM") & " Bulan" -> 5 Tahun 7 Bulan | G32: 2029
A33: =A32+1 -> 4 | B33: Helmy Widyantara | C33: Teknologi Informasi | D33: LK | E33: 45200 | F33: =DATEDIF(E33,TODAY(), "Y") & " Tahun " & DATEDIF(E33, TODAY(), "YM") & " Bulan" -> 2 Tahun 3 Bulan | G33: 2028
A34: =A33+1 -> 5 | B34: Philip Tobianto Daely | C34: Teknologi Informasi | D34: L | E34: 45597 | F34: =DATEDIF(E34,TODAY(), "Y") & " Tahun " & DATEDIF(E34, TODAY(), "YM") & " Bulan" -> 1 Tahun 2 Bulan | G34: =YEAR(E34)+5 -> 2029
A35: =A34+1 -> 6 | B35: Bernadus Anggo Seno Aji | C35: Teknologi Informasi | D35: L | E35: 45931 | F35: =DATEDIF(E35,TODAY(), "Y") & " Tahun " & DATEDIF(E35, TODAY(), "YM") & " Bulan" -> 0 Tahun 3 Bulan | G35: 2033

Sheet Dosen
A1: No | B1: NAMA | C1: Status Aktif | D1: PRODI | E1: NIP YPT | F1: NIDN | G1: NUPTK | H1: STATUS | I1: GELAR DEPAN | J1: GELAR BELAKANG | K1: ENTRY LEVEL | L1: JAFA LLDIKTI | M1: KENAIKAN JAFA KE- | N1: PROGRESS JAFUNG | O1: KUM JAFA TERAKHIR LLDIKTI | P1: BIDANG KEILMUAN JAFA TERAKHIR LLDIKTI | Q1: TMT JAFA TERAKHIR LLDIKTI / TMT DOSEN TETAP | R1: MASA JAFA TERAKHIR LLDIKTI (TAHUN) | S1: PANGKAT / GOLONGAN TERAKHIR | T1: TMT PANGKAT | U1: MASA KERJA PANGKAT TERAKHIR LLDIKTI | V1: POSISI | W1: PROFESI | X1: Nominasi Serdos | Y1: Eligible / Progress Serdos | Z1: SERTIFIKASI DOSEN | AA1: NOMOR REGISTRASI SERDOS | AB1: NOMOR SK SERDOS | AC1: TANGGAL SERDOS | AD1: NIRA | AE1: NOMOR NIRA | AF1: NOMOR SK NIRA | AG1: TANGGAL NIRA | AH1: PENDIDIKAN TERAKHIR | AI1: On Progress S3 | AJ1: JENIS IZIN STUDI | AK1: PID | AL1: PROGRESS PENDIDIKAN | AM1: TMT MASUK DOSEN (SESUAI KONTRAK) | AN1: MASA KERJA DOSEN | AO1: FAKULTAS | AP1: LOKASI KERJA PRODI FAKULTAS | AQ1: KODE DOSEN | AR1: Email Domain | AS1: No HP | AT1: ALAMAT | AU1: Keterangan Pindah Homebase / NIDN | AW1: Nama Gelar | AX1: Jenis Kelamin | AY1: Tempat Lahir | AZ1: Tanggal Lahir | BA1: Usia | BB1: Tahun dari TMT | BC1: Batas Eligibilitas | BD1: Tahun dari TMT | BE1: Eligible naik pangkat? | BF1: JENIS PEMBIAYAAN S3 | BG1: KATEGORI BEASISWA | BH1: NO. PID | BI1: TANGGAL PID | BJ1: TANGGAL MULAI PID | BK1: TANGGAL SELESAI PID | BL1: Struktural | BM1: TMT Non Aktif | BN1: TMT S3 | BO1: Selisih S3 | BP1: Selisih S3 (sems) | BQ1: Kelompok Keahlian ITTS | BR1: Kelompok Keahlian Tel-U | BS1: Kode Dosen Baru | BT1: FAKULTAS TELKOM UNIVERSITY SURABAYA | BU1: Email Domain Telkom University | BW1: MASA KERJA 1 Januari 2026 | BX1: S1 Kampus | BY1: S1 Prodi | BZ1: S2 Kampus | CA1: S2 Prodi | CB1: S3 Kampus | CC1: S3 Prodi | CD1: COE | CE1: KK | CF1: TGL NON AKTIF
A2: 26 | B2: Dominggo Bayu Baskara | C2: Aktif | D2: Digital Bisnis | E2: 19900005 | F2: 0722069004 | G2: 6954768669130292 | H2: TETAP | I2: Ir. | J2: S.T., M.MT. | K2: AA.2 | L2: AA | M2: =IF(L2="NJAD","AA",IF(L2="AA","L",IF(L2="L","LK","GB"))) -> L | N2: - | O2: 150 | P2: Manajemen Proyek dan Studi Kelayakan | Q2: 43990 | R2: =DATEDIF(Q2,TODAY(), "Y") & " Tahun " & DATEDIF(Q2, TODAY(), "YM") & " Bulan" -> 5 Tahun 7 Bulan | S2: Penata Muda Tk. I Golongan III/b | T2: 44044 | U2: =DATEDIF(T2,TODAY(), "Y") & " Tahun " & DATEDIF(T2, TODAY(), "YM") & " Bulan" -> 5 Tahun 5 Bulan | V2: Dosen S1 Digital Bisnis | W2: DOSEN | X2: =IF(AND(OR(L2="AA",L2="L"),OR(S2="Penata Muda Tk. I Golongan III/b",S2="Penata Golongan III/c"),DATEDIF(Q2,TODAY(),"m")>=23,ISBLANK(Z2),C2="Aktif"),"Nominasi Serdos","-") -> - | Z2: Punya | AA2: 22107201905191 | AB2: 22-001027-0048 | AC2: 44846 | AH2: S2 | AI2: Ya | AJ2: TB | AK2: Ya | AL2: On Progress S3 TB | AM2: 43101 | AN2: =DATEDIF(AM2,TODAY(),"y")&" tahun "&DATEDIF(AM2,TODAY(),"ym")&" bulan " -> 8 tahun 0 bulan | AO2: FTIB | AP2: Program Studi S1 Digital Bisnis (FTIB) | AQ2: DMI | AR2: domi@ittelkom-sby.ac.id | AS2: 85230001444 | AT2: Jl. Palem Selatan II MC/163, Waru, Sidoarjo, Jawa Timur 61256 | AW2: =VLOOKUP(B2,Sheet2!A27:I144,9,FALSE) -> Dominggo Bayu Baskara, S.T., M.MT. | AX2: Laki-laki | AY2: =VLOOKUP(B2,Sheet2!A27:C144,2,FALSE) -> Denpasar | AZ2: =VLOOKUP(B2,Sheet2!A27:C144,3,FALSE) -> 33046 | BA2: =DATEDIF(AZ2, TODAY(),"y") -> 35 | BL2: =VLOOKUP(B2,Sheet2!A27:D144,4,FALSE) -> Dosen | BR2: =VLOOKUP(B2,Sheet2!A27:E144,5,FALSE) -> Strategy, Human, Entrepreneurship & Economy (SHEE) | BS2: =VLOOKUP(B2,Sheet2!A27:F144,6,FALSE) -> DBB | BT2: =VLOOKUP(B2,Sheet2!A27:G144,7,FALSE) -> Fakultas Ekonomi dan Bisnis | BU2: =VLOOKUP(B2,Sheet2!A27:H144,8,FALSE) -> dominggobayu@telkomuniversity.ac.id | BV2: =COUNTIFS('Join TPA Dosen'!B:B,Dosen!B23) -> 1 | BW2: =DATEDIF(AM2,DATE(2026,1,1),"y")&" tahun "&DATEDIF(AM2,DATE(2026,1,1),"ym")&" bulan " -> 8 tahun 0 bulan | BX2: =VLOOKUP($B2,Sheet1!$A:$G,2,FALSE) -> ITS | BY2: =VLOOKUP($B2,Sheet1!$A:$G,3,FALSE) -> Teknologi Industri/Teknik Industri | BZ2: =VLOOKUP($B2,Sheet1!$A:$G,4,FALSE) -> ITS | CA2: =VLOOKUP($B2,Sheet1!$A:$G,5,FALSE) -> Manajemen Teknologi | CB2: =VLOOKUP($B2,Sheet1!$A:$G,6,FALSE) -> ITS | CC2: =VLOOKUP($B2,Sheet1!$A:$G,7,FALSE) -> Manajemen Teknologi | CD2: Intergrated and Embedded Systems | CE2: Rekayasa Industri dan Inovasi Bisnis (RIIB)
A3: 1 | B3: Tri Agus Djoko Kuntjoro | C3: Aktif | D3: Teknik Telekomunikasi | E3: 25620001 | F3: 0728016901 | G3: 0460740641130052 | H3: TETAP | I3: Ir. | J3: M.T. | K3: AA.2 | L3: AA | M3: =IF(L3="NJAD","AA",IF(L3="AA","L",IF(L3="L","LK","GB"))) -> L | N3: - | O3: 150 | P3: Konsep Pengembangan Sains dan Teknologi Telekomunikasi dan Pengenalan Teknik Telekomunikasi | Q3: 44144 | R3: =DATEDIF(Q3,TODAY(), "Y") & " Tahun " & DATEDIF(Q3, TODAY(), "YM") & " Bulan" -> 5 Tahun 2 Bulan | S3: Penata Muda Tk. I Golongan III/b | T3: 44256 | U3: =DATEDIF(T3,TODAY(), "Y") & " Tahun " & DATEDIF(T3, TODAY(), "YM") & " Bulan" -> 4 Tahun 10 Bulan | V3: Dosen S1 T. Telekomunikasi | W3: DOSEN | X3: =IF(AND(OR(L3="AA",L3="L"),OR(S3="Penata Muda Tk. I Golongan III/b",S3="Penata Golongan III/c"),DATEDIF(Q3,TODAY(),"m")>=23,ISBLANK(Z3),C3="Aktif"),"Nominasi Serdos","-") -> - | Z3: Punya | AA3: 25104105710770 | AB3: 25-002001-0035 | AC3: 45917 | AH3: S2 | AM3: 43101 | AN3: =DATEDIF(AM3,TODAY(),"y")&" tahun "&DATEDIF(AM3,TODAY(),"ym")&" bulan " -> 8 tahun 0 bulan | AO3: FTEIC | AP3: Program Studi S1 T. Telekomunikasi (FTEIC) | AQ3: TRI | AR3: triagus@ittelkom-sby.ac.id | AS3: 8123222469 | AT3: Jl. Danau sentani Utara H2A No. 31, Sawojajar, Malang | AW3: =VLOOKUP(B3,Sheet2!A2:I119,9,FALSE) -> Ir. Tri Agus Djoko Kuntjoro, M.T. | AX3: Laki-laki | AY3: =VLOOKUP(B3,Sheet2!A2:C119,2,FALSE) -> Malang | AZ3: =VLOOKUP(B3,Sheet2!A2:C119,3,FALSE) -> 22674 | BA3: =DATEDIF(AZ3, TODAY(),"y") -> 63 | BL3: =VLOOKUP(B3,Sheet2!A2:D119,4,FALSE) -> Dosen | BR3: =VLOOKUP(B3,Sheet2!A2:E119,5,FALSE) -> Intelligent Communications and Networks (ICON) | BS3: =VLOOKUP(B3,Sheet2!A2:F119,6,FALSE) -> ORO | BT3: =VLOOKUP(B3,Sheet2!A2:G119,7,FALSE) -> Fakultas Teknik Elektro | BU3: =VLOOKUP(B3,Sheet2!A2:H119,8,FALSE) -> triagusdjokokuntjoro@telkomuniversity.ac.id | BV3: =COUNTIFS('Join TPA Dosen'!B:B,Dosen!B2) -> 1 | BW3: =DATEDIF(AM3,DATE(2026,1,1),"y")&" tahun "&DATEDIF(AM3,DATE(2026,1,1),"ym")&" bulan " -> 8 tahun 0 bulan | BX3: =VLOOKUP($B3,Sheet1!$A:$G,2,FALSE) -> Univ. Brawijaya | BY3: =VLOOKUP($B3,Sheet1!$A:$G,3,FALSE) -> Teknik Elektro | BZ3: =VLOOKUP($B3,Sheet1!$A:$G,4,FALSE) -> ITB | CA3: =VLOOKUP($B3,Sheet1!$A:$G,5,FALSE) -> Elektroteknik | CB3: =VLOOKUP($B3,Sheet1!$A:$G,6,FALSE) -> - | CC3: =VLOOKUP($B3,Sheet1!$A:$G,7,FALSE) -> 0 | CD3: Circular Ecosystem and Sustainable Technology | CE3: ETHES (Electrical Engineering and Advanced Technologies)
A4: 5 | B4: Dimas Adiputra | C4: Aktif | D4: Teknik Elektro | E4: 19930001 | F4: 0725059301 | G4: 2857771672130342 | H4: TETAP | J4: B.Sc., M.Phil., Ph.D. | K4: L.3 | L4: L | M4: =IF(L4="NJAD","AA",IF(L4="AA","L",IF(L4="L","LK","GB"))) -> LK | O4: 300 | P4: Sistem Kendali, Pratikum Sistem Kendali, Elektronika dan Literasi TIK | Q4: 45108 | R4: =DATEDIF(Q4,TODAY(), "Y") & " Tahun " & DATEDIF(Q4, TODAY(), "YM") & " Bulan" -> 2 Tahun 6 Bulan | S4: Penata Golongan III/c | T4: 45261 | U4: =DATEDIF(T4,TODAY(), "Y") & " Tahun " & DATEDIF(T4, TODAY(), "YM") & " Bulan" -> 2 Tahun 1 Bulan | V4: Ketua Kelompok Riset Motion Analysis And Intervention | W4: DOSEN | X4: =IF(AND(OR(L4="AA",L4="L"),OR(S4="Penata Muda Tk. I Golongan III/b",S4="Penata Golongan III/c"),DATEDIF(Q4,TODAY(),"m")>=23,ISBLANK(Z4),C4="Aktif"),"Nominasi Serdos","-") -> - | Z4: Punya | AA4: 22107201901078 | AB4: 22-001001-0182 | AC4: 44783 | AH4: S3 | AM4: 43101 | AN4: =DATEDIF(AM4,TODAY(),"y")&" tahun "&DATEDIF(AM4,TODAY(),"ym")&" bulan " -> 8 tahun 0 bulan | AO4: FTEIC | AP4: Program Studi S1 Teknik Elektro (FTEIC) | AQ4: DMS | AR4: adimas@ittelkom-sby.ac.id | AS4: 81335397727 | AT4: Jl. KH. Hasyim No. 35 RT009/RW002 Siwalanpanji Buduran Sidoarjo | AW4: =VLOOKUP(B4,Sheet2!A6:I123,9,FALSE) -> Dimas Adiputra, B.Sc., M.Phil., Ph.D. | AX4: Laki-laki | AY4: =VLOOKUP(B4,Sheet2!A6:C123,2,FALSE) -> Jakarta | AZ4: =VLOOKUP(B4,Sheet2!A6:C123,3,FALSE) -> 34114 | BA4: =DATEDIF(AZ4, TODAY(),"y") -> 32 | BL4: =VLOOKUP(B4,Sheet2!A6:D123,4,FALSE) -> COE | BR4: =VLOOKUP(B4,Sheet2!A6:E123,5,FALSE) -> Control, Elektronics, and Intelligent Systems (CEIS) | BS4: =VLOOKUP(B4,Sheet2!A6:F123,6,FALSE) -> DIV | BT4: =VLOOKUP(B4,Sheet2!A6:G123,7,FALSE) -> Fakultas Teknik Elektro | BU4: =VLOOKUP(B4,Sheet2!A6:H123,8,FALSE) -> dimasze@telkomuniversity.ac.id | BV4: =COUNTIFS('Join TPA Dosen'!B:B,Dosen!B22) -> 1 | BW4: =DATEDIF(AM4,DATE(2026,1,1),"y")&" tahun "&DATEDIF(AM4,DATE(2026,1,1),"ym")&" bulan " -> 8 tahun 0 bulan | BX4: =VLOOKUP($B4,Sheet1!$A:$G,2,FALSE) -> President Univ | BY4: =VLOOKUP($B4,Sheet1!$A:$G,3,FALSE) -> Teknik Elektro | BZ4: =VLOOKUP($B4,Sheet1!$A:$G,4,FALSE) -> Universiti Teknologi Malaysia | CA4: =VLOOKUP($B4,Sheet1!$A:$G,5,FALSE) -> Teknik Elektro | CB4: =VLOOKUP($B4,Sheet1!$A:$G,6,FALSE) -> Universiti Teknologi Malaysia | CC4: =VLOOKUP($B4,Sheet1!$A:$G,7,FALSE) -> Teknik Elektro | CD4: Motion Technology for Safety, Health, and Wellness | CE4: ETHES (Electrical Engineering and Advanced Technologies)
A5: 47 | B5: Riza Akhsani Setyo Prayoga | C5: Non-Aktif | D5: Digital Bisnis | E5: 20940041 | F5: 0730049402 | H5: PROFESIONAL | J5: S.Kom., M.MT. | K5: AA.2 | L5: AA | M5: =IF(L5="NJAD","AA",IF(L5="AA","L",IF(L5="L","LK","GB"))) -> L | N5: - | O5: 150 | P5: Pemodelan Proses Bisnis, Literasi TIK dan Pemodelan Bisnis | Q5: 44805 | R5: =DATEDIF(Q5,TODAY(), "Y") & " Tahun " & DATEDIF(Q5, TODAY(), "YM") & " Bulan" -> 3 Tahun 4 Bulan | S5: Penata Muda Tk. I Golongan III/b | T5: 44927 | U5: =DATEDIF(T5,TODAY(), "Y") & " Tahun " & DATEDIF(T5, TODAY(), "YM") & " Bulan" -> 3 Tahun 0 Bulan | V5: Dosen S1 Digital Bisnis | W5: DOSEN | X5: =IF(AND(OR(L5="AA",L5="L"),OR(S5="Penata Muda Tk. I Golongan III/b",S5="Penata Golongan III/c"),DATEDIF(Q5,TODAY(),"m")>=23,ISBLANK(Z5),C5="Aktif"),"Nominasi Serdos","-") -> - | AC5: - | AH5: S2 | AM5: 44166 | AN5: =DATEDIF(AM5,TODAY(),"y")&" tahun "&DATEDIF(AM5,TODAY(),"ym")&" bulan " -> 5 tahun 1 bulan | AO5: FTIB | AP5: Program Studi S1 Digital Bisnis (FTIB) | AQ5: RAS | AR5: rizayoga30@ittelkom-sby.ac.id | AS5: 81286153175 | AT5: Jl. Ukel GG 1 No. 26, Kertosari, Babadan, Ponorogo | AW5: =VLOOKUP(B5,Sheet2!A48:I165,9,FALSE) -> Riza Akhsani Setyo Prayoga, S.Kom., M.MT. | AX5: Laki-laki | AY5: =VLOOKUP(B5,Sheet2!A48:C165,2,FALSE) -> Ponorogo | AZ5: =VLOOKUP(B5,Sheet2!A48:C165,3,FALSE) -> 34454 | BA5: =DATEDIF(AZ5, TODAY(),"y") -> 31 | BL5: =VLOOKUP(B5,Sheet2!A48:D165,4,FALSE) -> Dosen | BR5: =VLOOKUP(B5,Sheet2!A48:E165,5,FALSE) -> ICT Business Management (IBM) | BS5: =VLOOKUP(B5,Sheet2!A48:F165,6,FALSE) -> OGA | BT5: =VLOOKUP(B5,Sheet2!A48:G165,7,FALSE) -> Fakultas Ekonomi dan Bisnis | BU5: =VLOOKUP(B5,Sheet2!A48:H165,8,FALSE) -> rizayoga@telkomuniversity.ac.id | BV5: =COUNTIFS('Join TPA Dosen'!B:B,Dosen!B48) -> 1 | BW5: =DATEDIF(AM5,DATE(2026,1,1),"y")&" tahun "&DATEDIF(AM5,DATE(2026,1,1),"ym")&" bulan " -> 5 tahun 1 bulan | BX5: =VLOOKUP($B5,Sheet1!$A:$G,2,FALSE) -> Univ. Brawijaya | BY5: =VLOOKUP($B5,Sheet1!$A:$G,3,FALSE) -> Ilmu Komputer/Sistem Informasi | BZ5: =VLOOKUP($B5,Sheet1!$A:$G,4,FALSE) -> ITS | CA5: =VLOOKUP($B5,Sheet1!$A:$G,5,FALSE) -> Bisnis dan Manajemen Teknologi/Manajemen Teknologi | CB5: =VLOOKUP($B5,Sheet1!$A:$G,6,FALSE) -> - | CC5: =VLOOKUP($B5,Sheet1!$A:$G,7,FALSE) -> 0 | CD5: #N/A | CE5: #N/A
A6: 6 | B6: Isa Hafidz | C6: Aktif | D6: Teknik Elektro | E6: 19920002 | F6: 0728059203 | G6: 5860770671130292 | H6: TETAP | I6: Dr. | J6: S.T., M.T. | K6: L.3 | L6: L | M6: =IF(L6="NJAD","AA",IF(L6="AA","L",IF(L6="L","LK","GB"))) -> LK | O6: 200 | P6: Rangakaian Listrik, Praktikum Rangkaian Listrik, Elektromagnetika dan Matematika Teknik | Q6: 45108 | R6: =DATEDIF(Q6,TODAY(), "Y") & " Tahun " & DATEDIF(Q6, TODAY(), "YM") & " Bulan" -> 2 Tahun 6 Bulan | S6: Penata Golongan III/c | T6: 45658 | U6: =DATEDIF(T6,TODAY(), "Y") & " Tahun " & DATEDIF(T6, TODAY(), "YM") & " Bulan" -> 1 Tahun 0 Bulan | V6: Kaprodi S1 Teknik Elektro | W6: DOSEN | X6: =IF(AND(OR(L6="AA",L6="L"),OR(S6="Penata Muda Tk. I Golongan III/b",S6="Penata Golongan III/c"),DATEDIF(Q6,TODAY(),"m")>=23,ISBLANK(Z6),C6="Aktif"),"Nominasi Serdos","-") -> - | Z6: Punya | AA6: 22107201902507 | AB6: 22-002001-01238 | AC6: 44783 | AH6: S3 | AM6: 43101 | AN6: =DATEDIF(AM6,TODAY(),"y")&" tahun "&DATEDIF(AM6,TODAY(),"ym")&" bulan " -> 8 tahun 0 bulan | AO6: FTEIC | AP6: Program Studi S1 Teknik Elektro (FTEIC) | AQ6: ISA | AR6: isa@ittelkom-sby.ac.id | AS6: 85234852155 | AT6: Jl. Tambak Deres 6/2, Surabaya | AW6: =VLOOKUP(B6,Sheet2!A7:I124,9,FALSE) -> Dr. Isa Hafidz, S.T., M.T. | AX6: Laki-laki | AY6: =VLOOKUP(B6,Sheet2!A7:C124,2,FALSE) -> Surabaya | AZ6: =VLOOKUP(B6,Sheet2!A7:C124,3,FALSE) -> 33752 | BA6: =DATEDIF(AZ6, TODAY(),"y") -> 33 | BL6: =VLOOKUP(B6,Sheet2!A7:D124,4,FALSE) -> Kaprodi | BR6: =VLOOKUP(B6,Sheet2!A7:E124,5,FALSE) -> Control, Elektronics, and Intelligent Systems (CEIS) | BS6: =VLOOKUP(B6,Sheet2!A7:F124,6,FALSE) -> IHF | BT6: =VLOOKUP(B6,Sheet2!A7:G124,7,FALSE) -> Fakultas Teknik Elektro | BU6: =VLOOKUP(B6,Sheet2!A7:H124,8,FALSE) -> isahafidz@telkomuniversity.ac.id | BV6: =COUNTIFS('Join TPA Dosen'!B:B,Dosen!B31) -> 1 | BW6: =DATEDIF(AM6,DATE(2026,1,1),"y")&" tahun "&DATEDIF(AM6,DATE(2026,1,1),"ym")&" bulan " -> 8 tahun 0 bulan | BX6: =VLOOKUP($B6,Sheet1!$A:$G,2,FALSE) -> ITS | BY6: =VLOOKUP($B6,Sheet1!$A:$G,3,FALSE) -> Teknik Elektro | BZ6: =VLOOKUP($B6,Sheet1!$A:$G,4,FALSE) -> ITS | CA6: =VLOOKUP($B6,Sheet1!$A:$G,5,FALSE) -> Teknik Elektro - Teknik Sistem Tenaga | CB6: =VLOOKUP($B6,Sheet1!$A:$G,6,FALSE) -> ITS | CC6: =VLOOKUP($B6,Sheet1!$A:$G,7,FALSE) -> Teknik Elektro | CD6: Circular Ecosystem and Sustainable Technology | CE6: ETHES (Electrical Engineering and Advanced Technologies)
A7: 8 | B7: Farah Zakiyah Rahmanti | C7: Aktif | D7: Teknologi Informasi | E7: 20870006 | F7: 0715128708 | G7: 9547765666230283 | H7: TETAP | J7: S.ST., M.T. | K7: L.2 | L7: L | M7: =IF(L7="NJAD","AA",IF(L7="AA","L",IF(L7="L","LK","GB"))) -> LK | N7: - | O7: 200 | P7: Pemrograman Mobile, Praktikum Algoritma dan Pemrograman, Matermatika Diskrit, Perancangan Basis Data | Q7: 43984 | R7: =DATEDIF(Q7,TODAY(), "Y") & " Tahun " & DATEDIF(Q7, TODAY(), "YM") & " Bulan" -> 5 Tahun 7 Bulan | S7: Penata Golongan III/c | T7: 46023 | U7: =DATEDIF(T7,TODAY(), "Y") & " Tahun " & DATEDIF(T7, TODAY(), "YM") & " Bulan" -> 0 Tahun 0 Bulan | V7: Dosen S1 Teknologi Informasi | W7: DOSEN | X7: =IF(AND(OR(L7="AA",L7="L"),OR(S7="Penata Muda Tk. I Golongan III/b",S7="Penata Golongan III/c"),DATEDIF(Q7,TODAY(),"m")>=23,ISBLANK(Z7),C7="Aktif"),"Nominasi Serdos","-") -> - | Z7: Punya | AA7: 21107201900219 | AB7: 21-002002-0035 | AC7: 44529 | AH7: S2 | AI7: Ya | AJ7: IB | AK7: Tidak | AL7: On Progress S3 IB | AM7: 43101 | AN7: =DATEDIF(AM7,TODAY(),"y")&" tahun "&DATEDIF(AM7,TODAY(),"ym")&" bulan " -> 8 tahun 0 bulan | AO7: FTIB | AP7: Program Studi S1 Teknologi Informasi (FTIB) | AQ7: FRH | AR7: farah.zakiyah@ittelkom-sby.ac.id | AS7: 82257336595 | AT7: Jl. Kutisari Indah Selatan 6/9, Surabaya | AW7: =VLOOKUP(B7,Sheet2!A9:I126,9,FALSE) -> Farah Zakiyah Rahmanti, S.ST., M.T. | AX7: Perempuan | AY7: =VLOOKUP(B7,Sheet2!A9:C126,2,FALSE) -> Surabaya | AZ7: =VLOOKUP(B7,Sheet2!A9:C126,3,FALSE) -> 32126 | BA7: =DATEDIF(AZ7, TODAY(),"y") -> 38 | BL7: =VLOOKUP(B7,Sheet2!A9:D126,4,FALSE) -> Dosen | BR7: =VLOOKUP(B7,Sheet2!A9:E126,5,FALSE) -> Data Science and Intelligent Systems (DSIS) | BS7: =VLOOKUP(B7,Sheet2!A9:F126,6,FALSE) -> FZK | BT7: =VLOOKUP(B7,Sheet2!A9:G126,7,FALSE) -> Fakultas Informatika | BU7: =VLOOKUP(B7,Sheet2!A9:H126,8,FALSE) -> farahzakiyah@telkomuniversity.ac.id | BV7: =COUNTIFS('Join TPA Dosen'!B:B,Dosen!B26) -> 1 | BW7: =DATEDIF(AM7,DATE(2026,1,1),"y")&" tahun "&DATEDIF(AM7,DATE(2026,1,1),"ym")&" bulan " -> 8 tahun 0 bulan | BX7: =VLOOKUP($B7,Sheet1!$A:$G,2,FALSE) -> PENS | BY7: =VLOOKUP($B7,Sheet1!$A:$G,3,FALSE) -> Teknik Informatika | BZ7: =VLOOKUP($B7,Sheet1!$A:$G,4,FALSE) -> ITS | CA7: =VLOOKUP($B7,Sheet1!$A:$G,5,FALSE) -> Teknik Elektro | CB7: =VLOOKUP($B7,Sheet1!$A:$G,6,FALSE) -> ITS | CC7: =VLOOKUP($B7,Sheet1!$A:$G,7,FALSE) -> Teknik Elektro | CD7: Intergrated and Embedded Systems | CE7: Smart Computing Technology (SCOUT)
A8: 9 | B8: Helmy Widyantara | C8: Aktif | D8: Teknologi Informasi | E8: 19790001 | F8: 0717017902 | G8: 9449757658130112 | H8: TETAP | I8: Dr. | J8: S.Kom., M.Eng. | K8: LK.3 | L8: LK | M8: =IF(L8="NJAD","AA",IF(L8="AA","L",IF(L8="L","LK","GB"))) -> GB | N8: - | O8: 400 | P8: Otomasi Sistem | Q8: 45200 | R8: =DATEDIF(Q8,TODAY(), "Y") & " Tahun " & DATEDIF(Q8, TODAY(), "YM") & " Bulan" -> 2 Tahun 3 Bulan | S8: Penata Tk. I Golongan III/d | T8: 46023 | U8: =DATEDIF(T8,TODAY(), "Y") & " Tahun " & DATEDIF(T8, TODAY(), "YM") & " Bulan" -> 0 Tahun 0 Bulan | V8: Ketua Kelompok Riset Integrated And Embedded System | W8: DOSEN | X8: =IF(AND(OR(L8="AA",L8="L"),OR(S8="Penata Muda Tk. I Golongan III/b",S8="Penata Golongan III/c"),DATEDIF(Q8,TODAY(),"m")>=23,ISBLANK(Z8),C8="Aktif"),"Nominasi Serdos","-") -> - | Z8: Punya | AA8: 15107500409985 | AB8: 15 00201 0454 | AC8: 42357 | AH8: S3 | AM8: 43101 | AN8: =DATEDIF(AM8,TODAY(),"y")&" tahun "&DATEDIF(AM8,TODAY(),"ym")&" bulan " -> 8 tahun 0 bulan | AO8: FTIB | AP8: Program Studi S1 Teknologi Informasi (FTIB) | AQ8: HEL | AR8: helmywid@ittelkom-sby.ac.id | AS8: 8123182116 | AT8: Semampir Tengah IIA/26 Surabaya | AW8: =VLOOKUP(B8,Sheet2!A10:I127,9,FALSE) -> Dr. Helmy Widyantara, S.Kom., M.Eng. | AX8: Laki-laki | AY8: =VLOOKUP(B8,Sheet2!A10:C127,2,FALSE) -> Ngawi | AZ8: =VLOOKUP(B8,Sheet2!A10:C127,3,FALSE) -> 28872 | BA8: =DATEDIF(AZ8, TODAY(),"y") -> 47 | BL8: =VLOOKUP(B8,Sheet2!A10:D127,4,FALSE) -> COE | BR8: =VLOOKUP(B8,Sheet2!A10:E127,5,FALSE) -> Communication and Information Technology Infrastructure (CITI) | BS8: =VLOOKUP(B8,Sheet2!A10:F127,6,FALSE) -> CAP | BT8: =VLOOKUP(B8,Sheet2!A10:G127,7,FALSE) -> Fakultas Informatika | BU8: =VLOOKUP(B8,Sheet2!A10:H127,8,FALSE) -> helmywidyantara@telkomuniversity.ac.id | BV8: =COUNTIFS('Join TPA Dosen'!B:B,Dosen!B30) -> 1 | BW8: =DATEDIF(AM8,DATE(2026,1,1),"y")&" tahun "&DATEDIF(AM8,DATE(2026,1,1),"ym")&" bulan " -> 8 tahun 0 bulan | BX8: =VLOOKUP($B8,Sheet1!$A:$G,2,FALSE) -> STIKOM | BY8: =VLOOKUP($B8,Sheet1!$A:$G,3,FALSE) -> Teknik Komputer | BZ8: =VLOOKUP($B8,Sheet1!$A:$G,4,FALSE) -> UGM | CA8: =VLOOKUP($B8,Sheet1!$A:$G,5,FALSE) -> Teknik Elektro | CB8: =VLOOKUP($B8,Sheet1!$A:$G,6,FALSE) -> ITS | CC8: =VLOOKUP($B8,Sheet1!$A:$G,7,FALSE) -> Teknik Elektro | CD8: Intergrated and Embedded Systems | CE8: Smart Computing Technology (SCOUT)
A9: 11 | B9: Fidi Wincoko Putro | C9: Aktif | D9: Rekayasa Perangkat Lunak | E9: 19870004 | F9: 0730058702 | G9: 1862765666130262 | H9: TETAP | J9: S.ST., M.Kom. | K9: L.2 | L9: L | M9: =IF(L9="NJAD","AA",IF(L9="AA","L",IF(L9="L","LK","GB"))) -> LK | N9: - | O9: 200 | P9: Software Engineering | Q9: 45901 | R9: =DATEDIF(Q9,TODAY(), "Y") & " Tahun " & DATEDIF(Q9, TODAY(), "YM") & " Bulan" -> 0 Tahun 4 Bulan | S9: Penata Golongan III/c | T9: 46023 | U9: =DATEDIF(T9,TODAY(), "Y") & " Tahun " & DATEDIF(T9, TODAY(), "YM") & " Bulan" -> 0 Tahun 0 Bulan | V9: Kaprodi S1 RPL | W9: DOSEN | X9: =IF(AND(OR(L9="AA",L9="L"),OR(S9="Penata Muda Tk. I Golongan III/b",S9="Penata Golongan III/c"),DATEDIF(Q9,TODAY(),"m")>=23,ISBLANK(Z9),C9="Aktif"),"Nominasi Serdos","-") -> - | Z9: Punya | AA9: 25104105710334 | AB9: 25-001026-0131 | AC9: 45917 | AH9: S2 | AI9: Ya | AJ9: TB | AK9: Ya | AM9: 43101 | AN9: =DATEDIF(AM9,TODAY(),"y")&" tahun "&DATEDIF(AM9,TODAY(),"ym")&" bulan " -> 8 tahun 0 bulan | AO9: FTIB | AP9: Program Studi S1 RPL (FTIB) | AQ9: FWP | AR9: fidiwputro@ittelkom-sby.ac.id | AS9: 82143161793 | AT9: Jl. Cempaka 42, Kel Bangunsari, Kec Mejayan, Kab Madiun, Jawa Timur | AW9: =VLOOKUP(B9,Sheet2!A12:I129,9,FALSE) -> Fidi Wincoko Putro, S.ST., M.Kom. | AX9: Laki-laki | AY9: =VLOOKUP(B9,Sheet2!A12:C129,2,FALSE) -> Madiun | AZ9: =VLOOKUP(B9,Sheet2!A12:C129,3,FALSE) -> 31927 | BA9: =DATEDIF(AZ9, TODAY(),"y") -> 38 | BL9: Dosen | BR9: =VLOOKUP(B9,Sheet2!A12:E129,5,FALSE) -> Software Engineering and Algorithm (SEAL) | BS9: =VLOOKUP(B9,Sheet2!A12:F129,6,FALSE) -> FWP | BT9: =VLOOKUP(B9,Sheet2!A12:G129,7,FALSE) -> Fakultas Informatika | BU9: =VLOOKUP(B9,Sheet2!A12:H129,8,FALSE) -> fidiwputro@telkomuniversity.ac.id | BV9: =COUNTIFS('Join TPA Dosen'!B:B,Dosen!B12) -> 1 | BW9: =DATEDIF(AM9,DATE(2026,1,1),"y")&" tahun "&DATEDIF(AM9,DATE(2026,1,1),"ym")&" bulan " -> 8 tahun 0 bulan | BX9: =VLOOKUP($B9,Sheet1!$A:$G,2,FALSE) -> PENS | BY9: =VLOOKUP($B9,Sheet1!$A:$G,3,FALSE) -> Teknik Informatika | BZ9: =VLOOKUP($B9,Sheet1!$A:$G,4,FALSE) -> ITS | CA9: =VLOOKUP($B9,Sheet1!$A:$G,5,FALSE) -> Teknik Informatika | CB9: =VLOOKUP($B9,Sheet1!$A:$G,6,FALSE) -> - | CC9: =VLOOKUP($B9,Sheet1!$A:$G,7,FALSE) -> 0 | CD9: Motion Technology for Safety, Health, and Wellness | CE9: Smart Computing Technology (SCOUT)
A10: 101 | B10: Adisya Resti Rahmadanti | C10: Non-Aktif | D10: Digital Bisnis | E10: 23990018 | F10: 0727019901 | G10: 0459777678230052 | H10: PROFESIONAL | J10: S.M., M.A.B. | K10: NJAD.2 | L10: NJAD | M10: =IF(L10="NJAD","AA",IF(L10="AA","L",IF(L10="L","LK","GB"))) -> AA | N10: - | O10: 0 | Q10: 45170 | R10: =DATEDIF(Q10,TODAY(), "Y") & " Tahun " & DATEDIF(Q10, TODAY(), "YM") & " Bulan" -> 2 Tahun 4 Bulan | S10: - | T10: - | U10: =DATEDIF(T10,TODAY(), "Y") & " Tahun " & DATEDIF(T10, TODAY(), "YM") & " Bulan" -> #VALUE! | V10: Dosen S1 Digital Bisnis | W10: DOSEN | X10: =IF(AND(OR(L10="AA",L10="L"),OR(S10="Penata Muda Tk. I Golongan III/b",S10="Penata Golongan III/c"),DATEDIF(Q10,TODAY(),"m")>=23,ISBLANK(Z10),C10="Aktif"),"Nominasi Serdos","-") -> - | AC10: - | AH10: S2 | AM10: 45170 | AN10: =DATEDIF(AM10,TODAY(),"y")&" tahun "&DATEDIF(AM10,TODAY(),"ym")&" bulan " -> 2 tahun 4 bulan | AO10: FTIB | AP10: Program Studi S1 Digital Bisnis (FTIB) | AQ10: DIS | AR10: adisya@ittelkom-sby.ac.id | AS10: 81529137179 | AT10: Jl. Gedong Kuning 40A, Jogjakarta, 5517 | AW10: =VLOOKUP(B10,Sheet2!A102:I219,9,FALSE) -> Adisya Resti Rahmadanti, S.M., M.A.B. | AX10: Perempuan | AY10: =VLOOKUP(B10,Sheet2!A102:C219,2,FALSE) -> Bandung | AZ10: =VLOOKUP(B10,Sheet2!A102:C219,3,FALSE) -> 36187 | BA10: =DATEDIF(AZ10, TODAY(),"y") -> 26 | BL10: =VLOOKUP(B10,Sheet2!A102:D219,4,FALSE) -> Dosen | BR10: =VLOOKUP(B10,Sheet2!A102:E219,5,FALSE) -> Strategy, Human, Entrepreneurship & Economy (SHEE) | BS10: =VLOOKUP(B10,Sheet2!A102:F219,6,FALSE) -> NTI | BT10: =VLOOKUP(B10,Sheet2!A102:G219,7,FALSE) -> Fakultas Ekonomi dan Bisnis | BU10: =VLOOKUP(B10,Sheet2!A102:H219,8,FALSE) -> adisyaresti@telkomuniversity.ac.id | BV10: =COUNTIFS('Join TPA Dosen'!B:B,Dosen!B102) -> 1 | BW10: =DATEDIF(AM10,DATE(2026,1,1),"y")&" tahun "&DATEDIF(AM10,DATE(2026,1,1),"ym")&" bulan " -> 2 tahun 4 bulan | BX10: =VLOOKUP($B10,Sheet1!$A:$G,2,FALSE) -> ITS | BY10: =VLOOKUP($B10,Sheet1!$A:$G,3,FALSE) -> Manajemen Bisnis | BZ10: =VLOOKUP($B10,Sheet1!$A:$G,4,FALSE) -> ITB | CA10: =VLOOKUP($B10,Sheet1!$A:$G,5,FALSE) -> Administrasi Bisnis | CB10: =VLOOKUP($B10,Sheet1!$A:$G,6,FALSE) -> - | CC10: =VLOOKUP($B10,Sheet1!$A:$G,7,FALSE) -> 0 | CD10: #N/A | CE10: #N/A | CF10: 45839
A11: 12 | B11: Philip Tobianto Daely | C11: Aktif | D11: Teknologi Informasi | E11: 19940002 | F11: 0728069401 | G11: 5960772673130242 | H11: TETAP | J11: S.T., M.Eng., Ph.D. | K11: L.3 | L11: L | M11: =IF(L11="NJAD","AA",IF(L11="AA","L",IF(L11="L","LK","GB"))) -> LK | N11: - | O11: 200 | Q11: 45597 | R11: =DATEDIF(Q11,TODAY(), "Y") & " Tahun " & DATEDIF(Q11, TODAY(), "YM") & " Bulan" -> 1 Tahun 2 Bulan | S11: Penata Golongan III/c | T11: 45717 | U11: =DATEDIF(T11,TODAY(), "Y") & " Tahun " & DATEDIF(T11, TODAY(), "YM") & " Bulan" -> 0 Tahun 10 Bulan | V11: Dosen S1 Teknologi Informasi | W11: DOSEN | X11: =IF(AND(OR(L11="AA",L11="L"),OR(S11="Penata Muda Tk. I Golongan III/b",S11="Penata Golongan III/c"),DATEDIF(Q11,TODAY(),"m")>=23,ISBLANK(Z11),C11="Aktif"),"Nominasi Serdos","-") -> - | AC11: - | AH11: S3 | AM11: 43101 | AN11: =DATEDIF(AM11,TODAY(),"y")&" tahun "&DATEDIF(AM11,TODAY(),"ym")&" bulan " -> 8 tahun 0 bulan | AO11: FTIB | AP11: Program Studi S1 Teknologi Informasi (FTIB) | AQ11: PTD | AR11: philip.daely@ittelkom-sby.ac.id | AS11: 81219685567 | AT11: Jl. Teratai no. 20, Yogyakarta, DIY | AW11: =VLOOKUP(B11,Sheet2!A13:I130,9,FALSE) -> Philip Tobianto Daely, S.T., M.Eng., Ph.D. | AX11: Laki-laki | AY11: =VLOOKUP(B11,Sheet2!A13:C130,2,FALSE) -> Medan | AZ11: =VLOOKUP(B11,Sheet2!A13:C130,3,FALSE) -> 34513 | BA11: =DATEDIF(AZ11, TODAY(),"y") -> 31 | BL11: Koordinator KK | BR11: =VLOOKUP(B11,Sheet2!A13:E130,5,FALSE) -> Communication and Information Technology Infrastructure (CITI) | BS11: =VLOOKUP(B11,Sheet2!A13:F130,6,FALSE) -> PHI | BT11: =VLOOKUP(B11,Sheet2!A13:G130,7,FALSE) -> Fakultas Informatika | BU11: =VLOOKUP(B11,Sheet2!A13:H130,8,FALSE) -> ptdaely@telkomuniversity.ac.id | BV11: =COUNTIFS('Join TPA Dosen'!B:B,Dosen!B13) -> 1 | BW11: =DATEDIF(AM11,DATE(2026,1,1),"y")&" tahun "&DATEDIF(AM11,DATE(2026,1,1),"ym")&" bulan " -> 8 tahun 0 bulan | BX11: =VLOOKUP($B11,Sheet1!$A:$G,2,FALSE) -> Tel-U | BY11: =VLOOKUP($B11,Sheet1!$A:$G,3,FALSE) -> Teknik Elektro | BZ11: =VLOOKUP($B11,Sheet1!$A:$G,4,FALSE) -> Kumoh National Institute of Technology | CA11: =VLOOKUP($B11,Sheet1!$A:$G,5,FALSE) -> IT Convergence Engineering | CB11: =VLOOKUP($B11,Sheet1!$A:$G,6,FALSE) -> Kumoh National Institute of Technology | CC11: =VLOOKUP($B11,Sheet1!$A:$G,7,FALSE) -> IT Convergence Engineering | CD11: Intergrated and Embedded Systems | CE11: Smart Computing Technology (SCOUT)
A12: 115 | B12: Rudi Harianto | C12: Non-Aktif | D12: Digital Bisnis | E12: 24870001 | F12: 0701108702 | H12: PROFESIONAL | J12: S.E., M.A. | K12: AA.2 | L12: AA | M12: =IF(L12="NJAD","AA",IF(L12="AA","L",IF(L12="L","LK","GB"))) -> L | N12: - | O12: 150 | P12: Ekonomi, Akuntansi Pengantar 2, Akuntansi Biaya, Analisa Laporan Keuangan | Q12: 43543 | R12: =DATEDIF(Q12,TODAY(), "Y") & " Tahun " & DATEDIF(Q12, TODAY(), "YM") & " Bulan" -> 6 Tahun 10 Bulan | S12: Penata Muda Tk. I Golongan III/b | T12: 43770 | U12: =DATEDIF(T12,TODAY(), "Y") & " Tahun " & DATEDIF(T12, TODAY(), "YM") & " Bulan" -> 6 Tahun 2 Bulan | V12: Dosen S1 Digital Bisnis | W12: DOSEN | X12: =IF(AND(OR(L12="AA",L12="L"),OR(S12="Penata Muda Tk. I Golongan III/b",S12="Penata Golongan III/c"),DATEDIF(Q12,TODAY(),"m")>=23,ISBLANK(Z12),C12="Aktif"),"Nominasi Serdos","-") -> - | AC12: - | AH12: S2 | AI12: Ya | AJ12: IB | AK12: Tidak | AL12: On Progress S3 IB | AM12: 45505 | AN12: =DATEDIF(AM12,TODAY(),"y")&" tahun "&DATEDIF(AM12,TODAY(),"ym")&" bulan " -> 1 tahun 5 bulan | AO12: FTIB | AP12: Program Studi S1 Digital Bisnis (FTIB) | AS12: 82123556785 | AT12: Sidokapasan 1/54 SBY RT 001 RW 001, Kel. Sidodadi, Kec. Simokerto, Kota Surabaya, Jawa Timur | AW12: =VLOOKUP(B12,Sheet2!A116:I233,9,FALSE) -> Rudi Harianto, S.E., M.A. | AX12: Laki-laki | AY12: =VLOOKUP(B12,Sheet2!A116:C233,2,FALSE) -> Malang | AZ12: =VLOOKUP(B12,Sheet2!A116:C233,3,FALSE) -> 33004 | BA12: =DATEDIF(AZ12, TODAY(),"y") -> 35 | BL12: =VLOOKUP(B12,Sheet2!A116:D233,4,FALSE) -> Dosen | BS12: =VLOOKUP(B12,Sheet2!A116:F233,6,FALSE) -> RHO | BT12: =VLOOKUP(B12,Sheet2!A116:G233,7,FALSE) -> Fakultas Ekonomi dan Bisnis | BU12: =VLOOKUP(B12,Sheet2!A116:H233,8,FALSE) -> rudiharianto@telkomuniversity.ac.id | BV12: =COUNTIFS('Join TPA Dosen'!B:B,Dosen!B116) -> 1 | BW12: =DATEDIF(AM12,DATE(2026,1,1),"y")&" tahun "&DATEDIF(AM12,DATE(2026,1,1),"ym")&" bulan " -> 1 tahun 5 bulan | BX12: =VLOOKUP($B12,Sheet1!$A:$G,2,FALSE) -> 0 | BY12: =VLOOKUP($B12,Sheet1!$A:$G,3,FALSE) -> 0 | BZ12: =VLOOKUP($B12,Sheet1!$A:$G,4,FALSE) -> 0 | CA12: =VLOOKUP($B12,Sheet1!$A:$G,5,FALSE) -> 0 | CB12: =VLOOKUP($B12,Sheet1!$A:$G,6,FALSE) -> 0 | CC12: =VLOOKUP($B12,Sheet1!$A:$G,7,FALSE) -> 0 | CD12: Motion Technology for Safety, Health, and Wellness | CE12: Rekayasa Industri dan Inovasi Bisnis (RIIB) | CF12: 45689
A13: 13 | B13: Anifatul Faricha | C13: Aktif | D13: Teknik Elektro | E13: 19920003 | F13: 0704069202 | G13: 0936770671230312 | H13: TETAP | J13: S.T., M.Sc., Ph.D | K13: AA.3 | L13: AA | M13: =IF(L13="NJAD","AA",IF(L13="AA","L",IF(L13="L","LK","GB"))) -> L | N13: - | O13: 150 | P13: Praktikum Fisika 1A, Kalkulus 1A, Kalkulus 2A, Praktikum ALPRO (Alogaritma dan Pemrogaman Dasar) | Q13: 43789 | R13: =DATEDIF(Q13,TODAY(), "Y") & " Tahun " & DATEDIF(Q13, TODAY(), "YM") & " Bulan" -> 6 Tahun 1 Bulan | S13: Penata Muda Tk. I Golongan III/b | T13: 43891 | U13: =DATEDIF(T13,TODAY(), "Y") & " Tahun " & DATEDIF(T13, TODAY(), "YM") & " Bulan" -> 5 Tahun 10 Bulan | V13: Dosen S1 Teknik Elektro | W13: DOSEN | X13: =IF(AND(OR(L13="AA",L13="L"),OR(S13="Penata Muda Tk. I Golongan III/b",S13="Penata Golongan III/c"),DATEDIF(Q13,TODAY(),"m")>=23,ISBLANK(Z13),C13="Aktif"),"Nominasi Serdos","-") -> - | Z13: Punya | AA13: 25104105707981 | AB13: 25-002001-0078 | AC13: 45917 | AH13: S3 | AM13: 43101 | AN13: =DATEDIF(AM13,TODAY(),"y")&" tahun "&DATEDIF(AM13,TODAY(),"ym")&" bulan " -> 8 tahun 0 bulan | AO13: FTEIC | AP13: Program Studi S1 Teknik Elektro (FTEIC) | AQ13: IFA | AR13: faricha@ittelkom-sby.ac.id | AS13: 81360805290 | AT13: Sekaran RT/RW:005/001, Kec. Sekaran, Lamongan | AW13: =VLOOKUP(B13,Sheet2!A14:I131,9,FALSE) -> Anifatul Faricha, S.T., M.Sc., Ph.D | AX13: Perempuan | AY13: =VLOOKUP(B13,Sheet2!A14:C131,2,FALSE) -> Lamongan | AZ13: =VLOOKUP(B13,Sheet2!A14:C131,3,FALSE) -> 33759 | BA13: =DATEDIF(AZ13, TODAY(),"y") -> 33 | BL13: Koordinator KK | BR13: =VLOOKUP(B13,Sheet2!A14:E131,5,FALSE) -> Sustainable Material, Instrumentation, Energy, and Computation (SMART) | BS13: =VLOOKUP(B13,Sheet2!A14:F131,6,FALSE) -> EVE | BT13: =VLOOKUP(B13,Sheet2!A14:G131,7,FALSE) -> Fakultas Teknik Elektro | BU13: =VLOOKUP(B13,Sheet2!A14:H131,8,FALSE) -> faricha@telkomuniversity.ac.id | BV13: =COUNTIFS('Join TPA Dosen'!B:B,Dosen!B14) -> 1 | BW13: =DATEDIF(AM13,DATE(2026,1,1),"y")&" tahun "&DATEDIF(AM13,DATE(2026,1,1),"ym")&" bulan " -> 8 tahun 0 bulan | BX13: =VLOOKUP($B13,Sheet1!$A:$G,2,FALSE) -> ITS | BY13: =VLOOKUP($B13,Sheet1!$A:$G,3,FALSE) -> Teknik Elektro | BZ13: =VLOOKUP($B13,Sheet1!$A:$G,4,FALSE) -> National Taiwan Univ of Science and Tech | CA13: =VLOOKUP($B13,Sheet1!$A:$G,5,FALSE) -> Graduate Institute of Automation and Control | CB13: =VLOOKUP($B13,Sheet1!$A:$G,6,FALSE) -> Tokyo Institute of Technology | CC13: =VLOOKUP($B13,Sheet1!$A:$G,7,FALSE) -> Information and Communications Engineering | CD13: Motion Technology for Safety, Health, and Wellness | CE13: ETHES (Electrical Engineering and Advanced Technologies)
A14: 15 | B14: Anfazul Faridatul Azizah | C14: Aktif | D14: Sistem Informasi | E14: 19900002 | F14: 0715039004 | G14: 8647768669230332 | H14: TETAP | J14: S.Kom., M.Kom. | K14: AA.2 | L14: AA | M14: =IF(L14="NJAD","AA",IF(L14="AA","L",IF(L14="L","LK","GB"))) -> L | N14: - | O14: 150 | P14: Literasi TIK dan Pemodelan Proses Bisnis | Q14: 44117 | R14: =DATEDIF(Q14,TODAY(), "Y") & " Tahun " & DATEDIF(Q14, TODAY(), "YM") & " Bulan" -> 5 Tahun 3 Bulan | S14: Penata Muda Tk. I Golongan III/b | T14: 44440 | U14: =DATEDIF(T14,TODAY(), "Y") & " Tahun " & DATEDIF(T14, TODAY(), "YM") & " Bulan" -> 4 Tahun 4 Bulan | V14: Dosen S1 Sistem Informasi | W14: DOSEN | X14: =IF(AND(OR(L14="AA",L14="L"),OR(S14="Penata Muda Tk. I Golongan III/b",S14="Penata Golongan III/c"),DATEDIF(Q14,TODAY(),"m")>=23,ISBLANK(Z14),C14="Aktif"),"Nominasi Serdos","-") -> Nominasi Serdos | AC14: - | AH14: S2 | AI14: Ya | AJ14: IB | AK14: Tidak | AL14: On Progress S3 IB | AM14: 43101 | AN14: =DATEDIF(AM14,TODAY(),"y")&" tahun "&DATEDIF(AM14,TODAY(),"ym")&" bulan " -> 8 tahun 0 bulan | AO14: FTIB | AP14: Program Studi S1 Sistem Informasi (FTIB) | AQ14: AFA | AR14: anfazul.azizah@ittelkom-sby.ac.id | AS14: 82232504468 | AT14: Jalan Ketintang 3 / 7, Surabaya | AW14: =VLOOKUP(B14,Sheet2!A16:I133,9,FALSE) -> Anfazul Faridatul Azizah, S.Kom., M.Kom. | AX14: Perempuan | AY14: =VLOOKUP(B14,Sheet2!A16:C133,2,FALSE) -> Surabaya | AZ14: =VLOOKUP(B14,Sheet2!A16:C133,3,FALSE) -> 32947 | BA14: =DATEDIF(AZ14, TODAY(),"y") -> 35 | BL14: =VLOOKUP(B14,Sheet2!A16:D133,4,FALSE) -> Dosen | BR14: =VLOOKUP(B14,Sheet2!A16:E133,5,FALSE) -> Cybernetics | BS14: =VLOOKUP(B14,Sheet2!A16:F133,6,FALSE) -> AFC | BT14: =VLOOKUP(B14,Sheet2!A16:G133,7,FALSE) -> Fakultas Rekayasa Industri | BU14: =VLOOKUP(B14,Sheet2!A16:H133,8,FALSE) -> anfazulazizah@telkomuniversity.ac.id | BV14: =COUNTIFS('Join TPA Dosen'!B:B,Dosen!B16) -> 1 | BW14: =DATEDIF(AM14,DATE(2026,1,1),"y")&" tahun "&DATEDIF(AM14,DATE(2026,1,1),"ym")&" bulan " -> 8 tahun 0 bulan | BX14: =VLOOKUP($B14,Sheet1!$A:$G,2,FALSE) -> ITS | BY14: =VLOOKUP($B14,Sheet1!$A:$G,3,FALSE) -> Sistem Informasi | BZ14: =VLOOKUP($B14,Sheet1!$A:$G,4,FALSE) -> ITS | CA14: =VLOOKUP($B14,Sheet1!$A:$G,5,FALSE) -> Teknik Informatika - Sistem Informasi | CB14: =VLOOKUP($B14,Sheet1!$A:$G,6,FALSE) -> ITS | CC14: =VLOOKUP($B14,Sheet1!$A:$G,7,FALSE) -> Ilmu Komputer | CE14: Rekayasa Industri dan Inovasi Bisnis (RIIB)
A15: 17 | B15: Mohamad Yani | C15: Aktif | D15: Teknik Komputer | E15: 17910092 | F15: 0701129102 | G15: 0444769670130282 | H15: PROFESIONAL | J15: S.ST., M.Phil., Ph.D. | K15: NJAD.3 | L15: NJAD | M15: =IF(L15="NJAD","AA",IF(L15="AA","L",IF(L15="L","LK","GB"))) -> AA | N15: - | O15: 0 | Q15: 43101 | R15: =DATEDIF(Q15,TODAY(), "Y") & " Tahun " & DATEDIF(Q15, TODAY(), "YM") & " Bulan" -> 8 Tahun 0 Bulan | S15: - | T15: - | U15: =DATEDIF(T15,TODAY(), "Y") & " Tahun " & DATEDIF(T15, TODAY(), "YM") & " Bulan" -> #VALUE! | V15: Dosen S1 T. Komputer | W15: DOSEN | X15: =IF(AND(OR(L15="AA",L15="L"),OR(S15="Penata Muda Tk. I Golongan III/b",S15="Penata Golongan III/c"),DATEDIF(Q15,TODAY(),"m")>=23,ISBLANK(Z15),C15="Aktif"),"Nominasi Serdos","-") -> - | AC15: - | AH15: S3 | AM15: 43101 | AN15: =DATEDIF(AM15,TODAY(),"y")&" tahun "&DATEDIF(AM15,TODAY(),"ym")&" bulan " -> 8 tahun 0 bulan | AO15: FTEIC | AP15: Program Studi S1 T. Komputer (FTEIC) | AQ15: MAI | AR15: mai@ittelkom-sby.ac.id | AS15: 81226595253 | AT15: MEDOKAN AYU MA-I/J-35, SURABAYA | AW15: =VLOOKUP(B15,Sheet2!A18:I135,9,FALSE) -> Mohamad Yani, S.ST., M.Phil., Ph.D. | AX15: Laki-laki | AY15: =VLOOKUP(B15,Sheet2!A18:C135,2,FALSE) -> Surabaya | AZ15: =VLOOKUP(B15,Sheet2!A18:C135,3,FALSE) -> 33250 | BA15: =DATEDIF(AZ15, TODAY(),"y") -> 35 | BL15: =VLOOKUP(B15,Sheet2!A18:D135,4,FALSE) -> Dosen | BR15: =VLOOKUP(B15,Sheet2!A18:E135,5,FALSE) -> Control, Elektronics, and Intelligent Systems (CEIS) | BS15: =VLOOKUP(B15,Sheet2!A18:F135,6,FALSE) -> MIX | BT15: =VLOOKUP(B15,Sheet2!A18:G135,7,FALSE) -> Fakultas Teknik Elektro | BU15: =VLOOKUP(B15,Sheet2!A18:H135,8,FALSE) -> mohamadyani@telkomuniversity.ac.id | BV15: =COUNTIFS('Join TPA Dosen'!B:B,Dosen!B18) -> 1 | BW15: =DATEDIF(AM15,DATE(2026,1,1),"y")&" tahun "&DATEDIF(AM15,DATE(2026,1,1),"ym")&" bulan " -> 8 tahun 0 bulan | BX15: =VLOOKUP($B15,Sheet1!$A:$G,2,FALSE) -> PENS | BY15: =VLOOKUP($B15,Sheet1!$A:$G,3,FALSE) -> Mechatronics Engineering | BZ15: =VLOOKUP($B15,Sheet1!$A:$G,4,FALSE) -> Universiti Teknologi Malaysia | CA15: =VLOOKUP($B15,Sheet1!$A:$G,5,FALSE) -> Teknik Elektro | CB15: =VLOOKUP($B15,Sheet1!$A:$G,6,FALSE) -> Tokyo Metropolitan University | CC15: =VLOOKUP($B15,Sheet1!$A:$G,7,FALSE) -> Mechanical Systems Engineering | CD15: Intergrated and Embedded Systems | CE15: ETHES (Electrical Engineering and Advanced Technologies)
A16: 121 | B16: Egi Gumala Sari | C16: Non-Aktif | D16: Digital Bisnis | E16: 25980005 | H16: PROFESIONAL | J16: S.E., M.Ak. | K16: NJAD.2 | L16: NJAD | M16: =IF(L16="NJAD","AA",IF(L16="AA","L",IF(L16="L","LK","GB"))) -> AA | N16: - | O16: 0 | Q16: 45689 | R16: =DATEDIF(Q16,TODAY(), "Y") & " Tahun " & DATEDIF(Q16, TODAY(), "YM") & " Bulan" -> 0 Tahun 11 Bulan | S16: - | T16: - | U16: =DATEDIF(T16,TODAY(), "Y") & " Tahun " & DATEDIF(T16, TODAY(), "YM") & " Bulan" -> #VALUE! | V16: Dosen S1 Digital Bisnis | W16: DOSEN | X16: =IF(AND(OR(L16="AA",L16="L"),OR(S16="Penata Muda Tk. I Golongan III/b",S16="Penata Golongan III/c"),DATEDIF(Q16,TODAY(),"m")>=23,ISBLANK(Z16),C16="Aktif"),"Nominasi Serdos","-") -> - | AH16: S2 | AM16: 45689 | AN16: =DATEDIF(AM16,TODAY(),"y")&" tahun "&DATEDIF(AM16,TODAY(),"ym")&" bulan " -> 0 tahun 11 bulan | AO16: FTIB | AP16: Program Studi S1 Digital Bisnis (FTIB) | AQ16: EGS | AR16: riset.egigumalasari@gmail.com | AS16: 82123510747 | AT16: jl perintis kemardekaan no 154 kel padang matinggi | AW16: Egi Gumala Sari, S.E., M.Ak. | AX16: Perempuan | AY16: Gantung Ciri | AZ16: 32440 | BA16: =DATEDIF(AZ16, TODAY(),"y") -> 37 | BL16: Dosen | BR16: =VLOOKUP(B16,Sheet2!A122:E239,5,FALSE) -> #N/A | BS16: EGS | BT16: Fakultas Ekonomi dan Bisnis | BU16: egigumalasari@telkomuniversity.ac.id | BV16: =COUNTIFS('Join TPA Dosen'!B:B,Dosen!B122) -> 1 | BW16: =DATEDIF(AM16,DATE(2026,1,1),"y")&" tahun "&DATEDIF(AM16,DATE(2026,1,1),"ym")&" bulan " -> 0 tahun 11 bulan | BX16: =VLOOKUP($B16,Sheet1!$A:$G,2,FALSE) -> #N/A | BY16: =VLOOKUP($B16,Sheet1!$A:$G,3,FALSE) -> #N/A | BZ16: =VLOOKUP($B16,Sheet1!$A:$G,4,FALSE) -> #N/A | CA16: =VLOOKUP($B16,Sheet1!$A:$G,5,FALSE) -> #N/A | CB16: =VLOOKUP($B16,Sheet1!$A:$G,6,FALSE) -> #N/A | CC16: =VLOOKUP($B16,Sheet1!$A:$G,7,FALSE) -> #N/A | CD16: 0 | CE16: Rekayasa Industri dan Inovasi Bisnis (RIIB) | CF16: 45870
A17: 18 | B17: Muhsin | C17: Aktif | D17: Teknik Telekomunikasi | E17: 19940001 | F17: 0703049401 | G17: 9735772673130262 | H17: TETAP | J17: S.T., M.T., Ph. D. | K17: L.3 | L17: L | M17: =IF(L17="NJAD","AA",IF(L17="AA","L",IF(L17="L","LK","GB"))) -> LK | O17: 200 | P17: Elektromagnetika, Sinyal dan Sistem, Pengelolahan Sinyal Digital dan Ekonomi Teknik | Q17: 45108 | R17: =DATEDIF(Q17,TODAY(), "Y") & " Tahun " & DATEDIF(Q17, TODAY(), "YM") & " Bulan" -> 2 Tahun 6 Bulan | S17: Penata Golongan III/c | T17: 45261 | U17: =DATEDIF(T17,TODAY(), "Y") & " Tahun " & DATEDIF(T17, TODAY(), "YM") & " Bulan" -> 2 Tahun 1 Bulan | V17: Dosen S1 T. Telekomunikasi | W17: DOSEN | X17: =IF(AND(OR(L17="AA",L17="L"),OR(S17="Penata Muda Tk. I Golongan III/b",S17="Penata Golongan III/c"),DATEDIF(Q17,TODAY(),"m")>=23,ISBLANK(Z17),C17="Aktif"),"Nominasi Serdos","-") -> - | Z17: Punya | AA17: 22107201902509 | AB17: 22-001002-0047 | AC17: 44783 | AH17: S3 | AM17: 43101 | AN17: =DATEDIF(AM17,TODAY(),"y")&" tahun "&DATEDIF(AM17,TODAY(),"ym")&" bulan " -> 8 tahun 0 bulan | AO17: FTEIC | AP17: Program Studi S1 T. Telekomunikasi (FTEIC) | AQ17: UCN | AR17: muhsin@ittelkom-sby.ac.id | AS17: 81277773171 | AT17: Tanon Lor, Colomadu, Karanganyar | AW17: =VLOOKUP(B17,Sheet2!A19:I136,9,FALSE) -> Muhsin, S.T., M.T., Ph. D. | AX17: Laki-laki | AY17: =VLOOKUP(B17,Sheet2!A19:C136,2,FALSE) -> Karanganyar | AZ17: =VLOOKUP(B17,Sheet2!A19:C136,3,FALSE) -> 34427 | BA17: =DATEDIF(AZ17, TODAY(),"y") -> 31 | BL17: =VLOOKUP(B17,Sheet2!A19:D136,4,FALSE) -> Kabag | BR17: =VLOOKUP(B17,Sheet2!A19:E136,5,FALSE) -> Intelligent Communications and Networks (ICON) | BS17: =VLOOKUP(B17,Sheet2!A19:F136,6,FALSE) -> MCN | BT17: =VLOOKUP(B17,Sheet2!A19:G136,7,FALSE) -> Fakultas Teknik Elektro | BU17: =VLOOKUP(B17,Sheet2!A19:H136,8,FALSE) -> mmuhsin@telkomuniversity.ac.id | BV17: =COUNTIFS('Join TPA Dosen'!B:B,Dosen!B37) -> 1 | BW17: =DATEDIF(AM17,DATE(2026,1,1),"y")&" tahun "&DATEDIF(AM17,DATE(2026,1,1),"ym")&" bulan " -> 8 tahun 0 bulan | BX17: =VLOOKUP($B17,Sheet1!$A:$G,2,FALSE) -> Tel-U | BY17: =VLOOKUP($B17,Sheet1!$A:$G,3,FALSE) -> Teknik Telekomunikasi | BZ17: =VLOOKUP($B17,Sheet1!$A:$G,4,FALSE) -> Tel-U | CA17: =VLOOKUP($B17,Sheet1!$A:$G,5,FALSE) -> Teknik Elektro - Telekomunikasi | CB17: =VLOOKUP($B17,Sheet1!$A:$G,6,FALSE) -> Universiti Teknologi Malaysia | CC17: =VLOOKUP($B17,Sheet1!$A:$G,7,FALSE) -> Electrical System Engineering | CD17: Intergrated and Embedded Systems | CE17: ETHES (Electrical Engineering and Advanced Technologies)
A18: 19 | B18: Nilla Rachmaningrum | C18: Aktif | D18: Teknik Telekomunikasi | E18: 25780004 | F18: 0408067804 | G18: 3940756657230162 | H18: TETAP | J18: S.T., M.T. | K18: AA.2 | L18: AA | M18: =IF(L18="NJAD","AA",IF(L18="AA","L",IF(L18="L","LK","GB"))) -> L | N18: - | O18: 150 | P18: Elektromagnetika, Elektromagnetika Telekomunikasi, Antena dan Propagasi dan Sistem Komunikasi Seluler | Q18: 44218 | R18: =DATEDIF(Q18,TODAY(), "Y") & " Tahun " & DATEDIF(Q18, TODAY(), "YM") & " Bulan" -> 4 Tahun 11 Bulan | S18: Penata Muda Tk. I Golongan III/b | T18: 44593 | U18: =DATEDIF(T18,TODAY(), "Y") & " Tahun " & DATEDIF(T18, TODAY(), "YM") & " Bulan" -> 3 Tahun 11 Bulan | V18: Dosen S1 T. Telekomunikasi | W18: DOSEN | X18: =IF(AND(OR(L18="AA",L18="L"),OR(S18="Penata Muda Tk. I Golongan III/b",S18="Penata Golongan III/c"),DATEDIF(Q18,TODAY(),"m")>=23,ISBLANK(Z18),C18="Aktif"),"Nominasi Serdos","-") -> Nominasi Serdos | AC18: - | AH18: S2 | AM18: 43101 | AN18: =DATEDIF(AM18,TODAY(),"y")&" tahun "&DATEDIF(AM18,TODAY(),"ym")&" bulan " -> 8 tahun 0 bulan | AO18: FTEIC | AP18: Program Studi S1 T. Telekomunikasi (FTEIC) | AQ18: NRR | AR18: nilla.rachmaningrum@ittelkom-sby.ac.id | AS18: 85235758329 | AT18: Jl. Adhyaksa Raya No. 27, Bandung | AW18: =VLOOKUP(B18,Sheet2!A20:I137,9,FALSE) -> Nilla Rachmaningrum, S.T., M.T. | AX18: Perempuan | AY18: =VLOOKUP(B18,Sheet2!A20:C137,2,FALSE) -> Madiun | AZ18: =VLOOKUP(B18,Sheet2!A20:C137,3,FALSE) -> 28649 | BA18: =DATEDIF(AZ18, TODAY(),"y") -> 47 | BL18: =VLOOKUP(B18,Sheet2!A20:D137,4,FALSE) -> Dosen | BR18: =VLOOKUP(B18,Sheet2!A20:E137,5,FALSE) -> Intelligent Communications and Networks (ICON) | BS18: =VLOOKUP(B18,Sheet2!A20:F137,6,FALSE) -> NRR | BT18: =VLOOKUP(B18,Sheet2!A20:G137,7,FALSE) -> Fakultas Teknik Elektro | BU18: =VLOOKUP(B18,Sheet2!A20:H137,8,FALSE) -> nrachmaningrum@telkomuniversity.ac.id | BV18: =COUNTIFS('Join TPA Dosen'!B:B,Dosen!B20) -> 1 | BW18: =DATEDIF(AM18,DATE(2026,1,1),"y")&" tahun "&DATEDIF(AM18,DATE(2026,1,1),"ym")&" bulan " -> 8 tahun 0 bulan | BX18: =VLOOKUP($B18,Sheet1!$A:$G,2,FALSE) -> Univ. Brawijaya | BY18: =VLOOKUP($B18,Sheet1!$A:$G,3,FALSE) -> Teknik Elektro | BZ18: =VLOOKUP($B18,Sheet1!$A:$G,4,FALSE) -> Univ. Mercu Buana Jakarta | CA18: =VLOOKUP($B18,Sheet1!$A:$G,5,FALSE) -> Teknik Elektro | CB18: =VLOOKUP($B18,Sheet1!$A:$G,6,FALSE) -> - | CC18: =VLOOKUP($B18,Sheet1!$A:$G,7,FALSE) -> 0 | CD18: Motion Technology for Safety, Health, and Wellness | CE18: ETHES (Electrical Engineering and Advanced Technologies)
A19: 29 | B19: Dewi Rahmawati | C19: Aktif | D19: Rekayasa Perangkat Lunak | E19: 20940001 | F19: 0709039401 | G19: 5641772673230262 | H19: TETAP | I19: Dr. | J19: S.Kom., M.Kom. | K19: L.3 | L19: L | M19: =IF(L19="NJAD","AA",IF(L19="AA","L",IF(L19="L","LK","GB"))) -> LK | N19: - | O19: 200 | P19: Algoritma dan Struktur Data, Algoritma dan Pemrograman, Desain Interaksi Pengguna, Animasi dan Pemodelan 3D | Q19: 45108 | R19: =DATEDIF(Q19,TODAY(), "Y") & " Tahun " & DATEDIF(Q19, TODAY(), "YM") & " Bulan" -> 2 Tahun 6 Bulan | S19: Penata Golongan III/c | T19: 45658 | U19: =DATEDIF(T19,TODAY(), "Y") & " Tahun " & DATEDIF(T19, TODAY(), "YM") & " Bulan" -> 1 Tahun 0 Bulan | V19: Dosen S1 RPL | W19: DOSEN | X19: =IF(AND(OR(L19="AA",L19="L"),OR(S19="Penata Muda Tk. I Golongan III/b",S19="Penata Golongan III/c"),DATEDIF(Q19,TODAY(),"m")>=23,ISBLANK(Z19),C19="Aktif"),"Nominasi Serdos","-") -> - | Z19: Punya | AA19: 22107201905492 | AB19: 22-001013-0114 | AC19: 44846 | AH19: S3 | AM19: 43282 | AN19: =DATEDIF(AM19,TODAY(),"y")&" tahun "&DATEDIF(AM19,TODAY(),"ym")&" bulan " -> 7 tahun 6 bulan | AO19: FTIB | AP19: Program Studi S1 RPL (FTIB) | AQ19: DEW | AR19: dewirahmawati@ittelkom-sby.ac.id | AS19: 81359057346 | AT19: Perumahan Gempol Citra Asri O-24 Pasuruan | AW19: =VLOOKUP(B19,Sheet2!A30:I147,9,FALSE) -> Dr. Dewi Rahmawati, S.Kom., M.Kom. | AX19: Perempuan | AY19: =VLOOKUP(B19,Sheet2!A30:C147,2,FALSE) -> Malang | AZ19: =VLOOKUP(B19,Sheet2!A30:C147,3,FALSE) -> 34402 | BA19: =DATEDIF(AZ19, TODAY(),"y") -> 31 | BL19: =VLOOKUP(B19,Sheet2!A30:D147,4,FALSE) -> Dosen | BR19: =VLOOKUP(B19,Sheet2!A30:E147,5,FALSE) -> Data Science and Intelligent Systems (DSIS) | BS19: =VLOOKUP(B19,Sheet2!A30:F147,6,FALSE) -> DWX | BT19: =VLOOKUP(B19,Sheet2!A30:G147,7,FALSE) -> Fakultas Informatika | BU19: =VLOOKUP(B19,Sheet2!A30:H147,8,FALSE) -> dewirahmawati@telkomuniversity.ac.id | BV19: =COUNTIFS('Join TPA Dosen'!B:B,Dosen!B19) -> 1 | BW19: =DATEDIF(AM19,DATE(2026,1,1),"y")&" tahun "&DATEDIF(AM19,DATE(2026,1,1),"ym")&" bulan " -> 7 tahun 6 bulan | BX19: =VLOOKUP($B19,Sheet1!$A:$G,2,FALSE) -> Universitas Islam Negeri Maulana Malik Ibrahim Malang | BY19: =VLOOKUP($B19,Sheet1!$A:$G,3,FALSE) -> Teknik Informatika | BZ19: =VLOOKUP($B19,Sheet1!$A:$G,4,FALSE) -> ITS | CA19: =VLOOKUP($B19,Sheet1!$A:$G,5,FALSE) -> Teknik Informatika | CB19: =VLOOKUP($B19,Sheet1!$A:$G,6,FALSE) -> ITS | CC19: =VLOOKUP($B19,Sheet1!$A:$G,7,FALSE) -> Ilmu Komputer | CD19: Motion Technology for Safety, Health, and Wellness | CE19: Smart Computing Technology (SCOUT)
A20: 31 | B20: Ardian Yusuf Wicaksono | C20: Aktif | D20: Informatika | E20: 25920026 | F20: 0727099201 | G20: 5259770671130293 | H20: TETAP | J20: S.Kom., M.Kom. | K20: AA.2 | L20: AA | M20: =IF(L20="NJAD","AA",IF(L20="AA","L",IF(L20="L","LK","GB"))) -> L | N20: - | O20: 150 | P20: Konsep Pengembangan Sains dan Teknologi RPL, Fisika Dasar dan Praktikum Fisika Dasar | Q20: 43999 | R20: =DATEDIF(Q20,TODAY(), "Y") & " Tahun " & DATEDIF(Q20, TODAY(), "YM") & " Bulan" -> 5 Tahun 7 Bulan | S20: Penata Muda Tk. I Golongan III/b | T20: 44044 | U20: =DATEDIF(T20,TODAY(), "Y") & " Tahun " & DATEDIF(T20, TODAY(), "YM") & " Bulan" -> 5 Tahun 5 Bulan | V20: Koordinator Kelompok Keahlian Informatika Kampus Surabaya | W20: DOSEN | X20: =IF(AND(OR(L20="AA",L20="L"),OR(S20="Penata Muda Tk. I Golongan III/b",S20="Penata Golongan III/c"),DATEDIF(Q20,TODAY(),"m")>=23,ISBLANK(Z20),C20="Aktif"),"Nominasi Serdos","-") -> - | Z20: Punya | AA20: 22107201905491 | AB20: 22-002002-0133 | AC20: 44846 | AH20: S2 | AM20: 43282 | AN20: =DATEDIF(AM20,TODAY(),"y")&" tahun "&DATEDIF(AM20,TODAY(),"ym")&" bulan " -> 7 tahun 6 bulan | AO20: FTIB | AP20: Program Studi S1 Informatika (FTIB) | AQ20: ARD | AR20: ardian@ittelkom-sby.ac.id | AS20: 82245510526 | AT20: Jalan Mayor Bismo No. 26A RT/RW 02/02, Templek, Gadungan, Puncu, Kediri | AW20: =VLOOKUP(B20,Sheet2!A32:I149,9,FALSE) -> Ardian Yusuf Wicaksono, S.Kom., M.Kom. | AX20: Laki-laki | AY20: =VLOOKUP(B20,Sheet2!A32:C149,2,FALSE) -> Nganjuk | AZ20: =VLOOKUP(B20,Sheet2!A32:C149,3,FALSE) -> 33874 | BA20: =DATEDIF(AZ20, TODAY(),"y") -> 33 | BL20: =VLOOKUP(B20,Sheet2!A32:D149,4,FALSE) -> Kabag | BR20: =VLOOKUP(B20,Sheet2!A32:E149,5,FALSE) -> Data Science and Intelligent Systems (DSIS) | BS20: =VLOOKUP(B20,Sheet2!A32:F149,6,FALSE) -> CAK | BT20: =VLOOKUP(B20,Sheet2!A32:G149,7,FALSE) -> Fakultas Informatika | BU20: =VLOOKUP(B20,Sheet2!A32:H149,8,FALSE) -> ardianyw@telkomuniversity.ac.id | BV20: =COUNTIFS('Join TPA Dosen'!B:B,Dosen!B4) -> 1 | BW20: =DATEDIF(AM20,DATE(2026,1,1),"y")&" tahun "&DATEDIF(AM20,DATE(2026,1,1),"ym")&" bulan " -> 7 tahun 6 bulan | BX20: =VLOOKUP($B20,Sheet1!$A:$G,2,FALSE) -> ITS | BY20: =VLOOKUP($B20,Sheet1!$A:$G,3,FALSE) -> Teknologi Informasi/Teknik Informatika | BZ20: =VLOOKUP($B20,Sheet1!$A:$G,4,FALSE) -> ITS | CA20: =VLOOKUP($B20,Sheet1!$A:$G,5,FALSE) -> Teknologi Informasi/Teknik Informatika | CB20: =VLOOKUP($B20,Sheet1!$A:$G,6,FALSE) -> - | CC20: =VLOOKUP($B20,Sheet1!$A:$G,7,FALSE) -> 0 | CD20: Intergrated and Embedded Systems | CE20: Smart Computing Technology (SCOUT)
A21: 33 | B21: Rizqa Amelia Zunaidi | C21: Aktif | D21: Teknik Industri | E21: 20930036 | F21: 0711069301 | G21: 5943771672230272 | H21: TETAP | J21: S.T., M.T. | K21: L.2 | L21: L | M21: =IF(L21="NJAD","AA",IF(L21="AA","L",IF(L21="L","LK","GB"))) -> LK | N21: - | O21: 200 | P21: Teori Probabilitas, Statistika Industri, Pengendalian Mutu dan Perancangan Produk | Q21: 44927 | R21: =DATEDIF(Q21,TODAY(), "Y") & " Tahun " & DATEDIF(Q21, TODAY(), "YM") & " Bulan" -> 3 Tahun 0 Bulan | S21: Penata Golongan III/c | T21: 45047 | U21: =DATEDIF(T21,TODAY(), "Y") & " Tahun " & DATEDIF(T21, TODAY(), "YM") & " Bulan" -> 2 Tahun 8 Bulan | V21: Dosen S1 Teknik Industri | W21: DOSEN | X21: =IF(AND(OR(L21="AA",L21="L"),OR(S21="Penata Muda Tk. I Golongan III/b",S21="Penata Golongan III/c"),DATEDIF(Q21,TODAY(),"m")>=23,ISBLANK(Z21),C21="Aktif"),"Nominasi Serdos","-") -> - | Z21: Punya | AA21: 22107201902709 | AB21: 22-001001-0165 | AC21: 44783 | AH21: S2 | AI21: Ya | AJ21: TB | AK21: Ya | AM21: 43282 | AN21: =DATEDIF(AM21,TODAY(),"y")&" tahun "&DATEDIF(AM21,TODAY(),"ym")&" bulan " -> 7 tahun 6 bulan | AO21: FTEIC | AP21: Program Studi S1 Teknik Industri (FTEIC) | AQ21: RAZ | AR21: rizqazunaidi@ittelkom-sby.ac.id | AS21: 81221804899 | AT21: Perumahan Magersari Permai BK-29 RT 31 RW 07 Sidoarjo, Jawa Timur | AW21: =VLOOKUP(B21,Sheet2!A34:I151,9,FALSE) -> Rizqa Amelia Zunaidi, S.T., M.T. | AX21: Perempuan | AY21: =VLOOKUP(B21,Sheet2!A34:C151,2,FALSE) -> Bojonegoro | AZ21: =VLOOKUP(B21,Sheet2!A34:C151,3,FALSE) -> 34131 | BA21: =DATEDIF(AZ21, TODAY(),"y") -> 32 | BL21: =VLOOKUP(B21,Sheet2!A34:D151,4,FALSE) -> Dosen | BR21: =VLOOKUP(B21,Sheet2!A34:E151,5,FALSE) -> Engineering Management System | BS21: =VLOOKUP(B21,Sheet2!A34:F151,6,FALSE) -> ZQA | BT21: =VLOOKUP(B21,Sheet2!A34:G151,7,FALSE) -> Fakultas Rekayasa Industri | BU21: =VLOOKUP(B21,Sheet2!A34:H151,8,FALSE) -> rizqazunaidi@telkomuniversity.ac.id | BV21: =COUNTIFS('Join TPA Dosen'!B:B,Dosen!B44) -> 1 | BW21: =DATEDIF(AM21,DATE(2026,1,1),"y")&" tahun "&DATEDIF(AM21,DATE(2026,1,1),"ym")&" bulan " -> 7 tahun 6 bulan | BX21: =VLOOKUP($B21,Sheet1!$A:$G,2,FALSE) -> ITB | BY21: =VLOOKUP($B21,Sheet1!$A:$G,3,FALSE) -> Manajemen Rekayasa Industri | BZ21: =VLOOKUP($B21,Sheet1!$A:$G,4,FALSE) -> ITB | CA21: =VLOOKUP($B21,Sheet1!$A:$G,5,FALSE) -> Teknik dan Manajemen Industri | CB21: =VLOOKUP($B21,Sheet1!$A:$G,6,FALSE) -> - | CC21: =VLOOKUP($B21,Sheet1!$A:$G,7,FALSE) -> 0 | CD21: Circular Ecosystem and Sustainable Technology | CE21: Rekayasa Industri dan Inovasi Bisnis (RIIB)
A22: 34 | B22: Titus Kristanto | C22: Aktif | D22: Digital Bisnis | E22: 20860014 | F22: 0710028604 | G22: 7542764665137062 | H22: TETAP | J22: S.Kom., M.Kom. | K22: L.2 | L22: L | M22: =IF(L22="NJAD","AA",IF(L22="AA","L",IF(L22="L","LK","GB"))) -> LK | N22: - | O22: 200 | P22: Konsep Pengembangan Sains dan Teknologi, Etika Profesionalisme dan Komunikasi, Anlisis Kebutuhan Perangkat Lunak, Desain Interaksi Pengguna | Q22: 44428 | R22: =DATEDIF(Q22,TODAY(), "Y") & " Tahun " & DATEDIF(Q22, TODAY(), "YM") & " Bulan" -> 4 Tahun 4 Bulan | S22: Penata Golongan III/c | T22: 45047 | U22: =DATEDIF(T22,TODAY(), "Y") & " Tahun " & DATEDIF(T22, TODAY(), "YM") & " Bulan" -> 2 Tahun 8 Bulan | V22: Dosen S1 Digital Bisnis | W22: DOSEN | X22: =IF(AND(OR(L22="AA",L22="L"),OR(S22="Penata Muda Tk. I Golongan III/b",S22="Penata Golongan III/c"),DATEDIF(Q22,TODAY(),"m")>=23,ISBLANK(Z22),C22="Aktif"),"Nominasi Serdos","-") -> - | Z22: Punya | AA22: 18107200206321 | AB22: 1.8001e+15 | AC22: 43224 | AH22: S2 | AI22: Ya | AJ22: IB | AK22: Tidak | AL22: On Progress S3 IB | AM22: 43282 | AN22: =DATEDIF(AM22,TODAY(),"y")&" tahun "&DATEDIF(AM22,TODAY(),"ym")&" bulan " -> 7 tahun 6 bulan | AO22: FTIB | AP22: Program Studi S1 Digital Bisnis (FTIB) | AQ22: TTK | AR22: titus.kristanto@ittelkom-sby.ac.id | AS22: 81325019978 | AT22: Jl. Darmo Indah Selatan 3 Blok GG-25 Surabaya | AW22: =VLOOKUP(B22,Sheet2!A35:I152,9,FALSE) -> Titus Kristanto, S.Kom., M.Kom. | AX22: Laki-laki | AY22: =VLOOKUP(B22,Sheet2!A35:C152,2,FALSE) -> Surabaya | AZ22: =VLOOKUP(B22,Sheet2!A35:C152,3,FALSE) -> 31453 | BA22: =DATEDIF(AZ22, TODAY(),"y") -> 39 | BL22: =VLOOKUP(B22,Sheet2!A35:D152,4,FALSE) -> Dosen | BR22: =VLOOKUP(B22,Sheet2!A35:E152,5,FALSE) -> ICT Business Management (IBM) | BS22: =VLOOKUP(B22,Sheet2!A35:F152,6,FALSE) -> TTK | BT22: =VLOOKUP(B22,Sheet2!A35:G152,7,FALSE) -> Fakultas Ekonomi dan Bisnis | BU22: =VLOOKUP(B22,Sheet2!A35:H152,8,FALSE) -> tituskristanto@telkomuniversity.ac.id | BV22: =COUNTIFS('Join TPA Dosen'!B:B,Dosen!B76) -> 1 | BW22: =DATEDIF(AM22,DATE(2026,1,1),"y")&" tahun "&DATEDIF(AM22,DATE(2026,1,1),"ym")&" bulan " -> 7 tahun 6 bulan | BX22: =VLOOKUP($B22,Sheet1!$A:$G,2,FALSE) -> UNTAG | BY22: =VLOOKUP($B22,Sheet1!$A:$G,3,FALSE) -> Teknik/Teknik Informatika | BZ22: =VLOOKUP($B22,Sheet1!$A:$G,4,FALSE) -> ITS | CA22: =VLOOKUP($B22,Sheet1!$A:$G,5,FALSE) -> Teknik Informatika - Sistem Informasi | CB22: =VLOOKUP($B22,Sheet1!$A:$G,6,FALSE) -> ITS | CC22: =VLOOKUP($B22,Sheet1!$A:$G,7,FALSE) -> Ilmu Komputer | CD22: Circular Ecosystem and Sustainable Technology | CE22: Rekayasa Industri dan Inovasi Bisnis (RIIB)
A23: 35 | B23: Pangestu Widodo | C23: Aktif | D23: Teknik Komputer | E23: 20830012 | F23: 0721058310 | G23: 6853761662130212 | H23: TETAP | J23: S.T., M.Kom. | K23: AA.2 | L23: AA | M23: =IF(L23="NJAD","AA",IF(L23="AA","L",IF(L23="L","LK","GB"))) -> L | N23: - | O23: 150 | P23: Rekayasa Perangkat Lunak, Pemrograman Web, Kecerdasan Buatan | Q23: 45870 | R23: =DATEDIF(Q23,TODAY(), "Y") & " Tahun " & DATEDIF(Q23, TODAY(), "YM") & " Bulan" -> 0 Tahun 5 Bulan | S23: Penata Muda Tk. I Golongan III/b | T23: 45992 | U23: =DATEDIF(T23,TODAY(), "Y") & " Tahun " & DATEDIF(T23, TODAY(), "YM") & " Bulan" -> 0 Tahun 1 Bulan | V23: Dosen S1 T. Komputer | W23: DOSEN | X23: =IF(AND(OR(L23="AA",L23="L"),OR(S23="Penata Muda Tk. I Golongan III/b",S23="Penata Golongan III/c"),DATEDIF(Q23,TODAY(),"m")>=23,ISBLANK(Z23),C23="Aktif"),"Nominasi Serdos","-") -> - | AC23: - | AH23: S2 | AM23: 43282 | AN23: =DATEDIF(AM23,TODAY(),"y")&" tahun "&DATEDIF(AM23,TODAY(),"ym")&" bulan " -> 7 tahun 6 bulan | AO23: FTEIC | AP23: Program Studi S1 T. Komputer (FTEIC) | AQ23: PNG | AR23: pangestu@ittelkom-sby.ac.id | AS23: 85258754375 | AT23: Jl. Tumapel 1 RT/RW 007/009 Kel. Kauman Kec. Klojen Kota Malang | AW23: =VLOOKUP(B23,Sheet2!A36:I153,9,FALSE) -> Pangestu Widodo, S.T., M.Kom. | AX23: Laki-laki | AY23: =VLOOKUP(B23,Sheet2!A36:C153,2,FALSE) -> Malang | AZ23: =VLOOKUP(B23,Sheet2!A36:C153,3,FALSE) -> 30457 | BA23: =DATEDIF(AZ23, TODAY(),"y") -> 42 | BL23: =VLOOKUP(B23,Sheet2!A36:D153,4,FALSE) -> Dosen | BR23: =VLOOKUP(B23,Sheet2!A36:E153,5,FALSE) -> Signal Processing, Information Security, and Computer Engineering (SPICE) | BS23: =VLOOKUP(B23,Sheet2!A36:F153,6,FALSE) -> PNG | BT23: =VLOOKUP(B23,Sheet2!A36:G153,7,FALSE) -> Fakultas Teknik Elektro | BU23: =VLOOKUP(B23,Sheet2!A36:H153,8,FALSE) -> pangestuw@telkomuniversity.ac.id | BV23: =COUNTIFS('Join TPA Dosen'!B:B,Dosen!B36) -> 1 | BW23: =DATEDIF(AM23,DATE(2026,1,1),"y")&" tahun "&DATEDIF(AM23,DATE(2026,1,1),"ym")&" bulan " -> 7 tahun 6 bulan | BX23: =VLOOKUP($B23,Sheet1!$A:$G,2,FALSE) -> ITB | BY23: =VLOOKUP($B23,Sheet1!$A:$G,3,FALSE) -> Teknik Informatika | BZ23: =VLOOKUP($B23,Sheet1!$A:$G,4,FALSE) -> ITS | CA23: =VLOOKUP($B23,Sheet1!$A:$G,5,FALSE) -> Teknik Informatika | CB23: =VLOOKUP($B23,Sheet1!$A:$G,6,FALSE) -> - | CC23: =VLOOKUP($B23,Sheet1!$A:$G,7,FALSE) -> 0 | CD23: Intergrated and Embedded Systems | CE23: Smart Computing Technology (SCOUT)
A24: 36 | B24: Abduh Sayid Albana | C24: Aktif | D24: Teknik Logistik | E24: 19900001 | F24: 0702039003 | G24: 9634768669130272 | H24: TETAP | J24: S.T., M.T., M.Sc., Ph.D. | K24: L.3 | L24: L | M24: =IF(L24="NJAD","AA",IF(L24="AA","L",IF(L24="L","LK","GB"))) -> LK | N24: - | O24: 200 | P24: Kalkulus IA, Kalkulus IIA, Matriks dan Vektor, Penelitian Operasional I | Q24: 44032 | R24: =DATEDIF(Q24,TODAY(), "Y") & " Tahun " & DATEDIF(Q24, TODAY(), "YM") & " Bulan" -> 5 Tahun 5 Bulan | S24: Penata Golongan III/c | T24: 45047 | U24: =DATEDIF(T24,TODAY(), "Y") & " Tahun " & DATEDIF(T24, TODAY(), "YM") & " Bulan" -> 2 Tahun 8 Bulan | V24: Koordinator Kelompok Keahlian Rekayasa Industri Kampus Surabaya | W24: DOSEN | X24: =IF(AND(OR(L24="AA",L24="L"),OR(S24="Penata Muda Tk. I Golongan III/b",S24="Penata Golongan III/c"),DATEDIF(Q24,TODAY(),"m")>=23,ISBLANK(Z24),C24="Aktif"),"Nominasi Serdos","-") -> - | Z24: Punya | AA24: 23107201901133 | AB24: 23-002001-0272 | AC24: 45085 | AH24: S3 | AM24: 43282 | AN24: =DATEDIF(AM24,TODAY(),"y")&" tahun "&DATEDIF(AM24,TODAY(),"ym")&" bulan " -> 7 tahun 6 bulan | AO24: FTEIC | AP24: Program Studi S1 Teknik Logistik (FTEIC) | AQ24: ASA | AR24: abduh.albana@ittelkom-sby.ac.id | AS24: 82142628195 | AT24: Perum. Kwayangan Jl. Amarta IV, Rt.04 Rw.03, Ds. Kwayangan, Kec. Kedungwuni, Kab. Pekalongan, Jawa Tengah - 51173 | AW24: =VLOOKUP(B24,Sheet2!A37:I154,9,FALSE) -> Abduh Sayid Albana, S.T., M.T., M.Sc., Ph.D. | AX24: Laki-laki | AY24: =VLOOKUP(B24,Sheet2!A37:C154,2,FALSE) -> Pekalongan | AZ24: =VLOOKUP(B24,Sheet2!A37:C154,3,FALSE) -> 32934 | BA24: =DATEDIF(AZ24, TODAY(),"y") -> 35 | BL24: CoE | BR24: =VLOOKUP(B24,Sheet2!A37:E154,5,FALSE) -> Enterprise and Industrial System (EINS) | BS24: =VLOOKUP(B24,Sheet2!A37:F154,6,FALSE) -> EXE | BT24: =VLOOKUP(B24,Sheet2!A37:G154,7,FALSE) -> Fakultas Rekayasa Industri | BU24: =VLOOKUP(B24,Sheet2!A37:H154,8,FALSE) -> abduhalbana@telkomuniversity.ac.id | BV24: =COUNTIFS('Join TPA Dosen'!B:B,Dosen!B3) -> 1 | BW24: =DATEDIF(AM24,DATE(2026,1,1),"y")&" tahun "&DATEDIF(AM24,DATE(2026,1,1),"ym")&" bulan " -> 7 tahun 6 bulan | BX24: =VLOOKUP($B24,Sheet1!$A:$G,2,FALSE) -> ITS | BY24: =VLOOKUP($B24,Sheet1!$A:$G,3,FALSE) -> Teknologi Industri/Teknik Industri | BZ24: =VLOOKUP($B24,Sheet1!$A:$G,4,FALSE) -> ITS & Grenoble INP | CA24: =VLOOKUP($B24,Sheet1!$A:$G,5,FALSE) -> Teknologi Industri/Teknik Industri; Master Recherche | CB24: =VLOOKUP($B24,Sheet1!$A:$G,6,FALSE) -> Université Grenoble Alpes | CC24: =VLOOKUP($B24,Sheet1!$A:$G,7,FALSE) -> Industrial Engineering | CD24: Circular Ecosystem and Sustainable Technology | CE24: Rekayasa Industri dan Inovasi Bisnis (RIIB)
A25: 39 | B25: Bernadus Anggo Seno Aji | C25: Aktif | D25: Teknologi Informasi | E25: 23929009 | F25: 0704039202 | G25: 6636770671130272 | H25: TETAP | J25: S.Kom., M.Kom. | K25: L.2 | L25: L | M25: =IF(L25="NJAD","AA",IF(L25="AA","L",IF(L25="L","LK","GB"))) -> LK | O25: 200 | P25: Algoritma dan Pemrograman, Algoritma dan Struktur Data, Praktikum Algoritma dan Pemrograman, Praktikum Algoritma dan Struktur Data | Q25: 45931 | R25: =DATEDIF(Q25,TODAY(), "Y") & " Tahun " & DATEDIF(Q25, TODAY(), "YM") & " Bulan" -> 0 Tahun 3 Bulan | S25: Penata Golongan III/c | T25: 46023 | U25: =DATEDIF(T25,TODAY(), "Y") & " Tahun " & DATEDIF(T25, TODAY(), "YM") & " Bulan" -> 0 Tahun 0 Bulan | V25: Kaprodi S1 Teknologi Informasi | W25: DOSEN | X25: =IF(AND(OR(L25="AA",L25="L"),OR(S25="Penata Muda Tk. I Golongan III/b",S25="Penata Golongan III/c"),DATEDIF(Q25,TODAY(),"m")>=23,ISBLANK(Z25),C25="Aktif"),"Nominasi Serdos","-") -> - | Z25: Punya | AA25: 23107201903252 | AB25: 23-002002-0113 | AC25: 45085 | AH25: S2 | AI25: Ya | AJ25: TB | AK25: Ya | AM25: 43282 | AN25: =DATEDIF(AM25,TODAY(),"y")&" tahun "&DATEDIF(AM25,TODAY(),"ym")&" bulan " -> 7 tahun 6 bulan | AO25: FTIB | AP25: Program Studi S1 Teknologi Informasi (FTIB) | AQ25: BAS | AR25: bernadus.seno@ittelkom-sby.ac.id | AS25: 81324604072 | AT25: Desa Kapung Rt 001 Rw 002, Kecamatan Tanggungharjo, Grobogan | AW25: =VLOOKUP(B25,Sheet2!A40:I157,9,FALSE) -> Bernadus Anggo Seno Aji, S.Kom., M.Kom. | AX25: Laki-laki | AY25: =VLOOKUP(B25,Sheet2!A40:C157,2,FALSE) -> Grobogan | AZ25: =VLOOKUP(B25,Sheet2!A40:C157,3,FALSE) -> 33697 | BA25: =DATEDIF(AZ25, TODAY(),"y") -> 33 | BL25: Dosen | BR25: =VLOOKUP(B25,Sheet2!A40:E157,5,FALSE) -> Data Science and Intelligent Systems (DSIS) | BS25: =VLOOKUP(B25,Sheet2!A40:F157,6,FALSE) -> BOS | BT25: =VLOOKUP(B25,Sheet2!A40:G157,7,FALSE) -> Fakultas Informatika | BU25: =VLOOKUP(B25,Sheet2!A40:H157,8,FALSE) -> bernadusanggosenoaji@telkomuniversity.ac.id | BV25: =COUNTIFS('Join TPA Dosen'!B:B,Dosen!B9) -> 1 | BW25: =DATEDIF(AM25,DATE(2026,1,1),"y")&" tahun "&DATEDIF(AM25,DATE(2026,1,1),"ym")&" bulan " -> 7 tahun 6 bulan | BX25: =VLOOKUP($B25,Sheet1!$A:$G,2,FALSE) -> Tel-U | BY25: =VLOOKUP($B25,Sheet1!$A:$G,3,FALSE) -> Ilmu Komputasi | BZ25: =VLOOKUP($B25,Sheet1!$A:$G,4,FALSE) -> Tel-U | CA25: =VLOOKUP($B25,Sheet1!$A:$G,5,FALSE) -> Teknik Informatika | CB25: =VLOOKUP($B25,Sheet1!$A:$G,6,FALSE) -> - | CC25: =VLOOKUP($B25,Sheet1!$A:$G,7,FALSE) -> 0 | CD25: Intergrated and Embedded Systems | CE25: Smart Computing Technology (SCOUT)
A26: 41 | B26: Agus Sulistya | C26: Aktif | D26: Sistem Informasi | E26: 19750005 | F26: 8920230021 | G26: 4150753654130133 | H26: PERBANTUAN | J26: S.T., M.Sc., Ph.D | K26: L.3 | L26: L | M26: =IF(L26="NJAD","AA",IF(L26="AA","L",IF(L26="L","LK","GB"))) -> LK | N26: - | O26: 200 | P26: Penjaminan Kualitas Perangkat Lunak, Algoritma dan Pemrograman, Perancangan Basis Data Relational | Q26: 45444 | R26: =DATEDIF(Q26,TODAY(), "Y") & " Tahun " & DATEDIF(Q26, TODAY(), "YM") & " Bulan" -> 1 Tahun 7 Bulan | S26: Penata Golongan III/c | T26: 45748 | U26: =DATEDIF(T26,TODAY(), "Y") & " Tahun " & DATEDIF(T26, TODAY(), "YM") & " Bulan" -> 0 Tahun 9 Bulan | V26: Wakil Direktur Bidang Sumber Daya | W26: DOSEN | X26: =IF(AND(OR(L26="AA",L26="L"),OR(S26="Penata Muda Tk. I Golongan III/b",S26="Penata Golongan III/c"),DATEDIF(Q26,TODAY(),"m")>=23,ISBLANK(Z26),C26="Aktif"),"Nominasi Serdos","-") -> - | AC26: - | AH26: S3 | AM26: 43770 | AN26: =DATEDIF(AM26,TODAY(),"y")&" tahun "&DATEDIF(AM26,TODAY(),"ym")&" bulan " -> 6 tahun 2 bulan | AO26: FTIB | AP26: Program Studi S1 Sistem Informasi (FTIB) | AQ26: AGS | AR26: sulistya@ittelkom-sby.ac.id | AS26: 8127041015 | AT26: Jl. Rungkut Barata III/6, Rungkut Menanggal, Gunung Anyar, Surabaya | AW26: =VLOOKUP(B26,Sheet2!A42:I159,9,FALSE) -> Agus Sulistya, S.T., M.Sc., Ph.D | AX26: Laki-laki | AY26: =VLOOKUP(B26,Sheet2!A42:C159,2,FALSE) -> Magelang | AZ26: =VLOOKUP(B26,Sheet2!A42:C159,3,FALSE) -> 27624 | BA26: =DATEDIF(AZ26, TODAY(),"y") -> 50 | BL26: =VLOOKUP(B26,Sheet2!A42:D159,4,FALSE) -> Wakil Direktur Bidang Sumber Daya | BR26: =VLOOKUP(B26,Sheet2!A42:E159,5,FALSE) -> Cybernetics | BS26: =VLOOKUP(B26,Sheet2!A42:F159,6,FALSE) -> AGX | BT26: =VLOOKUP(B26,Sheet2!A42:G159,7,FALSE) -> Fakultas Rekayasa Industri | BU26: =VLOOKUP(B26,Sheet2!A42:H159,8,FALSE) -> sulistya@telkomuniversity.ac.id | BV26: =COUNTIFS('Join TPA Dosen'!B:B,Dosen!B42) -> 1 | BW26: =DATEDIF(AM26,DATE(2026,1,1),"y")&" tahun "&DATEDIF(AM26,DATE(2026,1,1),"ym")&" bulan " -> 6 tahun 2 bulan | BX26: =VLOOKUP($B26,Sheet1!$A:$G,2,FALSE) -> STT Telkom | BY26: =VLOOKUP($B26,Sheet1!$A:$G,3,FALSE) -> Teknik Informatika | BZ26: =VLOOKUP($B26,Sheet1!$A:$G,4,FALSE) -> Northeastern Univ | CA26: =VLOOKUP($B26,Sheet1!$A:$G,5,FALSE) -> Information Systems | CB26: =VLOOKUP($B26,Sheet1!$A:$G,6,FALSE) -> Singapore Manajement Univ | CC26: =VLOOKUP($B26,Sheet1!$A:$G,7,FALSE) -> Information Systems | CD26: Circular Ecosystem and Sustainable Technology | CE26: Smart Computing Technology (SCOUT)
A27: 42 | B27: Risdilah Mimma Untsa | C27: Aktif | D27: Teknik Telekomunikasi | E27: 20910025 | F27: 0720019102 | G27: 7452769670230282 | H27: PROFESIONAL | J27: S.ST., M.T. | K27: NJAD.2 | L27: NJAD | M27: =IF(L27="NJAD","AA",IF(L27="AA","L",IF(L27="L","LK","GB"))) -> AA | N27: - | O27: 0 | Q27: 43891 | R27: =DATEDIF(Q27,TODAY(), "Y") & " Tahun " & DATEDIF(Q27, TODAY(), "YM") & " Bulan" -> 5 Tahun 10 Bulan | S27: - | T27: - | U27: =DATEDIF(T27,TODAY(), "Y") & " Tahun " & DATEDIF(T27, TODAY(), "YM") & " Bulan" -> #VALUE! | V27: Dosen S1 T. Telekomunikasi | W27: DOSEN | X27: =IF(AND(OR(L27="AA",L27="L"),OR(S27="Penata Muda Tk. I Golongan III/b",S27="Penata Golongan III/c"),DATEDIF(Q27,TODAY(),"m")>=23,ISBLANK(Z27),C27="Aktif"),"Nominasi Serdos","-") -> - | AC27: - | AH27: S2 | AM27: 43885 | AN27: =DATEDIF(AM27,TODAY(),"y")&" tahun "&DATEDIF(AM27,TODAY(),"ym")&" bulan " -> 5 tahun 10 bulan | AO27: FTEIC | AP27: Program Studi S1 T. Telekomunikasi (FTEIC) | AQ27: RMU | AR27: risdilah.untsa@ittelkom-sby.ac.id | AS27: 82134018586 | AT27: Jl. Menur Pumpungan, Sukolilo, Surabaya | AW27: =VLOOKUP(B27,Sheet2!A43:I160,9,FALSE) -> Risdilah Mimma Untsa, S.ST., M.T. | AX27: Perempuan | AY27: =VLOOKUP(B27,Sheet2!A43:C160,2,FALSE) -> Surabaya | AZ27: =VLOOKUP(B27,Sheet2!A43:C160,3,FALSE) -> 33258 | BA27: =DATEDIF(AZ27, TODAY(),"y") -> 34 | BL27: =VLOOKUP(B27,Sheet2!A43:D160,4,FALSE) -> Dosen | BR27: =VLOOKUP(B27,Sheet2!A43:E160,5,FALSE) -> Signal Processing, Information Security, and Computer Engineering (SPICE) | BS27: =VLOOKUP(B27,Sheet2!A43:F160,6,FALSE) -> RLL | BT27: =VLOOKUP(B27,Sheet2!A43:G160,7,FALSE) -> Fakultas Teknik Elektro | BU27: =VLOOKUP(B27,Sheet2!A43:H160,8,FALSE) -> risdilah@telkomuniversity.ac.id | BV27: =COUNTIFS('Join TPA Dosen'!B:B,Dosen!B43) -> 1 | BW27: =DATEDIF(AM27,DATE(2026,1,1),"y")&" tahun "&DATEDIF(AM27,DATE(2026,1,1),"ym")&" bulan " -> 5 tahun 10 bulan | BX27: =VLOOKUP($B27,Sheet1!$A:$G,2,FALSE) -> PENS | BY27: =VLOOKUP($B27,Sheet1!$A:$G,3,FALSE) -> Telekomunikasi | BZ27: =VLOOKUP($B27,Sheet1!$A:$G,4,FALSE) -> ITS | CA27: =VLOOKUP($B27,Sheet1!$A:$G,5,FALSE) -> Teknik Elektro | CB27: =VLOOKUP($B27,Sheet1!$A:$G,6,FALSE) -> - | CC27: =VLOOKUP($B27,Sheet1!$A:$G,7,FALSE) -> 0 | CD27: Motion Technology for Safety, Health, and Wellness | CE27: ETHES (Electrical Engineering and Advanced Technologies)
A28: 43 | B28: Susijanto Tri Rasmana | C28: Aktif | D28: Teknik Komputer | E28: 22730002 | F28: 0727097302 | G28: 4259751652130093 | H28: TETAP | I28: Dr. | J28: S.Kom., M.T. | K28: L.3 | L28: L | M28: =IF(L28="NJAD","AA",IF(L28="AA","L",IF(L28="L","LK","GB"))) -> LK | N28: - | O28: 300 | P28: Penginderaan Elektronika, Sistem Pengaturan dan Sistem Digital | Q28: 45108 | R28: =DATEDIF(Q28,TODAY(), "Y") & " Tahun " & DATEDIF(Q28, TODAY(), "YM") & " Bulan" -> 2 Tahun 6 Bulan | S28: Penata Muda Tk. I Golongan III/b | T28: 45658 | U28: =DATEDIF(T28,TODAY(), "Y") & " Tahun " & DATEDIF(T28, TODAY(), "YM") & " Bulan" -> 1 Tahun 0 Bulan | V28: Kabag LPPM | W28: DOSEN | X28: =IF(AND(OR(L28="AA",L28="L"),OR(S28="Penata Muda Tk. I Golongan III/b",S28="Penata Golongan III/c"),DATEDIF(Q28,TODAY(),"m")>=23,ISBLANK(Z28),C28="Aktif"),"Nominasi Serdos","-") -> - | Z28: Punya | AA28: 15107201608505 | AB28: 15-001005-0777 | AC28: 42357 | AH28: S3 | AM28: 44075 | AN28: =DATEDIF(AM28,TODAY(),"y")&" tahun "&DATEDIF(AM28,TODAY(),"ym")&" bulan " -> 5 tahun 4 bulan | AO28: FTEIC | AP28: Program Studi S1 Teknik Elektro (FTEIC) | AQ28: SSJ | AR28: susijanto@ittelkom-sby.ac.id | AS28: 81216170645 | AT28: Jl. Merak III A/Q45, Sidoarjo | AW28: =VLOOKUP(B28,Sheet2!A44:I161,9,FALSE) -> Dr. Susijanto Tri Rasmana, S.Kom., M.T. | AX28: Laki-laki | AY28: =VLOOKUP(B28,Sheet2!A44:C161,2,FALSE) -> Surabaya | AZ28: =VLOOKUP(B28,Sheet2!A44:C161,3,FALSE) -> 26934 | BA28: =DATEDIF(AZ28, TODAY(),"y") -> 52 | BL28: Kaprodi | BR28: =VLOOKUP(B28,Sheet2!A44:E161,5,FALSE) -> Control, Elektronics, and Intelligent Systems (CEIS) | BS28: =VLOOKUP(B28,Sheet2!A44:F161,6,FALSE) -> SUZ | BT28: =VLOOKUP(B28,Sheet2!A44:G161,7,FALSE) -> Fakultas Teknik Elektro | BU28: =VLOOKUP(B28,Sheet2!A44:H161,8,FALSE) -> susijanto@telkomuniversity.ac.id | BV28: =COUNTIFS('Join TPA Dosen'!B:B,Dosen!B45) -> 1 | BW28: =DATEDIF(AM28,DATE(2026,1,1),"y")&" tahun "&DATEDIF(AM28,DATE(2026,1,1),"ym")&" bulan " -> 5 tahun 4 bulan | BX28: =VLOOKUP($B28,Sheet1!$A:$G,2,FALSE) -> STIKOM | BY28: =VLOOKUP($B28,Sheet1!$A:$G,3,FALSE) -> Teknik Komputer | BZ28: =VLOOKUP($B28,Sheet1!$A:$G,4,FALSE) -> ITS | CA28: =VLOOKUP($B28,Sheet1!$A:$G,5,FALSE) -> Teknik Elektro | CB28: =VLOOKUP($B28,Sheet1!$A:$G,6,FALSE) -> ITS | CC28: =VLOOKUP($B28,Sheet1!$A:$G,7,FALSE) -> Teknik Elektro | CD28: Motion Technology for Safety, Health, and Wellness | CE28: ETHES (Electrical Engineering and Advanced Technologies)
A29: 44 | B29: Ayu Endah Wahyuni | C29: Aktif | D29: Teknik Industri | E29: 23880010 | F29: 0401078801 | G29: 9033766667230323 | H29: TETAP | J29: S.T., M.T. | K29: L.2 | L29: L | M29: =IF(L29="NJAD","AA",IF(L29="AA","L",IF(L29="L","LK","GB"))) -> LK | N29: - | O29: 300 | P29: Organisasi dan Manajemen Perusahaan Industri, Manajemen SDM, Teknopreneur dan Perancangan Proses Bisnis | Q29: 45108 | R29: =DATEDIF(Q29,TODAY(), "Y") & " Tahun " & DATEDIF(Q29, TODAY(), "YM") & " Bulan" -> 2 Tahun 6 Bulan | S29: Penata Golongan III/c | T29: 45658 | U29: =DATEDIF(T29,TODAY(), "Y") & " Tahun " & DATEDIF(T29, TODAY(), "YM") & " Bulan" -> 1 Tahun 0 Bulan | V29: Kaprodi S1 Teknik Industri | W29: DOSEN | X29: =IF(AND(OR(L29="AA",L29="L"),OR(S29="Penata Muda Tk. I Golongan III/b",S29="Penata Golongan III/c"),DATEDIF(Q29,TODAY(),"m")>=23,ISBLANK(Z29),C29="Aktif"),"Nominasi Serdos","-") -> - | Z29: Punya | AA29: 18104103408060 | AB29: 1.8001e+15 | AC29: 43283 | AH29: S2 | AM29: 44013 | AN29: =DATEDIF(AM29,TODAY(),"y")&" tahun "&DATEDIF(AM29,TODAY(),"ym")&" bulan " -> 5 tahun 6 bulan | AO29: FTEIC | AP29: Program Studi S1 Teknik Industri (FTEIC) | AQ29: AYU | AR29: ayu.endah@ittelkom-sby.ac.id | AS29: 81395224118 | AT29: Jl. Guru Mughni, Kuningan Timur, Jakarta Selatan | AW29: =VLOOKUP(B29,Sheet2!A45:I162,9,FALSE) -> Ayu Endah Wahyuni, S.T., M.T. | AX29: Perempuan | AY29: =VLOOKUP(B29,Sheet2!A45:C162,2,FALSE) -> Denpasar | AZ29: =VLOOKUP(B29,Sheet2!A45:C162,3,FALSE) -> 32325 | BA29: =DATEDIF(AZ29, TODAY(),"y") -> 37 | BL29: =VLOOKUP(B29,Sheet2!A45:D162,4,FALSE) -> Kaprodi | BR29: =VLOOKUP(B29,Sheet2!A45:E162,5,FALSE) -> Engineering Management System | BS29: =VLOOKUP(B29,Sheet2!A45:F162,6,FALSE) -> AYV | BT29: =VLOOKUP(B29,Sheet2!A45:G162,7,FALSE) -> Fakultas Rekayasa Industri | BU29: =VLOOKUP(B29,Sheet2!A45:H162,8,FALSE) -> ayuendah@telkomuniversity.ac.id | BV29: =COUNTIFS('Join TPA Dosen'!B:B,Dosen!B6) -> 1 | BW29: =DATEDIF(AM29,DATE(2026,1,1),"y")&" tahun "&DATEDIF(AM29,DATE(2026,1,1),"ym")&" bulan " -> 5 tahun 6 bulan | BX29: =VLOOKUP($B29,Sheet1!$A:$G,2,FALSE) -> Tel-U | BY29: =VLOOKUP($B29,Sheet1!$A:$G,3,FALSE) -> Teknik Industri | BZ29: =VLOOKUP($B29,Sheet1!$A:$G,4,FALSE) -> ITB | CA29: =VLOOKUP($B29,Sheet1!$A:$G,5,FALSE) -> Teknik dan Manajemen Industri | CB29: =VLOOKUP($B29,Sheet1!$A:$G,6,FALSE) -> - | CC29: =VLOOKUP($B29,Sheet1!$A:$G,7,FALSE) -> 0 | CD29: Circular Ecosystem and Sustainable Technology | CE29: Rekayasa Industri dan Inovasi Bisnis (RIIB)
A30: 45 | B30: Muhamad Nasrullah | C30: Aktif | D30: Sistem Informasi | E30: 23900009 | F30: 0709059004 | G30: 3841768669130332 | H30: TETAP | J30: S.Kom., M.Kom. | K30: AA.2 | L30: AA | M30: =IF(L30="NJAD","AA",IF(L30="AA","L",IF(L30="L","LK","GB"))) -> L | N30: - | O30: 150 | P30: Sistem Enterprise, Jaringan Komputer dan Komunikasi Data, Arsitektur an Organisasi Komputer dan Sistem Operasi Komputer | Q30: 44743 | R30: =DATEDIF(Q30,TODAY(), "Y") & " Tahun " & DATEDIF(Q30, TODAY(), "YM") & " Bulan" -> 3 Tahun 6 Bulan | S30: Penata Muda Tk. I Golongan III/b | T30: 44896 | U30: =DATEDIF(T30,TODAY(), "Y") & " Tahun " & DATEDIF(T30, TODAY(), "YM") & " Bulan" -> 3 Tahun 1 Bulan | V30: Kabag Kemahasiswaan | W30: DOSEN | X30: =IF(AND(OR(L30="AA",L30="L"),OR(S30="Penata Muda Tk. I Golongan III/b",S30="Penata Golongan III/c"),DATEDIF(Q30,TODAY(),"m")>=23,ISBLANK(Z30),C30="Aktif"),"Nominasi Serdos","-") -> - | Z30: Punya | AA30: 25104105713091 | AB30: 25-005023-0038 | AC30: 45917 | AH30: S2 | AI30: Ya | AJ30: TB | AK30: Ya | AM30: 44075 | AN30: =DATEDIF(AM30,TODAY(),"y")&" tahun "&DATEDIF(AM30,TODAY(),"ym")&" bulan " -> 5 tahun 4 bulan | AO30: FTIB | AP30: Program Studi S1 Sistem Informasi (FTIB) | AQ30: NAS | AR30: emnasrul@ittelkom-sby.ac.id | AS30: 85259501314 | AT30: Dusun Kemuning RT. 03 RW. 05 Desa Menunggal Kecamatan Kedamean Kabupaten Gresik | AW30: =VLOOKUP(B30,Sheet2!A46:I163,9,FALSE) -> Muhamad Nasrullah, S.Kom., M.Kom. | AX30: Laki-laki | AY30: =VLOOKUP(B30,Sheet2!A46:C163,2,FALSE) -> Sidoarjo | AZ30: =VLOOKUP(B30,Sheet2!A46:C163,3,FALSE) -> 33002 | BA30: =DATEDIF(AZ30, TODAY(),"y") -> 35 | BL30: Dosen | BR30: =VLOOKUP(B30,Sheet2!A46:E163,5,FALSE) -> Enterprise and Industrial System (EINS) | BS30: =VLOOKUP(B30,Sheet2!A46:F163,6,FALSE) -> RLH | BT30: =VLOOKUP(B30,Sheet2!A46:G163,7,FALSE) -> Fakultas Rekayasa Industri | BU30: =VLOOKUP(B30,Sheet2!A46:H163,8,FALSE) -> emnasrul@telkomuniversity.ac.id | BV30: =COUNTIFS('Join TPA Dosen'!B:B,Dosen!B46) -> 1 | BW30: =DATEDIF(AM30,DATE(2026,1,1),"y")&" tahun "&DATEDIF(AM30,DATE(2026,1,1),"ym")&" bulan " -> 5 tahun 4 bulan | BX30: =VLOOKUP($B30,Sheet1!$A:$G,2,FALSE) -> ITS | BY30: =VLOOKUP($B30,Sheet1!$A:$G,3,FALSE) -> Sistem Informasi | BZ30: =VLOOKUP($B30,Sheet1!$A:$G,4,FALSE) -> ITS | CA30: =VLOOKUP($B30,Sheet1!$A:$G,5,FALSE) -> Sistem Informasi | CB30: =VLOOKUP($B30,Sheet1!$A:$G,6,FALSE) -> - | CC30: =VLOOKUP($B30,Sheet1!$A:$G,7,FALSE) -> 0 | CD30: Motion Technology for Safety, Health, and Wellness | CE30: Smart Computing Technology (SCOUT)
A31: 46 | B31: Sekar Widyasari Putri | C31: Aktif | D31: Digital Bisnis | E31: 24930005 | F31: 0704029302 | G31: 0536771672230252 | H31: TETAP | J31: S.A.B., M.Si. | K31: AA.2 | L31: AA | M31: =IF(L31="NJAD","AA",IF(L31="AA","L",IF(L31="L","LK","GB"))) -> L | N31: - | O31: 150 | P31: Etika Profesi, Manajemen Organisasi, Pengantar Manajemen Bisnis Digital dan Manajemen Hubungan Pelanggan | Q31: 44986 | R31: =DATEDIF(Q31,TODAY(), "Y") & " Tahun " & DATEDIF(Q31, TODAY(), "YM") & " Bulan" -> 2 Tahun 10 Bulan | S31: Penata Muda Tk. I Golongan III/b | T31: 45078 | U31: =DATEDIF(T31,TODAY(), "Y") & " Tahun " & DATEDIF(T31, TODAY(), "YM") & " Bulan" -> 2 Tahun 7 Bulan | V31: Kepala Urusan Pusat Bahasa | W31: DOSEN | X31: =IF(AND(OR(L31="AA",L31="L"),OR(S31="Penata Muda Tk. I Golongan III/b",S31="Penata Golongan III/c"),DATEDIF(Q31,TODAY(),"m")>=23,ISBLANK(Z31),C31="Aktif"),"Nominasi Serdos","-") -> Nominasi Serdos | Y31: On Progress | AC31: - | AH31: S2 | AM31: 44166 | AN31: =DATEDIF(AM31,TODAY(),"y")&" tahun "&DATEDIF(AM31,TODAY(),"ym")&" bulan " -> 5 tahun 1 bulan | AO31: FTIB | AP31: Program Studi S1 Digital Bisnis (FTIB) | AQ31: SWP | AR31: sekar@ittelkom-sby.ac.id | AS31: 81334448548 | AT31: Jl. Plamongan Indah Blok G3 No. 24, Batusari, Mranggen, Demak | AW31: =VLOOKUP(B31,Sheet2!A47:I164,9,FALSE) -> Sekar Widyasari Putri, S.A.B., M.Si. | AX31: Perempuan | AY31: =VLOOKUP(B31,Sheet2!A47:C164,2,FALSE) -> Semarang | AZ31: =VLOOKUP(B31,Sheet2!A47:C164,3,FALSE) -> 34061 | BA31: =DATEDIF(AZ31, TODAY(),"y") -> 32 | BL31: =VLOOKUP(B31,Sheet2!A47:D164,4,FALSE) -> Kepala Urusan | BR31: =VLOOKUP(B31,Sheet2!A47:E164,5,FALSE) -> Strategy, Human, Entrepreneurship & Economy (SHEE) | BS31: =VLOOKUP(B31,Sheet2!A47:F164,6,FALSE) -> SSQ | BT31: =VLOOKUP(B31,Sheet2!A47:G164,7,FALSE) -> Fakultas Ekonomi dan Bisnis | BU31: =VLOOKUP(B31,Sheet2!A47:H164,8,FALSE) -> sekarwidyasariputri@telkomuniversity.ac.id | BV31: =COUNTIFS('Join TPA Dosen'!B:B,Dosen!B47) -> 1 | BW31: =DATEDIF(AM31,DATE(2026,1,1),"y")&" tahun "&DATEDIF(AM31,DATE(2026,1,1),"ym")&" bulan " -> 5 tahun 1 bulan | BX31: =VLOOKUP($B31,Sheet1!$A:$G,2,FALSE) -> Undip | BY31: =VLOOKUP($B31,Sheet1!$A:$G,3,FALSE) -> Administrasi Bisnis | BZ31: =VLOOKUP($B31,Sheet1!$A:$G,4,FALSE) -> Undip | CA31: =VLOOKUP($B31,Sheet1!$A:$G,5,FALSE) -> Ilmu Sosial dan Politik/Ilmu Administrasi | CB31: =VLOOKUP($B31,Sheet1!$A:$G,6,FALSE) -> - | CC31: =VLOOKUP($B31,Sheet1!$A:$G,7,FALSE) -> 0 | CD31: Circular Ecosystem and Sustainable Technology | CE31: Rekayasa Industri dan Inovasi Bisnis (RIIB)
A32: 48 | B32: Ahmad Wali Satria Bahari Johan | C32: Aktif | D32: Informatika | E32: 25950031 | F32: 0713059501 | G32: 7845773674130212 | H32: TETAP | J32: S.ST., M.Kom. | K32: L.2 | L32: L | M32: LK | N32: - | O32: 200 | P32: Artificial Intelligence | Q32: 45901 | R32: =DATEDIF(Q32,TODAY(), "Y") & " Tahun " & DATEDIF(Q32, TODAY(), "YM") & " Bulan" -> 0 Tahun 4 Bulan | S32: Penata Golongan III/c | T32: 46023 | U32: =DATEDIF(T32,TODAY(), "Y") & " Tahun " & DATEDIF(T32, TODAY(), "YM") & " Bulan" -> 0 Tahun 0 Bulan | V32: Kepala Urusan Aktivitas Kemahasiswaan | W32: DOSEN | X32: =IF(AND(OR(L32="AA",L32="L"),OR(S32="Penata Muda Tk. I Golongan III/b",S32="Penata Golongan III/c"),DATEDIF(Q32,TODAY(),"m")>=23,ISBLANK(Z32),C32="Aktif"),"Nominasi Serdos","-") -> - | Y32: On Progress | AC32: - | AH32: S2 | AM32: 44166 | AN32: =DATEDIF(AM32,TODAY(),"y")&" tahun "&DATEDIF(AM32,TODAY(),"ym")&" bulan " -> 5 tahun 1 bulan | AO32: FTIB | AP32: Program Studi S1 Informatika (FTIB) | AQ32: AWS | AR32: ahmadsatria13@ittelkom-sby.ac.id | AS32: 82132194465 | AT32: Dsn. Bujel, Suwaloh, Balen, Bojonegoro | AW32: =VLOOKUP(B32,Sheet2!A49:I166,9,FALSE) -> Ahmad Wali Satria Bahari Johan, S.ST., M.Kom. | AX32: Laki-laki | AY32: =VLOOKUP(B32,Sheet2!A49:C166,2,FALSE) -> Bojonegoro | AZ32: =VLOOKUP(B32,Sheet2!A49:C166,3,FALSE) -> 34832 | BA32: =DATEDIF(AZ32, TODAY(),"y") -> 30 | BL32: Kabag | BR32: =VLOOKUP(B32,Sheet2!A49:E166,5,FALSE) -> Data Science and Intelligent Systems (DSIS) | BS32: =VLOOKUP(B32,Sheet2!A49:F166,6,FALSE) -> AWQ | BT32: =VLOOKUP(B32,Sheet2!A49:G166,7,FALSE) -> Fakultas Informatika | BU32: =VLOOKUP(B32,Sheet2!A49:H166,8,FALSE) -> ahmadsatria@telkomuniversity.ac.id | BV32: =COUNTIFS('Join TPA Dosen'!B:B,Dosen!B49) -> 1 | BW32: =DATEDIF(AM32,DATE(2026,1,1),"y")&" tahun "&DATEDIF(AM32,DATE(2026,1,1),"ym")&" bulan " -> 5 tahun 1 bulan | BX32: =VLOOKUP($B32,Sheet1!$A:$G,2,FALSE) -> POLINEMA | BY32: =VLOOKUP($B32,Sheet1!$A:$G,3,FALSE) -> Teknologi Informasi/Teknik Informatika | BZ32: =VLOOKUP($B32,Sheet1!$A:$G,4,FALSE) -> Univ. Brawijaya | CA32: =VLOOKUP($B32,Sheet1!$A:$G,5,FALSE) -> Ilmu Komputer/Ilmu Komputer | CB32: =VLOOKUP($B32,Sheet1!$A:$G,6,FALSE) -> - | CC32: =VLOOKUP($B32,Sheet1!$A:$G,7,FALSE) -> 0 | CD32: Intergrated and Embedded Systems | CE32: Smart Computing Technology (SCOUT)
A33: 49 | B33: Muhammad Dzulfikar Fauzi | C33: Aktif | D33: Informatika | E33: 25940031 | F33: 0711039403 | G33: 2643772673130292 | H33: TETAP | J33: S.Kom., M.Cs. | K33: L.2 | L33: L | M33: =IF(L33="NJAD","AA",IF(L33="AA","L",IF(L33="L","LK","GB"))) -> LK | N33: - | O33: 200 | P33: Rekayasa Perangkat Lunak : Capstone Project, Pemrograman Berbasis Objek, Pemrograman Integratif dan Pemrograman Web | Q33: 46023 | R33: =DATEDIF(Q33,TODAY(), "Y") & " Tahun " & DATEDIF(Q33, TODAY(), "YM") & " Bulan" -> 0 Tahun 0 Bulan | S33: Penata Muda Tk. I Golongan III/b | T33: 45505 | U33: =DATEDIF(T33,TODAY(), "Y") & " Tahun " & DATEDIF(T33, TODAY(), "YM") & " Bulan" -> 1 Tahun 5 Bulan | V33: Kaprodi S1 Informatika | W33: DOSEN | X33: =IF(AND(OR(L33="AA",L33="L"),OR(S33="Penata Muda Tk. I Golongan III/b",S33="Penata Golongan III/c"),DATEDIF(Q33,TODAY(),"m")>=23,ISBLANK(Z33),C33="Aktif"),"Nominasi Serdos","-") -> - | AC33: - | AH33: S2 | AM33: 44166 | AN33: =DATEDIF(AM33,TODAY(),"y")&" tahun "&DATEDIF(AM33,TODAY(),"ym")&" bulan " -> 5 tahun 1 bulan | AO33: FTIB | AP33: Program Studi S1 Informatika (FTIB) | AQ33: MDF | AR33: muhammad.dzulfikar.f@ittelkom-sby.ac.id | AS33: 85323076783 | AT33: Dsn. Kayen, Morosunggingan, Peterongan, Jombang | AW33: =VLOOKUP(B33,Sheet2!A50:I167,9,FALSE) -> Muhammad Dzulfikar Fauzi, S.Kom., M.Cs. | AX33: Laki-laki | AY33: =VLOOKUP(B33,Sheet2!A50:C167,2,FALSE) -> Jombang | AZ33: =VLOOKUP(B33,Sheet2!A50:C167,3,FALSE) -> 34641 | BA33: =DATEDIF(AZ33, TODAY(),"y") -> 31 | BL33: =VLOOKUP(B33,Sheet2!A50:D167,4,FALSE) -> Kaprodi | BR33: =VLOOKUP(B33,Sheet2!A50:E167,5,FALSE) -> Data Science and Intelligent Systems (DSIS) | BS33: =VLOOKUP(B33,Sheet2!A50:F167,6,FALSE) -> MDX | BT33: =VLOOKUP(B33,Sheet2!A50:G167,7,FALSE) -> Fakultas Informatika | BU33: =VLOOKUP(B33,Sheet2!A50:H167,8,FALSE) -> dzulfikarf@telkomuniversity.ac.id | BV33: =COUNTIFS('Join TPA Dosen'!B:B,Dosen!B50) -> 1 | BW33: =DATEDIF(AM33,DATE(2026,1,1),"y")&" tahun "&DATEDIF(AM33,DATE(2026,1,1),"ym")&" bulan " -> 5 tahun 1 bulan | BX33: =VLOOKUP($B33,Sheet1!$A:$G,2,FALSE) -> UIN JOGJA | BY33: =VLOOKUP($B33,Sheet1!$A:$G,3,FALSE) -> Teknik Informatika | BZ33: =VLOOKUP($B33,Sheet1!$A:$G,4,FALSE) -> UGM | CA33: =VLOOKUP($B33,Sheet1!$A:$G,5,FALSE) -> Matematika dan Ilmu Pengatahuan Alam/Ilmu Komputer | CB33: =VLOOKUP($B33,Sheet1!$A:$G,6,FALSE) -> - | CC33: =VLOOKUP($B33,Sheet1!$A:$G,7,FALSE) -> 0 | CD33: Motion Technology for Safety, Health, and Wellness | CE33: Smart Computing Technology (SCOUT)
A34: 50 | B34: Kharisma Monika Dian Pertiwi | C34: Aktif | D34: Informatika | E34: 23950024 | F34: 0706089501 | G34: 4138773674230223 | H34: TETAP | J34: S.Kom., M.Kom. | K34: AA.2 | L34: AA | M34: =IF(L34="NJAD","AA",IF(L34="AA","L",IF(L34="L","LK","GB"))) -> L | N34: - | O34: 150 | P34: Jaringan Komputer dan Komunikasi Data, Jaringan Komputer, Data Warehouse, Algoritma dan Struktur Data | Q34: 45047 | R34: =DATEDIF(Q34,TODAY(), "Y") & " Tahun " & DATEDIF(Q34, TODAY(), "YM") & " Bulan" -> 2 Tahun 8 Bulan | S34: Penata Muda Tk. I Golongan III/b | T34: 45170 | U34: =DATEDIF(T34,TODAY(), "Y") & " Tahun " & DATEDIF(T34, TODAY(), "YM") & " Bulan" -> 2 Tahun 4 Bulan | V34: Dosen S1 Informatika | W34: DOSEN | X34: =IF(AND(OR(L34="AA",L34="L"),OR(S34="Penata Muda Tk. I Golongan III/b",S34="Penata Golongan III/c"),DATEDIF(Q34,TODAY(),"m")>=23,ISBLANK(Z34),C34="Aktif"),"Nominasi Serdos","-") -> Nominasi Serdos | Y34: On Progress | AC34: - | AH34: S2 | AM34: 44166 | AN34: =DATEDIF(AM34,TODAY(),"y")&" tahun "&DATEDIF(AM34,TODAY(),"ym")&" bulan " -> 5 tahun 1 bulan | AO34: FTIB | AP34: Program Studi S1 Informatika (FTIB) | AQ34: KMD | AR34: kharismamonika@ittelkom-sby.ac.id | AS34: 81233777404 | AT34: Jl. YKP Pandugo 2F-4, Penjaringan Sari, Rungkut, Surabaya | AW34: =VLOOKUP(B34,Sheet2!A51:I168,9,FALSE) -> Kharisma Monika Dian Pertiwi, S.Kom., M.Kom. | AX34: Perempuan | AY34: =VLOOKUP(B34,Sheet2!A51:C168,2,FALSE) -> Madiun | AZ34: =VLOOKUP(B34,Sheet2!A51:C168,3,FALSE) -> 34858 | BA34: =DATEDIF(AZ34, TODAY(),"y") -> 30 | BL34: =VLOOKUP(B34,Sheet2!A51:D168,4,FALSE) -> Dosen | BR34: =VLOOKUP(B34,Sheet2!A51:E168,5,FALSE) -> Communication and Information Technology Infrastructure (CITI) | BS34: =VLOOKUP(B34,Sheet2!A51:F168,6,FALSE) -> KMP | BT34: =VLOOKUP(B34,Sheet2!A51:G168,7,FALSE) -> Fakultas Informatika | BU34: =VLOOKUP(B34,Sheet2!A51:H168,8,FALSE) -> kharismamonikadp@telkomuniversity.ac.id | BV34: =COUNTIFS('Join TPA Dosen'!B:B,Dosen!B51) -> 1 | BW34: =DATEDIF(AM34,DATE(2026,1,1),"y")&" tahun "&DATEDIF(AM34,DATE(2026,1,1),"ym")&" bulan " -> 5 tahun 1 bulan | BX34: =VLOOKUP($B34,Sheet1!$A:$G,2,FALSE) -> ITS | BY34: =VLOOKUP($B34,Sheet1!$A:$G,3,FALSE) -> Teknologi Informasi dan Komunikasi/Teknik Informatika | BZ34: =VLOOKUP($B34,Sheet1!$A:$G,4,FALSE) -> ITS | CA34: =VLOOKUP($B34,Sheet1!$A:$G,5,FALSE) -> Teknologi Elektro dan Informatika Cerdas/Teknik Informatika | CB34: =VLOOKUP($B34,Sheet1!$A:$G,6,FALSE) -> - | CC34: =VLOOKUP($B34,Sheet1!$A:$G,7,FALSE) -> 0 | CD34: Motion Technology for Safety, Health, and Wellness | CE34: Smart Computing Technology (SCOUT)
A35: 51 | B35: Rizky Fenaldo Maulana | C35: Aktif | D35: Informatika | E35: 25970012 | F35: 0714079701 | G35: 2046775676130173 | H35: TETAP | J35: S.Kom., M.Kom. | K35: AA.2 | L35: AA | M35: =IF(L35="NJAD","AA",IF(L35="AA","L",IF(L35="L","LK","GB"))) -> L | N35: - | O35: 150 | P35: Jaringan Komputer, Sistem Digital, Sistem Administrasi Server dan Pemrograman Integratif | Q35: 45108 | R35: =DATEDIF(Q35,TODAY(), "Y") & " Tahun " & DATEDIF(Q35, TODAY(), "YM") & " Bulan" -> 2 Tahun 6 Bulan | S35: Penata Muda Tk. I Golongan III/b | T35: 45505 | U35: =DATEDIF(T35,TODAY(), "Y") & " Tahun " & DATEDIF(T35, TODAY(), "YM") & " Bulan" -> 1 Tahun 5 Bulan | V35: Kabag Pusat Teknologi Informasi | W35: DOSEN | X35: =IF(AND(OR(L35="AA",L35="L"),OR(S35="Penata Muda Tk. I Golongan III/b",S35="Penata Golongan III/c"),DATEDIF(Q35,TODAY(),"m")>=23,ISBLANK(Z35),C35="Aktif"),"Nominasi Serdos","-") -> Nominasi Serdos | AC35: - | AH35: S2 | AM35: 44166 | AN35: =DATEDIF(AM35,TODAY(),"y")&" tahun "&DATEDIF(AM35,TODAY(),"ym")&" bulan " -> 5 tahun 1 bulan | AO35: FTIB | AP35: Program Studi S1 Informatika (FTIB) | AQ35: RFM | AR35: aldo@ittelkom-sby.ac.id | AS35: 81230777099 | AT35: Jl. Gajayana No. 796, Dinoyo, Lowokwaru, Malang | AW35: =VLOOKUP(B35,Sheet2!A52:I169,9,FALSE) -> Rizky Fenaldo Maulana, S.Kom., M.Kom. | AX35: Laki-laki | AY35: =VLOOKUP(B35,Sheet2!A52:C169,2,FALSE) -> Denpasar | AZ35: =VLOOKUP(B35,Sheet2!A52:C169,3,FALSE) -> 35625 | BA35: =DATEDIF(AZ35, TODAY(),"y") -> 28 | BL35: =VLOOKUP(B35,Sheet2!A52:D169,4,FALSE) -> Kabag | BR35: =VLOOKUP(B35,Sheet2!A52:E169,5,FALSE) -> Communication and Information Technology Infrastructure (CITI) | BS35: =VLOOKUP(B35,Sheet2!A52:F169,6,FALSE) -> RZO | BT35: =VLOOKUP(B35,Sheet2!A52:G169,7,FALSE) -> Fakultas Informatika | BU35: =VLOOKUP(B35,Sheet2!A52:H169,8,FALSE) -> rizkyfenaldo@telkomuniversity.ac.id | BV35: =COUNTIFS('Join TPA Dosen'!B:B,Dosen!B52) -> 1 | BW35: =DATEDIF(AM35,DATE(2026,1,1),"y")&" tahun "&DATEDIF(AM35,DATE(2026,1,1),"ym")&" bulan " -> 5 tahun 1 bulan | BX35: =VLOOKUP($B35,Sheet1!$A:$G,2,FALSE) -> ITS | BY35: =VLOOKUP($B35,Sheet1!$A:$G,3,FALSE) -> Teknologi Informasi dan Komunikasi/Teknik Informatika | BZ35: =VLOOKUP($B35,Sheet1!$A:$G,4,FALSE) -> ITS | CA35: =VLOOKUP($B35,Sheet1!$A:$G,5,FALSE) -> Teknologi Elektro dan Informatika Cerdas/Teknik Informatika | CB35: =VLOOKUP($B35,Sheet1!$A:$G,6,FALSE) -> - | CC35: =VLOOKUP($B35,Sheet1!$A:$G,7,FALSE) -> 0 | CD35: Intergrated and Embedded Systems | CE35: Smart Computing Technology (SCOUT)
A36: 52 | B36: Amalia Nur Alifah | C36: Aktif | D36: Sains Data | E36: 25940030 | F36: 0729129403 | G36: 1561772673230263 | H36: TETAP | J36: S.Si., M.Si. | K36: L.2 | L36: L | M36: =IF(L36="NJAD","AA",IF(L36="AA","L",IF(L36="L","LK","GB"))) -> LK | O36: 200 | P36: Logika Formal, Matriks dan Vektor, Teori Probabilitas dan Kriptografi | Q36: 46023 | R36: =DATEDIF(Q36,TODAY(), "Y") & " Tahun " & DATEDIF(Q36, TODAY(), "YM") & " Bulan" -> 0 Tahun 0 Bulan | S36: Penata Muda Tk. I Golongan III/b | T36: 45505 | U36: =DATEDIF(T36,TODAY(), "Y") & " Tahun " & DATEDIF(T36, TODAY(), "YM") & " Bulan" -> 1 Tahun 5 Bulan | V36: Dosen S1 Sains Data | W36: DOSEN | X36: =IF(AND(OR(L36="AA",L36="L"),OR(S36="Penata Muda Tk. I Golongan III/b",S36="Penata Golongan III/c"),DATEDIF(Q36,TODAY(),"m")>=23,ISBLANK(Z36),C36="Aktif"),"Nominasi Serdos","-") -> - | AC36: - | AH36: S2 | AM36: 44166 | AN36: =DATEDIF(AM36,TODAY(),"y")&" tahun "&DATEDIF(AM36,TODAY(),"ym")&" bulan " -> 5 tahun 1 bulan | AO36: FTIB | AP36: Program Studi S1 Sains Data (FTIB) | AQ36: ANA | AR36: amalialifah@ittelkom-sby.ac.id | AS36: 82229313437 | AT36: Jl. Gondangmanis, Gondangmanis, BAE, Kudus | AW36: =VLOOKUP(B36,Sheet2!A53:I170,9,FALSE) -> Amalia Nur Alifah, S.Si., M.Si. | AX36: Perempuan | AY36: =VLOOKUP(B36,Sheet2!A53:C170,2,FALSE) -> Kudus | AZ36: =VLOOKUP(B36,Sheet2!A53:C170,3,FALSE) -> 34697 | BA36: =DATEDIF(AZ36, TODAY(),"y") -> 31 | BL36: =VLOOKUP(B36,Sheet2!A53:D170,4,FALSE) -> Dosen | BR36: =VLOOKUP(B36,Sheet2!A53:E170,5,FALSE) -> Data Science and Intelligent Systems (DSIS) | BS36: =VLOOKUP(B36,Sheet2!A53:F170,6,FALSE) -> MAC | BT36: =VLOOKUP(B36,Sheet2!A53:G170,7,FALSE) -> Fakultas Informatika | BU36: =VLOOKUP(B36,Sheet2!A53:H170,8,FALSE) -> amalialifah@telkomuniversity.ac.id | BV36: =COUNTIFS('Join TPA Dosen'!B:B,Dosen!B53) -> 1 | BW36: =DATEDIF(AM36,DATE(2026,1,1),"y")&" tahun "&DATEDIF(AM36,DATE(2026,1,1),"ym")&" bulan " -> 5 tahun 1 bulan | BX36: =VLOOKUP($B36,Sheet1!$A:$G,2,FALSE) -> ITB | BY36: =VLOOKUP($B36,Sheet1!$A:$G,3,FALSE) -> Matematika dan Ilmu Pengatahuan Alam/Matematika | BZ36: =VLOOKUP($B36,Sheet1!$A:$G,4,FALSE) -> ITB | CA36: =VLOOKUP($B36,Sheet1!$A:$G,5,FALSE) -> Matematika dan Ilmu Pengatahuan Alam/Matematika | CB36: =VLOOKUP($B36,Sheet1!$A:$G,6,FALSE) -> - | CC36: =VLOOKUP($B36,Sheet1!$A:$G,7,FALSE) -> 0 | CD36: Circular Ecosystem and Sustainable Technology | CE36: Smart Computing Technology (SCOUT)
A37: 14 | B37: Mohammad Sholik | C37: Aktif | D37: Rekayasa Perangkat Lunak | E37: 19810001 | F37: 0709128101 | G37: 0541759660130163 | H37: TETAP | J37: S.Kom., M.Kom. | K37: AA.2 | L37: AA | M37: =IF(L37="NJAD","AA",IF(L37="AA","L",IF(L37="L","LK","GB"))) -> L | N37: - | O37: 150 | P37: Literasi Teknologi Inforomasi dan Komunikasi, Algoritma dan Struktur Data | Q37: 44081 | R37: =DATEDIF(Q37,TODAY(), "Y") & " Tahun " & DATEDIF(Q37, TODAY(), "YM") & " Bulan" -> 5 Tahun 4 Bulan | S37: Penata Muda Tk. I Golongan III/b | T37: 45078 | U37: =DATEDIF(T37,TODAY(), "Y") & " Tahun " & DATEDIF(T37, TODAY(), "YM") & " Bulan" -> 2 Tahun 7 Bulan | V37: Dosen S1 RPL | W37: DOSEN | X37: =IF(AND(OR(L37="AA",L37="L"),OR(S37="Penata Muda Tk. I Golongan III/b",S37="Penata Golongan III/c"),DATEDIF(Q37,TODAY(),"m")>=23,ISBLANK(Z37),C37="Aktif"),"Nominasi Serdos","-") -> - | Z37: Punya | AA37: 25104105710540 | AB37: 25-002001-0044 | AC37: 45917 | AH37: S2 | AI37: Ya | AJ37: TB | AK37: Ya | AL37: On Progress S3 TB | AM37: 43101 | AN37: =DATEDIF(AM37,TODAY(),"y")&" tahun "&DATEDIF(AM37,TODAY(),"ym")&" bulan " -> 8 tahun 0 bulan | AO37: FTIB | AP37: Program Studi S1 RPL (FTIB) | AQ37: MSK | AR37: mohammad.sholik@ittelkom-sby.ac.id | AS37: 811324984 | AT37: LOWAYU, RT. 029 RW. 008, DUKUN, GRESIK 61155 | AW37: =VLOOKUP(B37,Sheet2!A15:I132,9,FALSE) -> Mohammad Sholik, S.Kom., M.Kom. | AX37: Laki-laki | AY37: =VLOOKUP(B37,Sheet2!A15:C132,2,FALSE) -> Gresik | AZ37: =VLOOKUP(B37,Sheet2!A15:C132,3,FALSE) -> 29929 | BA37: =DATEDIF(AZ37, TODAY(),"y") -> 44 | BL37: =VLOOKUP(B37,Sheet2!A15:D132,4,FALSE) -> Dosen | BR37: =VLOOKUP(B37,Sheet2!A15:E132,5,FALSE) -> Data Science and Intelligent Systems (DSIS) | BS37: =VLOOKUP(B37,Sheet2!A15:F132,6,FALSE) -> HHH | BT37: =VLOOKUP(B37,Sheet2!A15:G132,7,FALSE) -> Fakultas Informatika | BU37: =VLOOKUP(B37,Sheet2!A15:H132,8,FALSE) -> mohammadsholik@telkomuniversity.ac.id | BV37: =COUNTIFS('Join TPA Dosen'!B:B,Dosen!B15) -> 1 | BW37: =DATEDIF(AM37,DATE(2026,1,1),"y")&" tahun "&DATEDIF(AM37,DATE(2026,1,1),"ym")&" bulan " -> 8 tahun 0 bulan | BX37: =VLOOKUP($B37,Sheet1!$A:$G,2,FALSE) -> UNTAG | BY37: =VLOOKUP($B37,Sheet1!$A:$G,3,FALSE) -> Teknik Informatika | BZ37: =VLOOKUP($B37,Sheet1!$A:$G,4,FALSE) -> ITS | CA37: =VLOOKUP($B37,Sheet1!$A:$G,5,FALSE) -> Teknik Informatika | CB37: =VLOOKUP($B37,Sheet1!$A:$G,6,FALSE) -> ITS | CC37: =VLOOKUP($B37,Sheet1!$A:$G,7,FALSE) -> Ilmu Komputer | CD37: Motion Technology for Safety, Health, and Wellness | CE37: Smart Computing Technology (SCOUT)
A38: 27 | B38: Billy Montolalu | C38: Aktif | D38: Rekayasa Perangkat Lunak | E38: 20870004 | F38: 0729088704 | G38: 9160765666137003 | H38: TETAP | J38: S.Kom., M.Kom. | K38: AA.2 | L38: AA | M38: =IF(L38="NJAD","AA",IF(L38="AA","L",IF(L38="L","LK","GB"))) -> L | N38: - | O38: 150 | P38: Kalkulus 1A, Algoritma dan Pemrograman Dasar | Q38: 44007 | R38: =DATEDIF(Q38,TODAY(), "Y") & " Tahun " & DATEDIF(Q38, TODAY(), "YM") & " Bulan" -> 5 Tahun 6 Bulan | S38: Penata Muda Tk. I Golongan III/b | T38: 44075 | U38: =DATEDIF(T38,TODAY(), "Y") & " Tahun " & DATEDIF(T38, TODAY(), "YM") & " Bulan" -> 5 Tahun 4 Bulan | V38: Dosen S1 RPL | W38: DOSEN | X38: =IF(AND(OR(L38="AA",L38="L"),OR(S38="Penata Muda Tk. I Golongan III/b",S38="Penata Golongan III/c"),DATEDIF(Q38,TODAY(),"m")>=23,ISBLANK(Z38),C38="Aktif"),"Nominasi Serdos","-") -> - | Z38: Punya | AA38: 22107201905478 | AB38: 22-001025-0480 | AC38: 44846 | AH38: S2 | AI38: Ya | AJ38: TB | AK38: Ya | AL38: On Progress S3 TB | AM38: 43282 | AN38: =DATEDIF(AM38,TODAY(),"y")&" tahun "&DATEDIF(AM38,TODAY(),"ym")&" bulan " -> 7 tahun 6 bulan | AO38: FTIB | AP38: Program Studi S1 RPL (FTIB) | AQ38: BLM | AR38: billy@ittelkom-sby.ac.id | AS38: 85233310837 | AT38: DSN. KRAJAN RT 19 RW 5, YOSOWILANGUN LOR, LUMAJANG | AW38: =VLOOKUP(B38,Sheet2!A28:I145,9,FALSE) -> Billy Montolalu, S.Kom., M.Kom. | AX38: Laki-laki | AY38: =VLOOKUP(B38,Sheet2!A28:C145,2,FALSE) -> Lumajang | AZ38: =VLOOKUP(B38,Sheet2!A28:C145,3,FALSE) -> 32017 | BA38: =DATEDIF(AZ38, TODAY(),"y") -> 38 | BL38: =VLOOKUP(B38,Sheet2!A28:D145,4,FALSE) -> Dosen | BR38: =VLOOKUP(B38,Sheet2!A28:E145,5,FALSE) -> Software Engineering and Algorithm (SEAL) | BS38: =VLOOKUP(B38,Sheet2!A28:F145,6,FALSE) -> BLM | BT38: =VLOOKUP(B38,Sheet2!A28:G145,7,FALSE) -> Fakultas Informatika | BU38: =VLOOKUP(B38,Sheet2!A28:H145,8,FALSE) -> billymontolalu@telkomuniversity.ac.id | BV38: =COUNTIFS('Join TPA Dosen'!B:B,Dosen!B10) -> 1 | BW38: =DATEDIF(AM38,DATE(2026,1,1),"y")&" tahun "&DATEDIF(AM38,DATE(2026,1,1),"ym")&" bulan " -> 7 tahun 6 bulan | BX38: =VLOOKUP($B38,Sheet1!$A:$G,2,FALSE) -> ITS | BY38: =VLOOKUP($B38,Sheet1!$A:$G,3,FALSE) -> Teknik Informatika | BZ38: =VLOOKUP($B38,Sheet1!$A:$G,4,FALSE) -> ITS | CA38: =VLOOKUP($B38,Sheet1!$A:$G,5,FALSE) -> Teknik Informatika | CB38: =VLOOKUP($B38,Sheet1!$A:$G,6,FALSE) -> ITS | CC38: =VLOOKUP($B38,Sheet1!$A:$G,7,FALSE) -> Ilmu Komputer | CD38: Intergrated and Embedded Systems | CE38: Smart Computing Technology (SCOUT)
A39: 56 | B39: Desita Nur Rachmaniar | C39: Aktif | D39: Teknik Logistik | E39: 25930030 | F39: 0707029303 | G39: 5539771672230282 | H39: TETAP | J39: S.T., M.Sc. | K39: AA.2 | L39: AA | M39: =IF(L39="NJAD","AA",IF(L39="AA","L",IF(L39="L","LK","GB"))) -> L | N39: - | O39: 150 | P39: Penelitian Operasional 1, Manajemen Proyek, Sistem Produksi dan Kewirausahaan | Q39: 45108 | R39: =DATEDIF(Q39,TODAY(), "Y") & " Tahun " & DATEDIF(Q39, TODAY(), "YM") & " Bulan" -> 2 Tahun 6 Bulan | S39: Penata Muda Tk. I Golongan III/b | T39: 45505 | U39: =DATEDIF(T39,TODAY(), "Y") & " Tahun " & DATEDIF(T39, TODAY(), "YM") & " Bulan" -> 1 Tahun 5 Bulan | V39: Dosen S1 Teknik Logistik | W39: DOSEN | X39: =IF(AND(OR(L39="AA",L39="L"),OR(S39="Penata Muda Tk. I Golongan III/b",S39="Penata Golongan III/c"),DATEDIF(Q39,TODAY(),"m")>=23,ISBLANK(Z39),C39="Aktif"),"Nominasi Serdos","-") -> Nominasi Serdos | AC39: - | AH39: S2 | AM39: 44166 | AN39: =DATEDIF(AM39,TODAY(),"y")&" tahun "&DATEDIF(AM39,TODAY(),"ym")&" bulan " -> 5 tahun 1 bulan | AO39: FTEIC | AP39: Program Studi S1 Teknik Logistik (FTEIC) | AQ39: DNR | AR39: desitanurr@ittelkom-sby.ac.id | AS39: 8113770702 | AT39: Jl. Jomegatan, Ngestiharjo, Kasihan, Bantul | AW39: =VLOOKUP(B39,Sheet2!A57:I174,9,FALSE) -> Desita Nur Rachmaniar, S.T., M.Sc. | AX39: Perempuan | AY39: =VLOOKUP(B39,Sheet2!A57:C174,2,FALSE) -> Bantul | AZ39: =VLOOKUP(B39,Sheet2!A57:C174,3,FALSE) -> 34152 | BA39: =DATEDIF(AZ39, TODAY(),"y") -> 32 | BL39: =VLOOKUP(B39,Sheet2!A57:D174,4,FALSE) -> Dosen | BR39: =VLOOKUP(B39,Sheet2!A57:E174,5,FALSE) -> Enterprise and Industrial System (EINS) | BS39: =VLOOKUP(B39,Sheet2!A57:F174,6,FALSE) -> DEZ | BT39: =VLOOKUP(B39,Sheet2!A57:G174,7,FALSE) -> Fakultas Rekayasa Industri | BU39: =VLOOKUP(B39,Sheet2!A57:H174,8,FALSE) -> desitanurr@telkomuniversity.ac.id | BV39: =COUNTIFS('Join TPA Dosen'!B:B,Dosen!B57) -> 1 | BW39: =DATEDIF(AM39,DATE(2026,1,1),"y")&" tahun "&DATEDIF(AM39,DATE(2026,1,1),"ym")&" bulan " -> 5 tahun 1 bulan | BX39: =VLOOKUP($B39,Sheet1!$A:$G,2,FALSE) -> Univ. Brawijaya | BY39: =VLOOKUP($B39,Sheet1!$A:$G,3,FALSE) -> Teknik/Teknik Industri | BZ39: =VLOOKUP($B39,Sheet1!$A:$G,4,FALSE) -> UGM | CA39: =VLOOKUP($B39,Sheet1!$A:$G,5,FALSE) -> Teknik/Teknik Industri | CB39: =VLOOKUP($B39,Sheet1!$A:$G,6,FALSE) -> - | CC39: =VLOOKUP($B39,Sheet1!$A:$G,7,FALSE) -> 0 | CD39: Circular Ecosystem and Sustainable Technology | CE39: Rekayasa Industri dan Inovasi Bisnis (RIIB)
A40: 57 | B40: Granita Hajar | C40: Aktif | D40: Teknik Logistik | E40: 24950003 | F40: 0723079501 | G40: 8055773674230213 | H40: TETAP | J40: S.T., M.T. | K40: L.2 | L40: L | M40: =IF(L40="NJAD","AA",IF(L40="AA","L",IF(L40="L","LK","GB"))) -> LK | N40: - | O40: 200 | P40: Manajemen Logistik, Manajemen Lean dan Logistik, Organisasi Manajemen dan Perusahaan dan Industri, Kewirausahaan | Q40: 46023 | R40: =DATEDIF(Q40,TODAY(), "Y") & " Tahun " & DATEDIF(Q40, TODAY(), "YM") & " Bulan" -> 0 Tahun 0 Bulan | S40: Penata Muda Tk. I Golongan III/b | T40: 45017 | U40: =DATEDIF(T40,TODAY(), "Y") & " Tahun " & DATEDIF(T40, TODAY(), "YM") & " Bulan" -> 2 Tahun 9 Bulan | V40: Dosen S1 Teknik Logistik | W40: DOSEN | X40: =IF(AND(OR(L40="AA",L40="L"),OR(S40="Penata Muda Tk. I Golongan III/b",S40="Penata Golongan III/c"),DATEDIF(Q40,TODAY(),"m")>=23,ISBLANK(Z40),C40="Aktif"),"Nominasi Serdos","-") -> - | Z40: Punya | AA40: 25104105713495 | AB40: 25-002001-0581 | AC40: 45917 | AH40: S2 | AM40: 44166 | AN40: =DATEDIF(AM40,TODAY(),"y")&" tahun "&DATEDIF(AM40,TODAY(),"ym")&" bulan " -> 5 tahun 1 bulan | AO40: FTEIC | AP40: Program Studi S1 Teknik Logistik (FTEIC) | AQ40: GRA | AR40: granita@ittelkom-sby.ac.id | AS40: 82143305935 | AT40: Jl. Jetis Kulon 1-A/21, Wonokromo, Surabaya | AW40: =VLOOKUP(B40,Sheet2!A58:I175,9,FALSE) -> Granita Hajar, S.T., M.T. | AX40: Perempuan | AY40: =VLOOKUP(B40,Sheet2!A58:C175,2,FALSE) -> Surabaya | AZ40: =VLOOKUP(B40,Sheet2!A58:C175,3,FALSE) -> 34903 | BA40: =DATEDIF(AZ40, TODAY(),"y") -> 30 | BL40: =VLOOKUP(B40,Sheet2!A58:D175,4,FALSE) -> Dosen | BR40: =VLOOKUP(B40,Sheet2!A58:E175,5,FALSE) -> Enterprise and Industrial System (EINS) | BS40: =VLOOKUP(B40,Sheet2!A58:F175,6,FALSE) -> GRN | BT40: =VLOOKUP(B40,Sheet2!A58:G175,7,FALSE) -> Fakultas Rekayasa Industri | BU40: =VLOOKUP(B40,Sheet2!A58:H175,8,FALSE) -> granita@telkomuniversity.ac.id | BV40: =COUNTIFS('Join TPA Dosen'!B:B,Dosen!B58) -> 1 | BW40: =DATEDIF(AM40,DATE(2026,1,1),"y")&" tahun "&DATEDIF(AM40,DATE(2026,1,1),"ym")&" bulan " -> 5 tahun 1 bulan | BX40: =VLOOKUP($B40,Sheet1!$A:$G,2,FALSE) -> UBAYA | BY40: =VLOOKUP($B40,Sheet1!$A:$G,3,FALSE) -> Teknik/Teknik Industri | BZ40: =VLOOKUP($B40,Sheet1!$A:$G,4,FALSE) -> ITS | CA40: =VLOOKUP($B40,Sheet1!$A:$G,5,FALSE) -> Teknologi Industri dan Rekayasa Sistem/Teknik Industri | CB40: =VLOOKUP($B40,Sheet1!$A:$G,6,FALSE) -> - | CC40: =VLOOKUP($B40,Sheet1!$A:$G,7,FALSE) -> 0 | CD40: Circular Ecosystem and Sustainable Technology | CE40: Rekayasa Industri dan Inovasi Bisnis (RIIB)
A41: 58 | B41: Nisa Isrofi | C41: Aktif | D41: Teknik Logistik | E41: 25930031 | F41: 0712059303 | G41: 5844771672230322 | H41: TETAP | J41: S.T., M.T. | K41: AA.2 | L41: AA | M41: =IF(L41="NJAD","AA",IF(L41="AA","L",IF(L41="L","LK","GB"))) -> L | N41: - | O41: 150 | P41: Perancangan Tata Letak Fasilitas, Organisasi Manajemen Perusahaan dan Industri, Matriks dan Vektor, Teori Probabilitas | Q41: 45108 | R41: =DATEDIF(Q41,TODAY(), "Y") & " Tahun " & DATEDIF(Q41, TODAY(), "YM") & " Bulan" -> 2 Tahun 6 Bulan | S41: Penata Muda Tk. I Golongan III/b | T41: 45505 | U41: =DATEDIF(T41,TODAY(), "Y") & " Tahun " & DATEDIF(T41, TODAY(), "YM") & " Bulan" -> 1 Tahun 5 Bulan | V41: Kaprodi S1 Teknik Logistik | W41: DOSEN | X41: =IF(AND(OR(L41="AA",L41="L"),OR(S41="Penata Muda Tk. I Golongan III/b",S41="Penata Golongan III/c"),DATEDIF(Q41,TODAY(),"m")>=23,ISBLANK(Z41),C41="Aktif"),"Nominasi Serdos","-") -> Nominasi Serdos | AC41: - | AH41: S2 | AM41: 44166 | AN41: =DATEDIF(AM41,TODAY(),"y")&" tahun "&DATEDIF(AM41,TODAY(),"ym")&" bulan " -> 5 tahun 1 bulan | AO41: FTEIC | AP41: Program Studi S1 Teknik Logistik (FTEIC) | AQ41: NIS | AR41: nisa.isrofi@ittelkom-sby.ac.id | AS41: 81331292077 | AT41: Jl. Pemenang IV Gang Masjid 1, Sukorejo, Ngasem, Kediri | AW41: =VLOOKUP(B41,Sheet2!A59:I176,9,FALSE) -> Nisa Isrofi, S.T., M.T. | AX41: Perempuan | AY41: =VLOOKUP(B41,Sheet2!A59:C176,2,FALSE) -> Kediri | AZ41: =VLOOKUP(B41,Sheet2!A59:C176,3,FALSE) -> 34308 | BA41: =DATEDIF(AZ41, TODAY(),"y") -> 32 | BL41: =VLOOKUP(B41,Sheet2!A59:D176,4,FALSE) -> Kaprodi | BR41: =VLOOKUP(B41,Sheet2!A59:E176,5,FALSE) -> Enterprise and Industrial System (EINS) | BS41: =VLOOKUP(B41,Sheet2!A59:F176,6,FALSE) -> NSX | BT41: =VLOOKUP(B41,Sheet2!A59:G176,7,FALSE) -> Fakultas Rekayasa Industri | BU41: =VLOOKUP(B41,Sheet2!A59:H176,8,FALSE) -> nisaisrofi@telkomuniversity.ac.id | BV41: =COUNTIFS('Join TPA Dosen'!B:B,Dosen!B59) -> 1 | BW41: =DATEDIF(AM41,DATE(2026,1,1),"y")&" tahun "&DATEDIF(AM41,DATE(2026,1,1),"ym")&" bulan " -> 5 tahun 1 bulan | BX41: =VLOOKUP($B41,Sheet1!$A:$G,2,FALSE) -> Univ. Brawijaya | BY41: =VLOOKUP($B41,Sheet1!$A:$G,3,FALSE) -> Teknik/Teknik Industri | BZ41: =VLOOKUP($B41,Sheet1!$A:$G,4,FALSE) -> ITS | CA41: =VLOOKUP($B41,Sheet1!$A:$G,5,FALSE) -> Teknologi Industri/Teknik Industri | CB41: =VLOOKUP($B41,Sheet1!$A:$G,6,FALSE) -> - | CC41: =VLOOKUP($B41,Sheet1!$A:$G,7,FALSE) -> 0 | CD41: Circular Ecosystem and Sustainable Technology | CE41: Rekayasa Industri dan Inovasi Bisnis (RIIB) | CF41: 45748
A42: 59 | B42: Fannush Shofi Akbar | C42: Aktif | D42: Teknik Telekomunikasi | E42: 25910023 | F42: 0722119101 | G42: 0454769670130263 | H42: TETAP | I42: Dr. | J42: S.ST. | K42: L.3 | L42: L | M42: =IF(L42="NJAD","AA",IF(L42="AA","L",IF(L42="L","LK","GB"))) -> LK | N42: - | O42: 200 | P42: Antena dan Propagasi, Elektromagnetika, Elektromagnetika Telekomunikasi dan Rekayasa Antena | Q42: 45108 | R42: =DATEDIF(Q42,TODAY(), "Y") & " Tahun " & DATEDIF(Q42, TODAY(), "YM") & " Bulan" -> 2 Tahun 6 Bulan | S42: Penata Golongan III/c | T42: 45505 | U42: =DATEDIF(T42,TODAY(), "Y") & " Tahun " & DATEDIF(T42, TODAY(), "YM") & " Bulan" -> 1 Tahun 5 Bulan | V42: Kaprodi S1 T. Telekomunikasi | W42: DOSEN | X42: =IF(AND(OR(L42="AA",L42="L"),OR(S42="Penata Muda Tk. I Golongan III/b",S42="Penata Golongan III/c"),DATEDIF(Q42,TODAY(),"m")>=23,ISBLANK(Z42),C42="Aktif"),"Nominasi Serdos","-") -> Nominasi Serdos | AC42: - | AH42: S3 | AM42: 43885 | AN42: =DATEDIF(AM42,TODAY(),"y")&" tahun "&DATEDIF(AM42,TODAY(),"ym")&" bulan " -> 5 tahun 10 bulan | AO42: FTEIC | AP42: Program Studi S1 T. Telekomunikasi (FTEIC) | AQ42: FSA | AR42: fannush.akbar@ittelkom-sby.ac.id | AS42: 81333391371 | AT42: Bendulmersi Besar Selatan 85, Surabaya | AW42: =VLOOKUP(B42,Sheet2!A60:I177,9,FALSE) -> Dr. Fannush Shofi Akbar, S.ST. | AX42: Laki-laki | AY42: =VLOOKUP(B42,Sheet2!A60:C177,2,FALSE) -> Surabaya | AZ42: =VLOOKUP(B42,Sheet2!A60:C177,3,FALSE) -> 33564 | BA42: =DATEDIF(AZ42, TODAY(),"y") -> 34 | BL42: =VLOOKUP(B42,Sheet2!A60:D177,4,FALSE) -> Kaprodi | BR42: =VLOOKUP(B42,Sheet2!A60:E177,5,FALSE) -> Intelligent Communications and Networks (ICON) | BS42: =VLOOKUP(B42,Sheet2!A60:F177,6,FALSE) -> FSX | BT42: =VLOOKUP(B42,Sheet2!A60:G177,7,FALSE) -> Fakultas Teknik Elektro | BU42: =VLOOKUP(B42,Sheet2!A60:H177,8,FALSE) -> fannushakbar@telkomuniversity.ac.id | BV42: =COUNTIFS('Join TPA Dosen'!B:B,Dosen!B60) -> 1 | BW42: =DATEDIF(AM42,DATE(2026,1,1),"y")&" tahun "&DATEDIF(AM42,DATE(2026,1,1),"ym")&" bulan " -> 5 tahun 10 bulan | BX42: =VLOOKUP($B42,Sheet1!$A:$G,2,FALSE) -> PENS | BY42: =VLOOKUP($B42,Sheet1!$A:$G,3,FALSE) -> Teknik Telekomunikasi | BZ42: =VLOOKUP($B42,Sheet1!$A:$G,4,FALSE) -> ITS | CA42: =VLOOKUP($B42,Sheet1!$A:$G,5,FALSE) -> Teknik Elektro | CB42: =VLOOKUP($B42,Sheet1!$A:$G,6,FALSE) -> ITS | CC42: =VLOOKUP($B42,Sheet1!$A:$G,7,FALSE) -> Teknik Elektro | CD42: Motion Technology for Safety, Health, and Wellness | CE42: ETHES (Electrical Engineering and Advanced Technologies)
A43: 61 | B43: Aris Kusumawati | C43: Aktif | D43: Sistem Informasi | E43: 21890010 | F43: 0720088905 | G43: 6152767668230373 | H43: PROFESIONAL | J43: S.Kom., M.Kom. | K43: AA.2 | L43: AA | M43: =IF(L43="NJAD","AA",IF(L43="AA","L",IF(L43="L","LK","GB"))) -> L | O43: 150 | P43: Manajemen Layanan, Rekayasa Proses Bisnis, Tata Kelola Si-ti | Q43: 45870 | R43: =DATEDIF(Q43,TODAY(), "Y") & " Tahun " & DATEDIF(Q43, TODAY(), "YM") & " Bulan" -> 0 Tahun 5 Bulan | S43: Penata Muda Tk. I Golongan III/b | T43: 45931 | U43: =DATEDIF(T43,TODAY(), "Y") & " Tahun " & DATEDIF(T43, TODAY(), "YM") & " Bulan" -> 0 Tahun 3 Bulan | V43: Dosen S1 Sistem Informasi | W43: DOSEN | X43: =IF(AND(OR(L43="AA",L43="L"),OR(S43="Penata Muda Tk. I Golongan III/b",S43="Penata Golongan III/c"),DATEDIF(Q43,TODAY(),"m")>=23,ISBLANK(Z43),C43="Aktif"),"Nominasi Serdos","-") -> - | AC43: - | AH43: S2 | AM43: 44470 | AN43: =DATEDIF(AM43,TODAY(),"y")&" tahun "&DATEDIF(AM43,TODAY(),"ym")&" bulan " -> 4 tahun 3 bulan | AO43: FTIB | AP43: Program Studi S1 Sistem Informasi (FTIB) | AQ43: ARS | AR43: arisk@ittelkom-sby.ac.id | AS43: 81330823998 | AT43: Jl. Sunan Giri Gg. Beringin Jaya No 11, Lamongan | AW43: =VLOOKUP(B43,Sheet2!A62:I179,9,FALSE) -> Aris Kusumawati, S.Kom., M.Kom. | AX43: Perempuan | AY43: =VLOOKUP(B43,Sheet2!A62:C179,2,FALSE) -> Lamongan | AZ43: =VLOOKUP(B43,Sheet2!A62:C179,3,FALSE) -> 32740 | BA43: =DATEDIF(AZ43, TODAY(),"y") -> 36 | BL43: =VLOOKUP(B43,Sheet2!A62:D179,4,FALSE) -> Dosen | BR43: =VLOOKUP(B43,Sheet2!A62:E179,5,FALSE) -> Enterprise and Industrial System (EINS) | BS43: =VLOOKUP(B43,Sheet2!A62:F179,6,FALSE) -> KUZ | BT43: =VLOOKUP(B43,Sheet2!A62:G179,7,FALSE) -> Fakultas Rekayasa Industri | BU43: =VLOOKUP(B43,Sheet2!A62:H179,8,FALSE) -> ariskusumawati@telkomuniversity.ac.id | BV43: =COUNTIFS('Join TPA Dosen'!B:B,Dosen!B62) -> 1 | BW43: =DATEDIF(AM43,DATE(2026,1,1),"y")&" tahun "&DATEDIF(AM43,DATE(2026,1,1),"ym")&" bulan " -> 4 tahun 3 bulan | BX43: =VLOOKUP($B43,Sheet1!$A:$G,2,FALSE) -> ITS | BY43: =VLOOKUP($B43,Sheet1!$A:$G,3,FALSE) -> Sistem Informasi | BZ43: =VLOOKUP($B43,Sheet1!$A:$G,4,FALSE) -> ITS | CA43: =VLOOKUP($B43,Sheet1!$A:$G,5,FALSE) -> Sistem Informasi | CB43: =VLOOKUP($B43,Sheet1!$A:$G,6,FALSE) -> - | CC43: =VLOOKUP($B43,Sheet1!$A:$G,7,FALSE) -> 0 | CD43: Motion Technology for Safety, Health, and Wellness | CE43: Rekayasa Industri dan Inovasi Bisnis (RIIB)
A44: 62 | B44: Mochamad Nizar Palefi Ma'ady | C44: Aktif | D44: Sistem Informasi | E44: 21910012 | F44: 0708119103 | G44: 7440769670130263 | H44: PROFESIONAL | J44: S.Kom., M.Kom., M.IM | K44: AA.2 | L44: AA | M44: =IF(L44="NJAD","AA",IF(L44="AA","L",IF(L44="L","LK","GB"))) -> L | N44: - | O44: 150 | P44: Analisis dan Perancangan Sistem Informasi, Data Mining, Algoritma dan Pemrograman | Q44: 45444 | R44: =DATEDIF(Q44,TODAY(), "Y") & " Tahun " & DATEDIF(Q44, TODAY(), "YM") & " Bulan" -> 1 Tahun 7 Bulan | S44: Penata Muda Tk. I Golongan III/b | T44: 45717 | U44: =DATEDIF(T44,TODAY(), "Y") & " Tahun " & DATEDIF(T44, TODAY(), "YM") & " Bulan" -> 0 Tahun 10 Bulan | V44: Sekretaris Prodi S1 Sistem Informasi | W44: DOSEN | X44: =IF(AND(OR(L44="AA",L44="L"),OR(S44="Penata Muda Tk. I Golongan III/b",S44="Penata Golongan III/c"),DATEDIF(Q44,TODAY(),"m")>=23,ISBLANK(Z44),C44="Aktif"),"Nominasi Serdos","-") -> - | AC44: - | AH44: S2 | AM44: 44562 | AN44: =DATEDIF(AM44,TODAY(),"y")&" tahun "&DATEDIF(AM44,TODAY(),"ym")&" bulan " -> 4 tahun 0 bulan | AO44: FTIB | AP44: Program Studi S1 Sistem Informasi (FTIB) | AQ44: MNP | AR44: nizar@ittelkom-sby.ac.id | AS44: 8123122708 | AT44: Jl. Taman Mulyosari Utara No. 21, Surabaya | AW44: =VLOOKUP(B44,Sheet2!A63:I180,9,FALSE) -> Mochamad Nizar Palefi Ma'ady, S.Kom., M.Kom., M.IM. | AX44: Laki-laki | AY44: =VLOOKUP(B44,Sheet2!A63:C180,2,FALSE) -> Bojonegoro | AZ44: =VLOOKUP(B44,Sheet2!A63:C180,3,FALSE) -> 33550 | BA44: =DATEDIF(AZ44, TODAY(),"y") -> 34 | BL44: Koordinator KK | BR44: =VLOOKUP(B44,Sheet2!A63:E180,5,FALSE) -> Cybernetics | BS44: =VLOOKUP(B44,Sheet2!A63:F180,6,FALSE) -> NZR | BT44: =VLOOKUP(B44,Sheet2!A63:G180,7,FALSE) -> Fakultas Rekayasa Industri | BU44: =VLOOKUP(B44,Sheet2!A63:H180,8,FALSE) -> mnizarpm@telkomuniversity.ac.id | BV44: =COUNTIFS('Join TPA Dosen'!B:B,Dosen!B63) -> 1 | BW44: =DATEDIF(AM44,DATE(2026,1,1),"y")&" tahun "&DATEDIF(AM44,DATE(2026,1,1),"ym")&" bulan " -> 4 tahun 0 bulan | BX44: =VLOOKUP($B44,Sheet1!$A:$G,2,FALSE) -> ITS | BY44: =VLOOKUP($B44,Sheet1!$A:$G,3,FALSE) -> Sistem Informasi | BZ44: =VLOOKUP($B44,Sheet1!$A:$G,4,FALSE) -> ITS & NTUST | CA44: =VLOOKUP($B44,Sheet1!$A:$G,5,FALSE) -> Teknik Informatika - Sistem Informasi & Information Management | CB44: =VLOOKUP($B44,Sheet1!$A:$G,6,FALSE) -> - | CC44: =VLOOKUP($B44,Sheet1!$A:$G,7,FALSE) -> 0 | CD44: Intergrated and Embedded Systems | CE44: Rekayasa Industri dan Inovasi Bisnis (RIIB)
A45: 53 | B45: Helisyah Nur Fadhilah | C45: Non-Aktif | D45: Sains Data | E45: 23950026 | F45: 0707019501 | G45: 9439773674230232 | H45: TETAP | I45: Dr. | J45: S.Si., M.Mat. | K45: AA.3 | L45: AA | M45: =IF(L45="NJAD","AA",IF(L45="AA","L",IF(L45="L","LK","GB"))) -> L | N45: - | O45: 150 | P45: Kalkulus 1B, Kalkulus 2B, Kecerdasan Buatan dan Matematika Teknik 2 | Q45: 45047 | R45: =DATEDIF(Q45,TODAY(), "Y") & " Tahun " & DATEDIF(Q45, TODAY(), "YM") & " Bulan" -> 2 Tahun 8 Bulan | S45: Penata Muda Tk. I Golongan III/b | T45: 45170 | U45: =DATEDIF(T45,TODAY(), "Y") & " Tahun " & DATEDIF(T45, TODAY(), "YM") & " Bulan" -> 2 Tahun 4 Bulan | V45: Dosen S1 Sains Data | W45: DOSEN | X45: =IF(AND(OR(L45="AA",L45="L"),OR(S45="Penata Muda Tk. I Golongan III/b",S45="Penata Golongan III/c"),DATEDIF(Q45,TODAY(),"m")>=23,ISBLANK(Z45),C45="Aktif"),"Nominasi Serdos","-") -> - | AC45: - | AH45: S3 | AM45: 44166 | AN45: =DATEDIF(AM45,TODAY(),"y")&" tahun "&DATEDIF(AM45,TODAY(),"ym")&" bulan " -> 5 tahun 1 bulan | AO45: FTIB | AP45: Program Studi S1 Sains Data (FTIB) | AQ45: HNF | AR45: helisyah07@ittelkom-sby.ac.id | AS45: 82131281868 | AT45: Jl. R.A. Kartini 1-A/21, Gresik | AW45: =VLOOKUP(B45,Sheet2!A54:I171,9,FALSE) -> Dr. Helisyah Nur Fadhilah, S.Si., M.Mat. | AX45: Perempuan | AY45: =VLOOKUP(B45,Sheet2!A54:C171,2,FALSE) -> Gresik | AZ45: =VLOOKUP(B45,Sheet2!A54:C171,3,FALSE) -> 34881 | BA45: =DATEDIF(AZ45, TODAY(),"y") -> 30 | BL45: =VLOOKUP(B45,Sheet2!A54:D171,4,FALSE) -> Dosen | BR45: =VLOOKUP(B45,Sheet2!A54:E171,5,FALSE) -> Data Science and Intelligent Systems (DSIS) | BS45: =VLOOKUP(B45,Sheet2!A54:F171,6,FALSE) -> HEF | BT45: =VLOOKUP(B45,Sheet2!A54:G171,7,FALSE) -> Fakultas Informatika | BU45: =VLOOKUP(B45,Sheet2!A54:H171,8,FALSE) -> helisyahnf@telkomuniversity.ac.id | BV45: =COUNTIFS('Join TPA Dosen'!B:B,Dosen!B54) -> 1 | BW45: =DATEDIF(AM45,DATE(2026,1,1),"y")&" tahun "&DATEDIF(AM45,DATE(2026,1,1),"ym")&" bulan " -> 5 tahun 1 bulan | BX45: =VLOOKUP($B45,Sheet1!$A:$G,2,FALSE) -> ITS | BY45: =VLOOKUP($B45,Sheet1!$A:$G,3,FALSE) -> Matematika dan Ilmu Pengatahuan Alam/Matematika | BZ45: =VLOOKUP($B45,Sheet1!$A:$G,4,FALSE) -> ITS | CA45: =VLOOKUP($B45,Sheet1!$A:$G,5,FALSE) -> Matematika, Komputasi, dan Sains Data/Matematika | CB45: =VLOOKUP($B45,Sheet1!$A:$G,6,FALSE) -> ITS | CC45: =VLOOKUP($B45,Sheet1!$A:$G,7,FALSE) -> Sains dan Analitika Data/Matematika | CD45: #N/A | CE45: #N/A
A46: 54 | B46: Moh. Hamim Zajuli Al Faroby | C46: Aktif | D46: Sains Data | E46: 23950023 | F46: 0724079501 | G46: 3056773674130233 | H46: TETAP | J46: S.Si., M.Mat. | K46: L.2 | L46: L | M46: =IF(L46="NJAD","AA",IF(L46="AA","L",IF(L46="L","LK","GB"))) -> LK | O46: 200 | P46: Algoritma dan Pemrograman, Teori Probabilitas, Matriks dan Vektor dan Statika Industri | Q46: 45931 | R46: =DATEDIF(Q46,TODAY(), "Y") & " Tahun " & DATEDIF(Q46, TODAY(), "YM") & " Bulan" -> 0 Tahun 3 Bulan | S46: Penata Golongan III/c | T46: 46023 | U46: =DATEDIF(T46,TODAY(), "Y") & " Tahun " & DATEDIF(T46, TODAY(), "YM") & " Bulan" -> 0 Tahun 0 Bulan | V46: Kaprodi S1 Sains Data | W46: DOSEN | X46: =IF(AND(OR(L46="AA",L46="L"),OR(S46="Penata Muda Tk. I Golongan III/b",S46="Penata Golongan III/c"),DATEDIF(Q46,TODAY(),"m")>=23,ISBLANK(Z46),C46="Aktif"),"Nominasi Serdos","-") -> - | Z46: Punya | AA46: 25104105713496 | AB46: 25-001008-0130 | AC46: 45917 | AH46: S2 | AI46: Ya | AJ46: TB | AK46: Ya | AL46: On Progress S3 TB | AM46: 44166 | AN46: =DATEDIF(AM46,TODAY(),"y")&" tahun "&DATEDIF(AM46,TODAY(),"ym")&" bulan " -> 5 tahun 1 bulan | AO46: FTIB | AP46: Program Studi S1 Sains Data (FTIB) | AQ46: HMM | AR46: alfaroby@ittelkom-sby.ac.id | AS46: 81331653603 | AT46: Dsn. Krajan, Gladag, Rogojampi, Banyuwangi | AW46: =VLOOKUP(B46,Sheet2!A55:I172,9,FALSE) -> Moh. Hamim Zajuli Al Faroby, S.Si., M.Mat. | AX46: Laki-laki | AY46: =VLOOKUP(B46,Sheet2!A55:C172,2,FALSE) -> Banyuwangi | AZ46: =VLOOKUP(B46,Sheet2!A55:C172,3,FALSE) -> 34904 | BA46: =DATEDIF(AZ46, TODAY(),"y") -> 30 | BL46: =VLOOKUP(B46,Sheet2!A55:D172,4,FALSE) -> Kaprodi | BR46: =VLOOKUP(B46,Sheet2!A55:E172,5,FALSE) -> Data Science and Intelligent Systems (DSIS) | BS46: =VLOOKUP(B46,Sheet2!A55:F172,6,FALSE) -> OBY | BT46: =VLOOKUP(B46,Sheet2!A55:G172,7,FALSE) -> Fakultas Informatika | BU46: =VLOOKUP(B46,Sheet2!A55:H172,8,FALSE) -> alfarobymhz@telkomuniversity.ac.id | BV46: =COUNTIFS('Join TPA Dosen'!B:B,Dosen!B55) -> 1 | BW46: =DATEDIF(AM46,DATE(2026,1,1),"y")&" tahun "&DATEDIF(AM46,DATE(2026,1,1),"ym")&" bulan " -> 5 tahun 1 bulan | BX46: =VLOOKUP($B46,Sheet1!$A:$G,2,FALSE) -> ITS | BY46: =VLOOKUP($B46,Sheet1!$A:$G,3,FALSE) -> Matematika, Komputasi, dan Sains Data/Matematika | BZ46: =VLOOKUP($B46,Sheet1!$A:$G,4,FALSE) -> ITS | CA46: =VLOOKUP($B46,Sheet1!$A:$G,5,FALSE) -> Sains dan Analitika Data/Matematika | CB46: =VLOOKUP($B46,Sheet1!$A:$G,6,FALSE) -> - | CC46: =VLOOKUP($B46,Sheet1!$A:$G,7,FALSE) -> 0 | CD46: Motion Technology for Safety, Health, and Wellness | CE46: Smart Computing Technology (SCOUT)
A47: 63 | B47: Purnama Anaking | C47: Aktif | D47: Sistem Informasi | E47: 21870007 | F47: 0724098701 | G47: 0256765666130223 | H47: PROFESIONAL | J47: S.Kom., M.Kom. | K47: NJAD.2 | L47: NJAD | M47: =IF(L47="NJAD","AA",IF(L47="AA","L",IF(L47="L","LK","GB"))) -> AA | N47: - | O47: 0 | Q47: 44562 | R47: =DATEDIF(Q47,TODAY(), "Y") & " Tahun " & DATEDIF(Q47, TODAY(), "YM") & " Bulan" -> 4 Tahun 0 Bulan | S47: - | T47: - | U47: =DATEDIF(T47,TODAY(), "Y") & " Tahun " & DATEDIF(T47, TODAY(), "YM") & " Bulan" -> #VALUE! | V47: Dosen S1 Sistem Informasi | W47: DOSEN | X47: =IF(AND(OR(L47="AA",L47="L"),OR(S47="Penata Muda Tk. I Golongan III/b",S47="Penata Golongan III/c"),DATEDIF(Q47,TODAY(),"m")>=23,ISBLANK(Z47),C47="Aktif"),"Nominasi Serdos","-") -> - | AC47: - | AH47: S2 | AM47: 44562 | AN47: =DATEDIF(AM47,TODAY(),"y")&" tahun "&DATEDIF(AM47,TODAY(),"ym")&" bulan " -> 4 tahun 0 bulan | AO47: FTIB | AP47: Program Studi S1 Sistem Informasi (FTIB) | AQ47: PUR | AR47: purnama.anaking@ittelkom-sby.ac.id | AS47: 81239428683 | AT47: Jl. Semampir Tengah 9 / 5D Surabaya | AW47: =VLOOKUP(B47,Sheet2!A64:I181,9,FALSE) -> Purnama Anaking, S.Kom., M.Kom. | AX47: Laki-laki | AY47: =VLOOKUP(B47,Sheet2!A64:C181,2,FALSE) -> Jakarta | AZ47: =VLOOKUP(B47,Sheet2!A64:C181,3,FALSE) -> 32044 | BA47: =DATEDIF(AZ47, TODAY(),"y") -> 38 | BL47: =VLOOKUP(B47,Sheet2!A64:D181,4,FALSE) -> Dosen | BR47: =VLOOKUP(B47,Sheet2!A64:E181,5,FALSE) -> Cybernetics | BS47: =VLOOKUP(B47,Sheet2!A64:F181,6,FALSE) -> PAK | BT47: =VLOOKUP(B47,Sheet2!A64:G181,7,FALSE) -> Fakultas Rekayasa Industri | BU47: =VLOOKUP(B47,Sheet2!A64:H181,8,FALSE) -> purnamaanaking@telkomuniversity.ac.id | BV47: =COUNTIFS('Join TPA Dosen'!B:B,Dosen!B64) -> 1 | BW47: =DATEDIF(AM47,DATE(2026,1,1),"y")&" tahun "&DATEDIF(AM47,DATE(2026,1,1),"ym")&" bulan " -> 4 tahun 0 bulan | BX47: =VLOOKUP($B47,Sheet1!$A:$G,2,FALSE) -> ITS | BY47: =VLOOKUP($B47,Sheet1!$A:$G,3,FALSE) -> Sistem Informasi | BZ47: =VLOOKUP($B47,Sheet1!$A:$G,4,FALSE) -> ITS | CA47: =VLOOKUP($B47,Sheet1!$A:$G,5,FALSE) -> Sistem Informasi | CB47: =VLOOKUP($B47,Sheet1!$A:$G,6,FALSE) -> - | CC47: =VLOOKUP($B47,Sheet1!$A:$G,7,FALSE) -> 0 | CD47: Motion Technology for Safety, Health, and Wellness | CE47: Smart Computing Technology (SCOUT)
A48: 64 | B48: Arrizky Ayu Faradila Purnama | C48: Aktif | D48: Teknik Telekomunikasi | E48: 22960009 | F48: 0714029601 | G48: 9546774675230212 | H48: PROFESIONAL | J48: S.T., M.T. | K48: NJAD.2 | L48: NJAD | M48: =IF(L48="NJAD","AA",IF(L48="AA","L",IF(L48="L","LK","GB"))) -> AA | N48: - | O48: 0 | Q48: 44627 | R48: =DATEDIF(Q48,TODAY(), "Y") & " Tahun " & DATEDIF(Q48, TODAY(), "YM") & " Bulan" -> 3 Tahun 10 Bulan | S48: - | T48: - | U48: =DATEDIF(T48,TODAY(), "Y") & " Tahun " & DATEDIF(T48, TODAY(), "YM") & " Bulan" -> #VALUE! | V48: Dosen S1 T. Telekomunikasi | W48: DOSEN | X48: =IF(AND(OR(L48="AA",L48="L"),OR(S48="Penata Muda Tk. I Golongan III/b",S48="Penata Golongan III/c"),DATEDIF(Q48,TODAY(),"m")>=23,ISBLANK(Z48),C48="Aktif"),"Nominasi Serdos","-") -> - | AC48: - | AH48: S2 | AM48: 44627 | AN48: =DATEDIF(AM48,TODAY(),"y")&" tahun "&DATEDIF(AM48,TODAY(),"ym")&" bulan " -> 3 tahun 10 bulan | AO48: FTEIC | AP48: Program Studi S1 T. Telekomunikasi (FTEIC) | AQ48: AAF | AR48: arrzkyafp@ittelkom-sby.ac.id | AS48: 82116869268 | AT48: Jl. Soekarno Hatta, RT/RW 005/002, Gg. Rambutan, Kelutan, Trenggalek | AW48: =VLOOKUP(B48,Sheet2!A65:I182,9,FALSE) -> Arrizky Ayu Faradila Purnama, S.T., M.T. | AX48: Perempuan | AY48: =VLOOKUP(B48,Sheet2!A65:C182,2,FALSE) -> Trenggalek | AZ48: =VLOOKUP(B48,Sheet2!A65:C182,3,FALSE) -> 35109 | BA48: =DATEDIF(AZ48, TODAY(),"y") -> 29 | BL48: =VLOOKUP(B48,Sheet2!A65:D182,4,FALSE) -> Dosen | BR48: =VLOOKUP(B48,Sheet2!A65:E182,5,FALSE) -> Intelligent Communications and Networks (ICON) | BS48: =VLOOKUP(B48,Sheet2!A65:F182,6,FALSE) -> KYA | BT48: =VLOOKUP(B48,Sheet2!A65:G182,7,FALSE) -> Fakultas Teknik Elektro | BU48: =VLOOKUP(B48,Sheet2!A65:H182,8,FALSE) -> kyafara@telkomuniversity.ac.id | BV48: =COUNTIFS('Join TPA Dosen'!B:B,Dosen!B65) -> 1 | BW48: =DATEDIF(AM48,DATE(2026,1,1),"y")&" tahun "&DATEDIF(AM48,DATE(2026,1,1),"ym")&" bulan " -> 3 tahun 9 bulan | BX48: =VLOOKUP($B48,Sheet1!$A:$G,2,FALSE) -> Tel-U | BY48: =VLOOKUP($B48,Sheet1!$A:$G,3,FALSE) -> Teknik Telekomunikasi | BZ48: =VLOOKUP($B48,Sheet1!$A:$G,4,FALSE) -> Tel-U | CA48: =VLOOKUP($B48,Sheet1!$A:$G,5,FALSE) -> Teknik Elektro | CB48: =VLOOKUP($B48,Sheet1!$A:$G,6,FALSE) -> - | CC48: =VLOOKUP($B48,Sheet1!$A:$G,7,FALSE) -> 0 | CD48: Motion Technology for Safety, Health, and Wellness | CE48: ETHES (Electrical Engineering and Advanced Technologies)
